Workbook
Name Cellule_1000: 'T4 B2-immo'!$D$18
Name Cellule_1001: 'T4 B2-immo'!$D$21
Name Cellule_1002: 'T4 B2-immo'!$D$22
Name Cellule_10022: 'T15 Encourag'!$C$28
Name Cellule_10023: 'T15 Encourag'!$C$29
Name Cellule_10024: 'T15 Encourag'!$D$28
Name Cellule_10025: 'T15 Encourag'!$D$29
Name Cellule_10026: 'T15 Encourag'!$E$28
Name Cellule_10027: 'T15 Encourag'!$E$29
Name Cellule_10028: 'T15 Encourag'!$E$21
Name Cellule_10029: 'T15 Encourag'!$E$22
Name Cellule_1003: 'T4 B2-immo'!$D$23
Name Cellule_1004: 'T4 B2-immo'!$D$24
Name Cellule_10040: 'T15 Encourag'!$C$21
Name Cellule_10041: 'T15 Encourag'!$C$22
Name Cellule_10042: 'T15 Encourag'!$D$21
Name Cellule_10043: 'T15 Encourag'!$D$22
Name Cellule_1005: 'T4 B2-immo'!$D$27
Name Cellule_1006: 'T4 B2-immo'!$D$25
Name Cellule_10061_1: 'T16 Amort'!$A$24
Name Cellule_10061_10: 'T16 Amort'!$A$33
Name Cellule_10061_2: 'T16 Amort'!$A$25
Name Cellule_10061_3: 'T16 Amort'!$A$26
Name Cellule_10061_4: 'T16 Amort'!$A$27
Name Cellule_10061_5: 'T16 Amort'!$A$28
Name Cellule_10061_6: 'T16 Amort'!$A$29
Name Cellule_10061_7: 'T16 Amort'!$A$30
Name Cellule_10061_8: 'T16 Amort'!$A$31
Name Cellule_10061_9: 'T16 Amort'!$A$32
Name Cellule_10064: 'T4 B2-immo'!$B$9
Name Cellule_10065: 'T4 B2-immo'!$C$9
Name Cellule_10066: 'T4 B2-immo'!$D$9
Name Cellule_10067: 'T4 B2-immo'!$E$9
Name Cellule_10068: 'T4 B2-immo'!$F$9
Name Cellule_10069: 'T4 B2-immo'!$G$9
Name Cellule_1007: 'T4 B2-immo'!$D$26
Name Cellule_10070: 'T4 B2-immo'!$H$9
Name Cellule_10071: 'T4 B2-immo'!$I$9
Name Cellule_10073: 'T4 B2-immo'!$B$14
Name Cellule_10074: 'T4 B2-immo'!$C$14
Name Cellule_10075: 'T4 B2-immo'!$D$14
Name Cellule_10076: 'T4 B2-immo'!$E$14
Name Cellule_10077: 'T4 B2-immo'!$F$14
Name Cellule_10078: 'T4 B2-immo'!$G$14
Name Cellule_10079: 'T4 B2-immo'!$H$14
Name Cellule_1008: 'T4 B2-immo'!$E$10
Name Cellule_10080: 'T4 B2-immo'!$I$14
Name Cellule_10082: 'T4 B2-immo'!$B$20
Name Cellule_10083: 'T4 B2-immo'!$C$20
Name Cellule_10084: 'T4 B2-immo'!$D$20
Name Cellule_10085: 'T4 B2-immo'!$E$20
Name Cellule_10086: 'T4 B2-immo'!$F$20
Name Cellule_10087: 'T4 B2-immo'!$G$20
Name Cellule_10088: 'T4 B2-immo'!$H$20
Name Cellule_10089: 'T4 B2-immo'!$I$20
Name Cellule_1009: 'T4 B2-immo'!$E$11
Name Cellule_10091: 'T6 TB11'!$D$28
Name Cellule_1010: 'T4 B2-immo'!$E$12
Name Cellule_1011: 'T4 B2-immo'!$E$15
Name Cellule_1012: 'T4 B2-immo'!$E$16

Sheet Feuil1
A12: Identification société
H15: T 5 : ESG

Sheet Identification
A7: Dénomination sociale | B7: CLUB DE COMPTA
A9: Siège social | B9: MAROC
A11: Exercice social | B11: du | C11: 44562 | D11: au | E11: 31/12/2022
A13: IF | C13: 7777777
A15: TP
A17: RC | C17: 7777

Sheet Couverture Etats de synthèse
B7: Etats de synthèse
A13: DECLARATION AU TITRE DE L'ANNEE
B15: Du | C15: =Identification!C11 -> 44562 | D15: Au | E15: =Identification!E11 -> 31/12/2022
A21: Raison sociale : | C21: =Identification!B7 -> CLUB DE COMPTA
A23: Article I.F. | F23: =Identification!C13 -> 7777777
A27: Adresse : | C27: =Identification!B9 -> MAROC
A31: R.C. n° | C31: =Identification!C17 -> 7777
A32: Taxe Professionnelle n° | C32: =Identification!C15 -> 0
E36: A ………………… Le …/…/……..
E38: Signature
A44: CADRE RESERVE A L'ADMINISTRATION
A46: Numéro d'Enregistrement de la Déclaration : .............................................
A48: Date : ...................................................
E49: Signature
A54: N.B. : Les tableaux de 1 à 14 sont conformes aux états prévus par la loi n° 9-88 relative aux obligations
A55: comptables des commerçants promulguée par le Dahir n° 1,92,138 du 3 Joumada II 1413 (15,12,1992)

Sheet Couverture
L1: Modèle 100/IS/N
A4: PIECES ANNEXES A LA
A5: DECLARATION FISCALE
A7: IMPOT SUR LES SOCIETES
A9: (Modèle Comptable Normal)
A13: DECLARATION AU TITRE DE L'ANNEE
B15: Du | C15: =Identification!C11 -> 44562 | D15: Au | E15: =Identification!E11 -> 31/12/2022
A21: Raison sociale : | C21: =Identification!B7 -> CLUB DE COMPTA
A23: Article I.F. | F23: =Identification!B7 -> CLUB DE COMPTA
A27: Adresse : | B27: =Identification!B9 -> MAROC
A31: R.C. n° | B31: =Identification!C17 -> 7777
A32: Taxe Professionnelle n° | B32: =Identification!C15 -> 0
E36: ='Couverture Etats de synthèse'!E36 -> A ………………… Le …/…/……..
E38: Signature
A44: CADRE RESERVE A L'ADMINISTRATION
A46: Numéro d'Enregistrement de la Déclaration : .............................................
A48: Date : ...................................................
E49: Signature
A54: N.B. : Les tableaux de 1 à 14 sont conformes aux états prévus par la loi n° 9-88 relative aux obligations
A55: comptables des commerçants promulguée par le Dahir n° 1,92,138 du 3 Joumada II 1413 (15,12,1992)

Sheet Programme
A1: N° Odre | B1: Tableau | C1: A | D1: B | E1: C | F1: D | G1: E | H1: F | I1: G
A2: 1 | B2: PG | C2: <?xml version="1.0" encoding="utf-8"?>
A3: =+A2+1 -> 2 | B3: PG | C3: <Liasse>
A4: =+A3+1 -> 3 | B4: PG | D4: <modele>
A5: =+A4+1 -> 4 | B5: PG | E5: <id>1</id>
A6: =+A5+1 -> 5 | B6: PG | D6: </modele>
A7: =+A6+1 -> 6 | B7: PG | D7: <resultatFiscal>
A8: =+A7+1 -> 7 | B8: PG | D8: =CONCATENATE("<identifiantFiscal>",Identification!C13,"</identifiantFiscal>") -> <identifiantFiscal>7777777</identifiantFiscal>
A9: =+A8+1 -> 8 | B9: PG | E9: =CONCATENATE("<exerciceFiscalDu>",CONCATENATE(YEAR(Identification!C11),"-0",MONTH(Identification!C11),"-0",DAY(Identification!C11)),"</exerciceFiscalDu>") -> <exerciceFiscalDu>2022-01-01</exerciceFiscalDu>
A10: =+A9+1 -> 9 | B10: PG | E10: =CONCATENATE("<exerciceFiscalAu>",CONCATENATE(YEAR(Identification!E11),"-",MONTH(Identification!E11),"-",DAY(Identification!E11)),"</exerciceFiscalAu>") -> <exerciceFiscalAu>2022-12-31</exerciceFiscalAu>
A11: =+A10+1 -> 10 | B11: PG | D11: </resultatFiscal>
A12: =+A11+1 -> 11 | B12: PG | D12: <!-- Partie 2 : Liasse Fiscale -->
A13: =+A12+1 -> 12 | B13: PG | D13: <!-- Les valeurs de chaque tableau de la liasse -->
A14: =+A13+1 -> 13 | B14: PG | D14: <groupeValeursTableau>
A15: =+A14+1 -> 14 | B15: PG | E15: <ValeursTableau>
A16: =+A15+1 -> 15 | B16: T01 Actif | F16: <tableau><id>2</id></tableau>
A17: =+A16+1 -> 16 | B17: T01 Actif | F17: <groupeValeurs>
A18: =+A17+1 -> 17 | B18: T01 Actif | G18: <ValeurCellule>
A19: =+A18+1 -> 18 | B19: T01 Actif | H19: <cellule>
A20: =+A19+1 -> 19 | B20: T01 Actif | I20: <codeEdi>238</codeEdi>
A21: =+A20+1 -> 20 | B21: T01 Actif | H21: </cellule>
A22: =+A21+1 -> 21 | B22: T01 Actif | H22: =CONCATENATE("<valeur>",Cellule_238,"</valeur>") -> <valeur>5000</valeur>
A23: =+A22+1 -> 22 | B23: T01 Actif | G23: </ValeurCellule>
A24: =+A23+1 -> 23 | B24: T01 Actif | G24: <ValeurCellule>
A25: =+A24+1 -> 24 | B25: T01 Actif | H25: <cellule>
A26: =+A25+1 -> 25 | B26: T01 Actif | I26: <codeEdi>239</codeEdi>
A27: =+A26+1 -> 26 | B27: T01 Actif | H27: </cellule>
A28: =+A27+1 -> 27 | B28: T01 Actif | H28: =CONCATENATE("<valeur>",Cellule_239,"</valeur>") -> <valeur>0</valeur>
A29: =+A28+1 -> 28 | B29: T01 Actif | G29: </ValeurCellule>
A30: =+A29+1 -> 29 | B30: T01 Actif | G30: <ValeurCellule>
A31: =+A30+1 -> 30 | B31: T01 Actif | H31: <cellule>
A32: =+A31+1 -> 31 | B32: T01 Actif | I32: <codeEdi>240</codeEdi>
A33: =+A32+1 -> 32 | B33: T01 Actif | H33: </cellule>
A34: =+A33+1 -> 33 | B34: T01 Actif | H34: =CONCATENATE("<valeur>",Cellule_240,"</valeur>") -> <valeur>0</valeur>
A35: =+A34+1 -> 34 | B35: T01 Actif | G35: </ValeurCellule>
A36: =+A35+1 -> 35 | B36: T01 Actif | G36: <ValeurCellule>
A37: =+A36+1 -> 36 | B37: T01 Actif | H37: <cellule>
A38: =+A37+1 -> 37 | B38: T01 Actif | I38: <codeEdi>497</codeEdi>
A39: =+A38+1 -> 38 | B39: T01 Actif | H39: </cellule>
A40: =+A39+1 -> 39 | B40: T01 Actif | H40: =CONCATENATE("<valeur>",Cellule_497,"</valeur>") -> <valeur>5000</valeur>
A41: =+A40+1 -> 40 | B41: T01 Actif | G41: </ValeurCellule>
A42: =+A41+1 -> 41 | B42: T01 Actif | G42: <ValeurCellule>
A43: =+A42+1 -> 42 | B43: T01 Actif | H43: <cellule>
A44: =+A43+1 -> 43 | B44: T01 Actif | I44: <codeEdi>241</codeEdi>
A45: =+A44+1 -> 44 | B45: T01 Actif | H45: </cellule>
A46: =+A45+1 -> 45 | B46: T01 Actif | H46: =CONCATENATE("<valeur>",Cellule_241,"</valeur>") -> <valeur>2360,87</valeur>
A47: =+A46+1 -> 46 | B47: T01 Actif | G47: </ValeurCellule>
A48: =+A47+1 -> 47 | B48: T01 Actif | G48: <ValeurCellule>
A49: =+A48+1 -> 48 | B49: T01 Actif | H49: <cellule>
A50: =+A49+1 -> 49 | B50: T01 Actif | I50: <codeEdi>242</codeEdi>
A51: =+A50+1 -> 50 | B51: T01 Actif | H51: </cellule>
A52: =+A51+1 -> 51 | B52: T01 Actif | H52: =CONCATENATE("<valeur>",Cellule_242,"</valeur>") -> <valeur>0</valeur>
A53: =+A52+1 -> 52 | B53: T01 Actif | G53: </ValeurCellule>
A54: =+A53+1 -> 53 | B54: T01 Actif | G54: <ValeurCellule>
A55: =+A54+1 -> 54 | B55: T01 Actif | H55: <cellule>
A56: =+A55+1 -> 55 | B56: T01 Actif | I56: <codeEdi>243</codeEdi>
A57: =+A56+1 -> 56 | B57: T01 Actif | H57: </cellule>
A58: =+A57+1 -> 57 | B58: T01 Actif | H58: =CONCATENATE("<valeur>",Cellule_243,"</valeur>") -> <valeur>0</valeur>
A59: =+A58+1 -> 58 | B59: T01 Actif | G59: </ValeurCellule>
A60: =+A59+1 -> 59 | B60: T01 Actif | G60: <ValeurCellule>
A61: =+A60+1 -> 60 | B61: T01 Actif | H61: <cellule>
A62: =+A61+1 -> 61 | B62: T01 Actif | I62: <codeEdi>498</codeEdi>
A63: =+A62+1 -> 62 | B63: T01 Actif | H63: </cellule>
A64: =+A63+1 -> 63 | B64: T01 Actif | H64: =CONCATENATE("<valeur>",Cellule_498,"</valeur>") -> <valeur>2360,87</valeur>
A65: =+A64+1 -> 64 | B65: T01 Actif | G65: </ValeurCellule>
A66: =+A65+1 -> 65 | B66: T01 Actif | G66: <ValeurCellule>
A67: =+A66+1 -> 66 | B67: T01 Actif | H67: <cellule>
A68: =+A67+1 -> 67 | B68: T01 Actif | I68: <codeEdi>244</codeEdi>
A69: =+A68+1 -> 68 | B69: T01 Actif | H69: </cellule>
A70: =+A69+1 -> 69 | B70: T01 Actif | H70: =CONCATENATE("<valeur>",Cellule_244,"</valeur>") -> <valeur>2639,13</valeur>
A71: =+A70+1 -> 70 | B71: T01 Actif | G71: </ValeurCellule>
A72: =+A71+1 -> 71 | B72: T01 Actif | G72: <ValeurCellule>
A73: =+A72+1 -> 72 | B73: T01 Actif | H73: <cellule>
A74: =+A73+1 -> 73 | B74: T01 Actif | I74: <codeEdi>245</codeEdi>
A75: =+A74+1 -> 74 | B75: T01 Actif | H75: </cellule>
A76: =+A75+1 -> 75 | B76: T01 Actif | H76: =CONCATENATE("<valeur>",Cellule_245,"</valeur>") -> <valeur>0</valeur>
A77: =+A76+1 -> 76 | B77: T01 Actif | G77: </ValeurCellule>
A78: =+A77+1 -> 77 | B78: T01 Actif | G78: <ValeurCellule>
A79: =+A78+1 -> 78 | B79: T01 Actif | H79: <cellule>
A80: =+A79+1 -> 79 | B80: T01 Actif | I80: <codeEdi>246</codeEdi>
A81: =+A80+1 -> 80 | B81: T01 Actif | H81: </cellule>
A82: =+A81+1 -> 81 | B82: T01 Actif | H82: =CONCATENATE("<valeur>",Cellule_246,"</valeur>") -> <valeur>0</valeur>
A83: =+A82+1 -> 82 | B83: T01 Actif | G83: </ValeurCellule>
A84: =+A83+1 -> 83 | B84: T01 Actif | G84: <ValeurCellule>
A85: =+A84+1 -> 84 | B85: T01 Actif | H85: <cellule>
A86: =+A85+1 -> 85 | B86: T01 Actif | I86: <codeEdi>499</codeEdi>
A87: =+A86+1 -> 86 | B87: T01 Actif | H87: </cellule>
A88: =+A87+1 -> 87 | B88: T01 Actif | H88: =CONCATENATE("<valeur>",Cellule_499,"</valeur>") -> <valeur>2639,13</valeur>
A89: =+A88+1 -> 88 | B89: T01 Actif | G89: </ValeurCellule>
A90: =+A89+1 -> 89 | B90: T01 Actif | G90: <ValeurCellule>
A91: =+A90+1 -> 90 | B91: T01 Actif | H91: <cellule>
A92: =+A91+1 -> 91 | B92: T01 Actif | I92: <codeEdi>247</codeEdi>
A93: =+A92+1 -> 92 | B93: T01 Actif | H93: </cellule>
A94: =+A93+1 -> 93 | B94: T01 Actif | H94: =CONCATENATE("<valeur>",Cellule_247,"</valeur>") -> <valeur>4305,63</valeur>
A95: =+A94+1 -> 94 | B95: T01 Actif | G95: </ValeurCellule>
A96: =+A95+1 -> 95 | B96: T01 Actif | G96: <ValeurCellule>
A97: =+A96+1 -> 96 | B97: T01 Actif | H97: <cellule>
A98: =+A97+1 -> 97 | B98: T01 Actif | I98: <codeEdi>248</codeEdi>
A99: =+A98+1 -> 98 | B99: T01 Actif | H99: </cellule>
A100: =+A99+1 -> 99 | B100: T01 Actif | H100: =CONCATENATE("<valeur>",Cellule_248,"</valeur>") -> <valeur>0</valeur>
...

Sheet Xml
A1: =CONCATENATE(Programme!C2,Programme!D2,Programme!E2,Programme!F2,Programme!G2,Programme!H2,Programme!I2) -> <?xml version="1.0" encoding="utf-8"?>
A2: =CONCATENATE(Programme!C3,Programme!D3,Programme!E3,Programme!F3,Programme!G3,Programme!H3,Programme!I3) -> <Liasse>
A3: =CONCATENATE(Programme!C4,Programme!D4,Programme!E4,Programme!F4,Programme!G4,Programme!H4,Programme!I4) -> <modele>
A4: =CONCATENATE(Programme!C5,Programme!D5,Programme!E5,Programme!F5,Programme!G5,Programme!H5,Programme!I5) -> <id>1</id>
A5: =CONCATENATE(Programme!C6,Programme!D6,Programme!E6,Programme!F6,Programme!G6,Programme!H6,Programme!I6) -> </modele>
A6: =CONCATENATE(Programme!C7,Programme!D7,Programme!E7,Programme!F7,Programme!G7,Programme!H7,Programme!I7) -> <resultatFiscal>
A7: =CONCATENATE(Programme!C8,Programme!D8,Programme!E8,Programme!F8,Programme!G8,Programme!H8,Programme!I8) -> <identifiantFiscal>7777777</identifiantFiscal>
A8: =CONCATENATE(Programme!C9,Programme!D9,Programme!E9,Programme!F9,Programme!G9,Programme!H9,Programme!I9) -> <exerciceFiscalDu>2022-01-01</exerciceFiscalDu>
A9: =CONCATENATE(Programme!C10,Programme!D10,Programme!E10,Programme!F10,Programme!G10,Programme!H10,Programme!I10) -> <exerciceFiscalAu>2022-12-31</exerciceFiscalAu>
A10: =CONCATENATE(Programme!C11,Programme!D11,Programme!E11,Programme!F11,Programme!G11,Programme!H11,Programme!I11) -> </resultatFiscal>
A11: =CONCATENATE(Programme!C12,Programme!D12,Programme!E12,Programme!F12,Programme!G12,Programme!H12,Programme!I12) -> <!-- Partie 2 : Liasse Fiscale -->
A12: =CONCATENATE(Programme!C13,Programme!D13,Programme!E13,Programme!F13,Programme!G13,Programme!H13,Programme!I13) -> <!-- Les valeurs de chaque tableau de la liasse -->
... A11738: =CONCATENATE(Programme!C11739,Programme!D11739,Programme!E11739,Programme!F11739,Programme!G11739,Programme!H11739,Programme!I11739) -> </Liasse>

Sheet Balance N
A1: Compte | B1: Libellé | C1: Débit Période N | D1: Crédit Période N | E1: Solde Débit N | F1: Solde Crédit N
A2: 11110000 | B2: CAPITAL | C2: 0 | D2: 100000 | E2: 0 | F2: 100000
A3: 11690000 | B3: ANV DEBITEUR | C3: 18918.67 | D3: 0 | E3: 18918.67 | F3: 0
A4: 14810000 | B4: WAFASALAF | C4: 93239.76 | D4: 928651.92 | E4: 0 | F4: 835412.16
A5: 14810100 | B5: RCI FIN | C5: 11938.55 | D5: 100000 | E5: 0 | F5: 88061.45
A6: 14820300 | B6: SOFAC CREDIT | C6: 0 | D6: 81942 | E6: 0 | F6: 81942
A7: 21110000 | B7: Frais constitution | C7: 5000 | D7: 0 | E7: 5000 | F7: 0
A8: 23232000 | B8: MATERIEL ET OUTILLAGE | C8: 9700 | D8: 0 | E8: 9700 | F8: 0
A9: 23400000 | B9: MATRIEL DE TRANSPORT | C9: 1578827.6 | D9: 0 | E9: 1578827.6 | F9: 0
A10: 28110000 | B10: Amort frais constitution | C10: 0 | D10: 2360.87 | E10: 0 | F10: 2360.87
A11: 28322000 | B11: AMOT MATERIEL ET OULILLAGE | C11: 0 | D11: 1215 | E11: 0 | F11: 1215
A12: 28340000 | B12: AMPORT MAT DE TRANSP | C12: 0 | D12: 169962.26 | E12: 0 | F12: 169962.26
A13: 34110000 | B13: Frs avances et acompte | C13: 504198.25 | D13: 504198.25 | E13: 0 | F13: 0
... A32: 61455000 | B32: TELEPHONE | C32: 3306 | D32: 0 | E32: 3306 | F32: 0
A33: 61470000 | B33: frais bancaire | C33: =6139.91+1466.39 -> 7606.3 | D33: 0 | E33: 7606.3 | F33: 0
A34: 61610000 | B34: impot et taxes | C34: 17477 | D34: 0 | E34: 17477 | F34: 0
A35: 61673000 | B35: VIGNETTE | C35: 10710 | D35: 0 | E35: 10710 | F35: 0
A36: 61710000 | B36: SALAIRE BRUT | C36: 28731 | D36: 0 | E36: 28731 | F36: 0
A37: 61740000 | B37: COT P P | C37: 5445.55 | D37: 0 | E37: 5445.55 | F37: 0
A38: 61911000 | B38: DEA FRAIS CONSTITUTION | C38: 1666.5 | D38: 0 | E38: 1666.5 | F38: 0
A39: 61940000 | B39: AMORT MAT CORPORELLE | C39: 171177.26 | D39: 0 | E39: 171177.26 | F39: 0
A40: 63111000 | B40: INTERETS SUR EMPRUNETS | C40: 43957.11 | D40: 0 | E40: 43957.11 | F40: 0
A42: 67010000 | B42: IMPOT SUR LE BENIFICE | C42: 2384 | D42: 0 | E42: 2384 | F42: 0
A43: 71240000 | B43: vente prod prestation de services | C43: 0 | D43: 381666.67 | E43: 0 | F43: 381666.67
A44: 89000000 | B44: Bilan d'ouverture | C44: 18918.67 | D44: 18918.67 | E44: 0 | F44: 0

Sheet Balance N-1
A1: Compte | B1: Libellé | C1: Débit Période | D1: Crédit Période | E1: Débit Cumulé | F1: Crédit Cumulé | G1: Solde Cumulé
A2: 11110000 | B2: CAPITAL | C2: 0 | D2: 100000 | E2: 0 | F2: 100000
A3: 21110000 | B3: Frais constitution | C3: 5000 | D3: 0 | E3: 5000 | F3: 0
A4: 28110000 | B4: Amort frais constitution | C4: 0 | D4: 694.37 | E4: 0 | F4: 694.37
A5: 34550300 | B5: TVA10 % | C5: 34.53 | D5: 0 | E5: 34.53 | F5: 0
A6: 44320000 | B6: SALAIRE NET | C6: 10000 | D6: 10000 | E6: 0 | F6: 0
A7: 44410000 | B7: COT CNSS | C7: 1073 | D7: 2146 | E7: 0 | F7: 1073
A8: 44450000 | B8: COT AMO | C8: 318.5 | D8: 637 | E8: 0 | F8: 318.5
A9: 44525000 | B9: IR | C9: 0 | D9: 88 | E9: 0 | F9: 88
A10: 44630000 | B10: COMPTE COURANT D'ASSOCIE | C10: 340475.8 | D10: 574000.8 | E10: 0 | F10: 233525
A11: 51410000 | B11: ATTIJARIWAFA BANK | C11: 469000.8 | D11: 246155.13 | E11: 222845.67 | F11: 0
A12: 51610000 | B12: CAISSE | C12: 108900 | D12: 20000 | E12: 88900 | F12: 0
A13: 61312000 | B13: loyer | C13: 5000 | D13: 0 | E13: 5000 | F13: 0
... A17: 61911000 | B17: DEA FRAIS CONSTITUTION | C17: 694.37 | D17: 0 | E17: 694.37 | F17: 0

Sheet Balance N Retraitée
A1: Numero | B1: Libellé | C1: SD N-1 | D1: SC N-1 | E1: Débit Période | F1: Crédit Période | G1: SD N | H1: SC N | K1: Débit P. | L1: Crédit P. | M1: Solde
A2: =FIXED('Balance N'!A2,0,1) -> 11110000 | B2: =+'Balance N'!B2 -> CAPITAL | C2: =ROUND('Balance N'!#REF!,2) -> #REF! | D2: =ROUND('Balance N'!#REF!,2) -> #REF! | E2: =ROUND('Balance N'!C2,2) -> 0 | F2: =ROUND('Balance N'!D2,2) -> 100000 | G2: =ROUND('Balance N'!E2,2) -> 0 | H2: =ROUND('Balance N'!F2,2) -> 100000 | I2: =MID(A2,1,1) -> 1 | J2: 1 | K2: =SUMIF(I:I,J2,C:C) -> #REF! | L2: =SUMIF(I:I,J2,D:D) -> #REF! | M2: =+K2-L2 -> #REF! | N2: =+M2 -> #REF!
A3: =FIXED('Balance N'!A3,0,1) -> 11690000 | B3: =+'Balance N'!B3 -> ANV DEBITEUR | C3: =ROUND('Balance N'!#REF!,2) -> #REF! | D3: =ROUND('Balance N'!#REF!,2) -> #REF! | E3: =ROUND('Balance N'!C3,2) -> 18918.67 | F3: =ROUND('Balance N'!D3,2) -> 0 | G3: =ROUND('Balance N'!E3,2) -> 18918.67 | H3: =ROUND('Balance N'!F3,2) -> 0 | I3: =MID(A3,1,1) -> 1 | J3: 2 | K3: =SUMIF(I:I,J3,C:C) -> #REF! | L3: =SUMIF(I:I,J3,D:D) -> #REF! | M3: =+K3-L3 -> #REF! | N3: =+N2+M3 -> #REF!
A4: =FIXED('Balance N'!A4,0,1) -> 14810000 | B4: =+'Balance N'!B4 -> WAFASALAF | C4: =ROUND('Balance N'!#REF!,2) -> #REF! | D4: =ROUND('Balance N'!#REF!,2) -> #REF! | E4: =ROUND('Balance N'!C4,2) -> 93239.76 | F4: =ROUND('Balance N'!D4,2) -> 928651.92 | G4: =ROUND('Balance N'!E4,2) -> 0 | H4: =ROUND('Balance N'!F4,2) -> 835412.16 | I4: =MID(A4,1,1) -> 1 | J4: 3 | K4: =SUMIF(I:I,J4,C:C) -> #REF! | L4: =SUMIF(I:I,J4,D:D) -> #REF! | M4: =+K4-L4 -> #REF! | N4: =+N3+M4 -> #REF!
A5: =FIXED('Balance N'!A5,0,1) -> 14810100 | B5: =+'Balance N'!B5 -> RCI FIN | C5: =ROUND('Balance N'!#REF!,2) -> #REF! | D5: =ROUND('Balance N'!#REF!,2) -> #REF! | E5: =ROUND('Balance N'!C5,2) -> 11938.55 | F5: =ROUND('Balance N'!D5,2) -> 100000 | G5: =ROUND('Balance N'!E5,2) -> 0 | H5: =ROUND('Balance N'!F5,2) -> 88061.45 | I5: =MID(A5,1,1) -> 1 | J5: 4 | K5: =SUMIF(I:I,J5,C:C) -> #REF! | L5: =SUMIF(I:I,J5,D:D) -> #REF! | M5: =+K5-L5 -> #REF! | N5: =+N4+M5 -> #REF!
A6: =FIXED('Balance N'!A6,0,1) -> 14820300 | B6: =+'Balance N'!B6 -> SOFAC CREDIT | C6: =ROUND('Balance N'!#REF!,2) -> #REF! | D6: =ROUND('Balance N'!#REF!,2) -> #REF! | E6: =ROUND('Balance N'!C6,2) -> 0 | F6: =ROUND('Balance N'!D6,2) -> 81942 | G6: =ROUND('Balance N'!E6,2) -> 0 | H6: =ROUND('Balance N'!F6,2) -> 81942 | I6: =MID(A6,1,1) -> 1 | J6: 5 | K6: =SUMIF(I:I,J6,C:C) -> #REF! | L6: =SUMIF(I:I,J6,D:D) -> #REF! | M6: =+K6-L6 -> #REF! | N6: =+N5+M6 -> #REF! | O6: =SUM(K2:K6) -> #REF! | P6: =SUM(L2:L6) -> #REF! | Q6: =+O6-P6 -> #REF!
A7: =FIXED('Balance N'!A7,0,1) -> 21110000 | B7: =+'Balance N'!B7 -> Frais constitution | C7: =ROUND('Balance N'!#REF!,2) -> #REF! | D7: =ROUND('Balance N'!#REF!,2) -> #REF! | E7: =ROUND('Balance N'!C7,2) -> 5000 | F7: =ROUND('Balance N'!D7,2) -> 0 | G7: =ROUND('Balance N'!E7,2) -> 5000 | H7: =ROUND('Balance N'!F7,2) -> 0 | I7: =MID(A7,1,1) -> 2 | J7: 6 | K7: =SUMIF(I:I,J7,C:C) -> #REF! | L7: =SUMIF(I:I,J7,D:D) -> #REF! | M7: =+K7-L7 -> #REF! | N7: =M7 -> #REF!
A8: =FIXED('Balance N'!A8,0,1) -> 23232000 | B8: =+'Balance N'!B8 -> MATERIEL ET OUTILLAGE | C8: =ROUND('Balance N'!#REF!,2) -> #REF! | D8: =ROUND('Balance N'!#REF!,2) -> #REF! | E8: =ROUND('Balance N'!C8,2) -> 9700 | F8: =ROUND('Balance N'!D8,2) -> 0 | G8: =ROUND('Balance N'!E8,2) -> 9700 | H8: =ROUND('Balance N'!F8,2) -> 0 | I8: =MID(A8,1,1) -> 2 | J8: 7 | K8: =SUMIF(I:I,J8,C:C) -> #REF! | L8: =SUMIF(I:I,J8,D:D) -> #REF! | M8: =+K8-L8 -> #REF! | N8: =+N7+M8 -> #REF!
A9: =FIXED('Balance N'!A9,0,1) -> 23400000 | B9: =+'Balance N'!B9 -> MATRIEL DE TRANSPORT | C9: =ROUND('Balance N'!#REF!,2) -> #REF! | D9: =ROUND('Balance N'!#REF!,2) -> #REF! | E9: =ROUND('Balance N'!C9,2) -> 1578827.6 | F9: =ROUND('Balance N'!D9,2) -> 0 | G9: =ROUND('Balance N'!E9,2) -> 1578827.6 | H9: =ROUND('Balance N'!F9,2) -> 0 | I9: =MID(A9,1,1) -> 2 | J9: 8 | K9: =SUMIF(I:I,J9,C:C) -> #REF! | L9: =SUMIF(I:I,J9,D:D) -> #REF! | M9: =+K9-L9 -> #REF! | O9: =SUM(K7:K9) -> #REF! | P9: =SUM(L7:L9) -> #REF! | Q9: =+O9-P9 -> #REF!
A10: =FIXED('Balance N'!A10,0,1) -> 28110000 | B10: =+'Balance N'!B10 -> Amort frais constitution | C10: =ROUND('Balance N'!#REF!,2) -> #REF! | D10: =ROUND('Balance N'!#REF!,2) -> #REF! | E10: =ROUND('Balance N'!C10,2) -> 0 | F10: =ROUND('Balance N'!D10,2) -> 2360.87 | G10: =ROUND('Balance N'!E10,2) -> 0 | H10: =ROUND('Balance N'!F10,2) -> 2360.87 | I10: =MID(A10,1,1) -> 2 | J10: Total | K10: =SUM(K2:K9) -> #REF! | L10: =SUM(L2:L9) -> #REF! | M10: =SUM(M2:M9) -> #REF!
A11: =FIXED('Balance N'!A11,0,1) -> 28322000 | B11: =+'Balance N'!B11 -> AMOT MATERIEL ET OULILLAGE | C11: =ROUND('Balance N'!#REF!,2) -> #REF! | D11: =ROUND('Balance N'!#REF!,2) -> #REF! | E11: =ROUND('Balance N'!C11,2) -> 0 | F11: =ROUND('Balance N'!D11,2) -> 1215 | G11: =ROUND('Balance N'!E11,2) -> 0 | H11: =ROUND('Balance N'!F11,2) -> 1215 | I11: =MID(A11,1,1) -> 2
A12: =FIXED('Balance N'!A12,0,1) -> 28340000 | B12: =+'Balance N'!B12 -> AMPORT MAT DE TRANSP | C12: =ROUND('Balance N'!#REF!,2) -> #REF! | D12: =ROUND('Balance N'!#REF!,2) -> #REF! | E12: =ROUND('Balance N'!C12,2) -> 0 | F12: =ROUND('Balance N'!D12,2) -> 169962.26 | G12: =ROUND('Balance N'!E12,2) -> 0 | H12: =ROUND('Balance N'!F12,2) -> 169962.26 | I12: =MID(A12,1,1) -> 2
A13: =FIXED('Balance N'!A13,0,1) -> 34110000 | B13: =+'Balance N'!B13 -> Frs avances et acompte | C13: =ROUND('Balance N'!#REF!,2) -> #REF! | D13: =ROUND('Balance N'!#REF!,2) -> #REF! | E13: =ROUND('Balance N'!C13,2) -> 504198.25 | F13: =ROUND('Balance N'!D13,2) -> 504198.25 | G13: =ROUND('Balance N'!E13,2) -> 0 | H13: =ROUND('Balance N'!F13,2) -> 0 | I13: =MID(A13,1,1) -> 3
A14: =FIXED('Balance N'!A14,0,1) -> 34210000 | B14: =+'Balance N'!B14 -> clients collectiive | C14: =ROUND('Balance N'!#REF!,2) -> #REF! | D14: =ROUND('Balance N'!#REF!,2) -> #REF! | E14: =ROUND('Balance N'!C14,2) -> 483000 | F14: =ROUND('Balance N'!D14,2) -> 195000 | G14: =ROUND('Balance N'!E14,2) -> 288000 | H14: =ROUND('Balance N'!F14,2) -> 0 | I14: =MID(A14,1,1) -> 3
A15: =FIXED('Balance N'!A15,0,1) -> 34550100 | B15: =+'Balance N'!B15 -> tva 20% | C15: =ROUND('Balance N'!#REF!,2) -> #REF! | D15: =ROUND('Balance N'!#REF!,2) -> #REF! | E15: =ROUND('Balance N'!C15,2) -> 42169.66 | F15: =ROUND('Balance N'!D15,2) -> 22567.97 | G15: =ROUND('Balance N'!E15,2) -> 19601.69 | H15: =ROUND('Balance N'!F15,2) -> 0 | I15: =MID(A15,1,1) -> 3
A16: =FIXED('Balance N'!A16,0,1) -> 34550300 | B16: =+'Balance N'!B16 -> TVA10 % | C16: =ROUND('Balance N'!#REF!,2) -> #REF! | D16: =ROUND('Balance N'!#REF!,2) -> #REF! | E16: =ROUND('Balance N'!C16,2) -> 4690.35 | F16: =ROUND('Balance N'!D16,2) -> 3491.32 | G16: =ROUND('Balance N'!E16,2) -> 1199.03 | H16: =ROUND('Balance N'!F16,2) -> 0 | I16: =MID(A16,1,1) -> 3
A17: =FIXED('Balance N'!A17,0,1) -> 34560000 | B17: =+'Balance N'!B17 -> CREDIT TVA | C17: =ROUND('Balance N'!#REF!,2) -> #REF! | D17: =ROUND('Balance N'!#REF!,2) -> #REF! | E17: =ROUND('Balance N'!C17,2) -> 3385.76 | F17: =ROUND('Balance N'!D17,2) -> 3385.76 | G17: =ROUND('Balance N'!E17,2) -> 0 | H17: =ROUND('Balance N'!F17,2) -> 0 | I17: =MID(A17,1,1) -> 3
A18: =FIXED('Balance N'!A18,0,1) -> 44110100 | B18: =+'Balance N'!B18 -> FOURNISSEUR LOCAUX | C18: =ROUND('Balance N'!#REF!,2) -> #REF! | D18: =ROUND('Balance N'!#REF!,2) -> #REF! | E18: =ROUND('Balance N'!C18,2) -> 1636170.1 | F18: =ROUND('Balance N'!D18,2) -> 1643743.3 | G18: =ROUND('Balance N'!E18,2) -> 0 | H18: =ROUND('Balance N'!F18,2) -> 7573.2 | I18: =MID(A18,1,1) -> 4
A19: =FIXED('Balance N'!A19,0,1) -> 44320000 | B19: =+'Balance N'!B19 -> SALAIRE NET | C19: =ROUND('Balance N'!#REF!,2) -> #REF! | D19: =ROUND('Balance N'!#REF!,2) -> #REF! | E19: =ROUND('Balance N'!C19,2) -> 26727 | F19: =ROUND('Balance N'!D19,2) -> 26727 | G19: =ROUND('Balance N'!E19,2) -> 0 | H19: =ROUND('Balance N'!F19,2) -> 0 | I19: =MID(A19,1,1) -> 4
A20: =FIXED('Balance N'!A20,0,1) -> 44410000 | B20: =+'Balance N'!B20 -> COT CNSS | C20: =ROUND('Balance N'!#REF!,2) -> #REF! | D20: =ROUND('Balance N'!#REF!,2) -> #REF! | E20: =ROUND('Balance N'!C20,2) -> 6006.57 | F20: =ROUND('Balance N'!D20,2) -> 6620.41 | G20: =ROUND('Balance N'!E20,2) -> 0 | H20: =ROUND('Balance N'!F20,2) -> 613.84 | I20: =MID(A20,1,1) -> 4
A21: =FIXED('Balance N'!A21,0,1) -> 44450000 | B21: =+'Balance N'!B21 -> COT AMO | C21: =ROUND('Balance N'!#REF!,2) -> #REF! | D21: =ROUND('Balance N'!#REF!,2) -> #REF! | E21: =ROUND('Balance N'!C21,2) -> 1782.97 | F21: =ROUND('Balance N'!D21,2) -> 1965.15 | G21: =ROUND('Balance N'!E21,2) -> 0 | H21: =ROUND('Balance N'!F21,2) -> 182.18 | I21: =MID(A21,1,1) -> 4
A22: =FIXED('Balance N'!A22,0,1) -> 44525000 | B22: =+'Balance N'!B22 -> IR | C22: =ROUND('Balance N'!#REF!,2) -> #REF! | D22: =ROUND('Balance N'!#REF!,2) -> #REF! | E22: =ROUND('Balance N'!C22,2) -> 0 | F22: =ROUND('Balance N'!D22,2) -> 343.49 | G22: =ROUND('Balance N'!E22,2) -> 0 | H22: =ROUND('Balance N'!F22,2) -> 343.49 | I22: =MID(A22,1,1) -> 4
... A614: =FIXED('Balance N'!A614,0,1) -> 0 | B614: =+'Balance N'!B614 -> 0 | C614: =ROUND('Balance N'!#REF!,2) -> #REF! | D614: =ROUND('Balance N'!#REF!,2) -> #REF! | E614: =ROUND('Balance N'!C614,2) -> 0 | F614: =ROUND('Balance N'!D614,2) -> 0 | G614: =ROUND('Balance N'!E614,2) -> 0 | H614: =ROUND('Balance N'!F614,2) -> 0 | I614: =MID(A614,1,1) -> 0
C615: =ROUND('Balance N'!#REF!,2) -> #REF! | D615: =ROUND('Balance N'!#REF!,2) -> #REF! | E615: =ROUND('Balance N'!C615,2) -> 0 | F615: =ROUND('Balance N'!D615,2) -> 0 | G615: =ROUND('Balance N'!E615,2) -> 0 | H615: =ROUND('Balance N'!F615,2) -> 0

Sheet Balance N-1 Retraitée
A1: Numero | B1: Libellé | C1: SD N-1 | D1: SC N-1 | E1: Débit Période | F1: Crédit Période | G1: SD N | H1: SC N | K1: Débit P. | L1: Crédit P. | M1: Solde
A2: =FIXED('Balance N-1'!A2,0,1) -> 11110000 | B2: =+'Balance N-1'!B2 -> CAPITAL | C2: =ROUND('Balance N-1'!#REF!,2) -> #REF! | D2: =ROUND('Balance N-1'!#REF!,2) -> #REF! | E2: =ROUND('Balance N-1'!C2,2) -> 0 | F2: =ROUND('Balance N-1'!D2,2) -> 100000 | G2: =ROUND('Balance N-1'!E2,2) -> 0 | H2: =ROUND('Balance N-1'!F2,2) -> 100000 | I2: =MID(A2,1,1) -> 1 | J2: 1 | K2: =SUMIF(I:I,J2,C:C) -> #REF! | L2: =SUMIF(I:I,J2,D:D) -> #REF! | M2: =+K2-L2 -> #REF! | N2: =+M2 -> #REF!
A3: =FIXED('Balance N-1'!A3,0,1) -> 21110000 | B3: =+'Balance N-1'!B3 -> Frais constitution | C3: =ROUND('Balance N-1'!#REF!,2) -> #REF! | D3: =ROUND('Balance N-1'!#REF!,2) -> #REF! | E3: =ROUND('Balance N-1'!C3,2) -> 5000 | F3: =ROUND('Balance N-1'!D3,2) -> 0 | G3: =ROUND('Balance N-1'!E3,2) -> 5000 | H3: =ROUND('Balance N-1'!F3,2) -> 0 | I3: =MID(A3,1,1) -> 2 | J3: 2 | K3: =SUMIF(I:I,J3,C:C) -> #REF! | L3: =SUMIF(I:I,J3,D:D) -> #REF! | M3: =+K3-L3 -> #REF! | N3: =+N2+M3 -> #REF!
A4: =FIXED('Balance N-1'!A4,0,1) -> 28110000 | B4: =+'Balance N-1'!B4 -> Amort frais constitution | C4: =ROUND('Balance N-1'!#REF!,2) -> #REF! | D4: =ROUND('Balance N-1'!#REF!,2) -> #REF! | E4: =ROUND('Balance N-1'!C4,2) -> 0 | F4: =ROUND('Balance N-1'!D4,2) -> 694.37 | G4: =ROUND('Balance N-1'!E4,2) -> 0 | H4: =ROUND('Balance N-1'!F4,2) -> 694.37 | I4: =MID(A4,1,1) -> 2 | J4: 3 | K4: =SUMIF(I:I,J4,C:C) -> #REF! | L4: =SUMIF(I:I,J4,D:D) -> #REF! | M4: =+K4-L4 -> #REF! | N4: =+N3+M4 -> #REF!
A5: =FIXED('Balance N-1'!A5,0,1) -> 34550300 | B5: =+'Balance N-1'!B5 -> TVA10 % | C5: =ROUND('Balance N-1'!#REF!,2) -> #REF! | D5: =ROUND('Balance N-1'!#REF!,2) -> #REF! | E5: =ROUND('Balance N-1'!C5,2) -> 34.53 | F5: =ROUND('Balance N-1'!D5,2) -> 0 | G5: =ROUND('Balance N-1'!E5,2) -> 34.53 | H5: =ROUND('Balance N-1'!F5,2) -> 0 | I5: =MID(A5,1,1) -> 3 | J5: 4 | K5: =SUMIF(I:I,J5,C:C) -> #REF! | L5: =SUMIF(I:I,J5,D:D) -> #REF! | M5: =+K5-L5 -> #REF! | N5: =+N4+M5 -> #REF!
A6: =FIXED('Balance N-1'!A6,0,1) -> 44320000 | B6: =+'Balance N-1'!B6 -> SALAIRE NET | C6: =ROUND('Balance N-1'!#REF!,2) -> #REF! | D6: =ROUND('Balance N-1'!#REF!,2) -> #REF! | E6: =ROUND('Balance N-1'!C6,2) -> 10000 | F6: =ROUND('Balance N-1'!D6,2) -> 10000 | G6: =ROUND('Balance N-1'!E6,2) -> 0 | H6: =ROUND('Balance N-1'!F6,2) -> 0 | I6: =MID(A6,1,1) -> 4 | J6: 5 | K6: =SUMIF(I:I,J6,C:C) -> #REF! | L6: =SUMIF(I:I,J6,D:D) -> #REF! | M6: =+K6-L6 -> #REF! | N6: =+N5+M6 -> #REF! | O6: =SUM(K2:K6) -> #REF! | P6: =SUM(L2:L6) -> #REF! | Q6: =+O6-P6 -> #REF!
A7: =FIXED('Balance N-1'!A7,0,1) -> 44410000 | B7: =+'Balance N-1'!B7 -> COT CNSS | C7: =ROUND('Balance N-1'!#REF!,2) -> #REF! | D7: =ROUND('Balance N-1'!#REF!,2) -> #REF! | E7: =ROUND('Balance N-1'!C7,2) -> 1073 | F7: =ROUND('Balance N-1'!D7,2) -> 2146 | G7: =ROUND('Balance N-1'!E7,2) -> 0 | H7: =ROUND('Balance N-1'!F7,2) -> 1073 | I7: =MID(A7,1,1) -> 4 | J7: 6 | K7: =SUMIF(I:I,J7,C:C) -> #REF! | L7: =SUMIF(I:I,J7,D:D) -> #REF! | M7: =+K7-L7 -> #REF! | N7: =M7 -> #REF!
A8: =FIXED('Balance N-1'!A8,0,1) -> 44450000 | B8: =+'Balance N-1'!B8 -> COT AMO | C8: =ROUND('Balance N-1'!#REF!,2) -> #REF! | D8: =ROUND('Balance N-1'!#REF!,2) -> #REF! | E8: =ROUND('Balance N-1'!C8,2) -> 318.5 | F8: =ROUND('Balance N-1'!D8,2) -> 637 | G8: =ROUND('Balance N-1'!E8,2) -> 0 | H8: =ROUND('Balance N-1'!F8,2) -> 318.5 | I8: =MID(A8,1,1) -> 4 | J8: 7 | K8: =SUMIF(I:I,J8,C:C) -> 0 | L8: =SUMIF(I:I,J8,D:D) -> 0 | M8: =+K8-L8 -> 0 | N8: =+N7+M8 -> #REF!
A9: =FIXED('Balance N-1'!A9,0,1) -> 44525000 | B9: =+'Balance N-1'!B9 -> IR | C9: =ROUND('Balance N-1'!#REF!,2) -> #REF! | D9: =ROUND('Balance N-1'!#REF!,2) -> #REF! | E9: =ROUND('Balance N-1'!C9,2) -> 0 | F9: =ROUND('Balance N-1'!D9,2) -> 88 | G9: =ROUND('Balance N-1'!E9,2) -> 0 | H9: =ROUND('Balance N-1'!F9,2) -> 88 | I9: =MID(A9,1,1) -> 4 | J9: 8 | K9: =SUMIF(I:I,J9,C:C) -> 0 | L9: =SUMIF(I:I,J9,D:D) -> 0 | M9: =+K9-L9 -> 0 | O9: =SUM(K7:K9) -> #REF! | P9: =SUM(L7:L9) -> #REF! | Q9: =+O9-P9 -> #REF!
A10: =FIXED('Balance N-1'!A10,0,1) -> 44630000 | B10: =+'Balance N-1'!B10 -> COMPTE COURANT D'ASSOCIE | C10: =ROUND('Balance N-1'!#REF!,2) -> #REF! | D10: =ROUND('Balance N-1'!#REF!,2) -> #REF! | E10: =ROUND('Balance N-1'!C10,2) -> 340475.8 | F10: =ROUND('Balance N-1'!D10,2) -> 574000.8 | G10: =ROUND('Balance N-1'!E10,2) -> 0 | H10: =ROUND('Balance N-1'!F10,2) -> 233525 | I10: =MID(A10,1,1) -> 4 | J10: Total | K10: =SUM(K2:K9) -> #REF! | L10: =SUM(L2:L9) -> #REF! | M10: =SUM(M2:M9) -> #REF!
A11: =FIXED('Balance N-1'!A11,0,1) -> 51410000 | B11: =+'Balance N-1'!B11 -> ATTIJARIWAFA BANK | C11: =ROUND('Balance N-1'!#REF!,2) -> #REF! | D11: =ROUND('Balance N-1'!#REF!,2) -> #REF! | E11: =ROUND('Balance N-1'!C11,2) -> 469000.8 | F11: =ROUND('Balance N-1'!D11,2) -> 246155.13 | G11: =ROUND('Balance N-1'!E11,2) -> 222845.67 | H11: =ROUND('Balance N-1'!F11,2) -> 0 | I11: =MID(A11,1,1) -> 5
A12: =FIXED('Balance N-1'!A12,0,1) -> 51610000 | B12: =+'Balance N-1'!B12 -> CAISSE | C12: =ROUND('Balance N-1'!#REF!,2) -> #REF! | D12: =ROUND('Balance N-1'!#REF!,2) -> #REF! | E12: =ROUND('Balance N-1'!C12,2) -> 108900 | F12: =ROUND('Balance N-1'!D12,2) -> 20000 | G12: =ROUND('Balance N-1'!E12,2) -> 88900 | H12: =ROUND('Balance N-1'!F12,2) -> 0 | I12: =MID(A12,1,1) -> 5
A13: =FIXED('Balance N-1'!A13,0,1) -> 61312000 | B13: =+'Balance N-1'!B13 -> loyer | C13: =ROUND('Balance N-1'!#REF!,2) -> #REF! | D13: =ROUND('Balance N-1'!#REF!,2) -> #REF! | E13: =ROUND('Balance N-1'!C13,2) -> 5000 | F13: =ROUND('Balance N-1'!D13,2) -> 0 | G13: =ROUND('Balance N-1'!E13,2) -> 5000 | H13: =ROUND('Balance N-1'!F13,2) -> 0 | I13: =MID(A13,1,1) -> 6
A14: =FIXED('Balance N-1'!A14,0,1) -> 61470000 | B14: =+'Balance N-1'!B14 -> frais bancaire | C14: =ROUND('Balance N-1'!#REF!,2) -> #REF! | D14: =ROUND('Balance N-1'!#REF!,2) -> #REF! | E14: =ROUND('Balance N-1'!C14,2) -> 353.3 | F14: =ROUND('Balance N-1'!D14,2) -> 0 | G14: =ROUND('Balance N-1'!E14,2) -> 353.3 | H14: =ROUND('Balance N-1'!F14,2) -> 0 | I14: =MID(A14,1,1) -> 6
A15: =FIXED('Balance N-1'!A15,0,1) -> 61710000 | B15: =+'Balance N-1'!B15 -> SALAIRE BRUT | C15: =ROUND('Balance N-1'!#REF!,2) -> #REF! | D15: =ROUND('Balance N-1'!#REF!,2) -> #REF! | E15: =ROUND('Balance N-1'!C15,2) -> 10762 | F15: =ROUND('Balance N-1'!D15,2) -> 0 | G15: =ROUND('Balance N-1'!E15,2) -> 10762 | H15: =ROUND('Balance N-1'!F15,2) -> 0 | I15: =MID(A15,1,1) -> 6
A16: =FIXED('Balance N-1'!A16,0,1) -> 61740000 | B16: =+'Balance N-1'!B16 -> COT P P | C16: =ROUND('Balance N-1'!#REF!,2) -> #REF! | D16: =ROUND('Balance N-1'!#REF!,2) -> #REF! | E16: =ROUND('Balance N-1'!C16,2) -> 2109 | F16: =ROUND('Balance N-1'!D16,2) -> 0 | G16: =ROUND('Balance N-1'!E16,2) -> 2109 | H16: =ROUND('Balance N-1'!F16,2) -> 0 | I16: =MID(A16,1,1) -> 6
A17: =FIXED('Balance N-1'!A17,0,1) -> 61911000 | B17: =+'Balance N-1'!B17 -> DEA FRAIS CONSTITUTION | C17: =ROUND('Balance N-1'!#REF!,2) -> #REF! | D17: =ROUND('Balance N-1'!#REF!,2) -> #REF! | E17: =ROUND('Balance N-1'!C17,2) -> 694.37 | F17: =ROUND('Balance N-1'!D17,2) -> 0 | G17: =ROUND('Balance N-1'!E17,2) -> 694.37 | H17: =ROUND('Balance N-1'!F17,2) -> 0 | I17: =MID(A17,1,1) -> 6
A18: =FIXED('Balance N-1'!A18,0,1) -> 0 | B18: =+'Balance N-1'!B18 -> 0 | C18: =ROUND('Balance N-1'!#REF!,2) -> #REF! | D18: =ROUND('Balance N-1'!#REF!,2) -> #REF! | E18: =ROUND('Balance N-1'!C18,2) -> 0 | F18: =ROUND('Balance N-1'!D18,2) -> 0 | G18: =ROUND('Balance N-1'!E18,2) -> 0 | H18: =ROUND('Balance N-1'!F18,2) -> 0 | I18: =MID(A18,1,1) -> 0
A19: =FIXED('Balance N-1'!A19,0,1) -> 0 | B19: =+'Balance N-1'!B19 -> 0 | C19: =ROUND('Balance N-1'!#REF!,2) -> #REF! | D19: =ROUND('Balance N-1'!#REF!,2) -> #REF! | E19: =ROUND('Balance N-1'!C19,2) -> 0 | F19: =ROUND('Balance N-1'!D19,2) -> 0 | G19: =ROUND('Balance N-1'!E19,2) -> 0 | H19: =ROUND('Balance N-1'!F19,2) -> 0 | I19: =MID(A19,1,1) -> 0
A20: =FIXED('Balance N-1'!A20,0,1) -> 0 | B20: =+'Balance N-1'!B20 -> 0 | C20: =ROUND('Balance N-1'!#REF!,2) -> #REF! | D20: =ROUND('Balance N-1'!#REF!,2) -> #REF! | E20: =ROUND('Balance N-1'!C20,2) -> 0 | F20: =ROUND('Balance N-1'!D20,2) -> 0 | G20: =ROUND('Balance N-1'!E20,2) -> 0 | H20: =ROUND('Balance N-1'!F20,2) -> 0 | I20: =MID(A20,1,1) -> 0
A21: =FIXED('Balance N-1'!A21,0,1) -> 0 | B21: =+'Balance N-1'!B21 -> 0 | C21: =ROUND('Balance N-1'!#REF!,2) -> #REF! | D21: =ROUND('Balance N-1'!#REF!,2) -> #REF! | E21: =ROUND('Balance N-1'!C21,2) -> 0 | F21: =ROUND('Balance N-1'!D21,2) -> 0 | G21: =ROUND('Balance N-1'!E21,2) -> 0 | H21: =ROUND('Balance N-1'!F21,2) -> 0 | I21: =MID(A21,1,1) -> 0
A22: =FIXED('Balance N-1'!A22,0,1) -> 0 | B22: =+'Balance N-1'!B22 -> 0 | C22: =ROUND('Balance N-1'!#REF!,2) -> #REF! | D22: =ROUND('Balance N-1'!#REF!,2) -> #REF! | E22: =ROUND('Balance N-1'!C22,2) -> 0 | F22: =ROUND('Balance N-1'!D22,2) -> 0 | G22: =ROUND('Balance N-1'!E22,2) -> 0 | H22: =ROUND('Balance N-1'!F22,2) -> 0 | I22: =MID(A22,1,1) -> 0
... A616: =FIXED('Balance N-1'!A616,0,1) -> 0 | B616: =+'Balance N-1'!B616 -> 0 | C616: =ROUND('Balance N-1'!#REF!,2) -> #REF! | D616: =ROUND('Balance N-1'!#REF!,2) -> #REF! | E616: =ROUND('Balance N-1'!C616,2) -> 0 | F616: =ROUND('Balance N-1'!D616,2) -> 0 | G616: =ROUND('Balance N-1'!E616,2) -> 0 | H616: =ROUND('Balance N-1'!F616,2) -> 0 | I616: =MID(A616,1,1) -> 0
C617: =ROUND('Balance N-1'!#REF!,2) -> #REF! | D617: =ROUND('Balance N-1'!#REF!,2) -> #REF! | E617: =ROUND('Balance N-1'!C617,2) -> 0 | F617: =ROUND('Balance N-1'!D617,2) -> 0 | G617: =ROUND('Balance N-1'!E617,2) -> 0 | H617: =ROUND('Balance N-1'!F617,2) -> 0

Sheet T1 Bilan
A1: Tableau n° 1
C2: BILAN (ACTIF)
C3: (modèle normal) | E3: Exercice clos le : | G3: =Couverture!E15 -> 31/12/2022
B4: ACTIF | D4: Exercice | G4: Exercice Précédent
D5: Amortissement
C6: Brut | D6: et | E6: Net | G6: Net
D7: provisions
B8: IMMOBILISATIONS EN NON VALEURS (A) | C8: =SUM(C9:C11) -> 5000 | D8: =SUM(D9:D11) -> 2360.87 | E8: =SUM(E9:E11) -> 2639.13 | G8: =SUM(G9:G11) -> 4305.63
B9: * Frais préliminaires | C9: =SUMIF('Balance N Retraitée'!A:A,"211*",'Balance N Retraitée'!G:G)-SUMIF('Balance N Retraitée'!A:A,"211*",'Balance N Retraitée'!H:H) -> 5000 | D9: =(SUMIF('Balance N Retraitée'!A:A,"2811*",'Balance N Retraitée'!H:H)-SUMIF('Balance N Retraitée'!A:A,"2811*",'Balance N Retraitée'!G:G))+(SUMIF('Balance N Retraitée'!A:A,"2911*",'Balance N Retraitée'!H:H)-SUMIF('Balance N Retraitée'!A:A,"2911*",'Balance N Retraitée'!G:G)) -> 2360.87 | E9: =+C9-D9 -> 2639.13 | G9: =(SUMIF('Balance N-1 Retraitée'!A:A,"211*",'Balance N-1 Retraitée'!G:G)-SUMIF('Balance N-1 Retraitée'!A:A,"211*",'Balance N-1 Retraitée'!H:H))-(SUMIF('Balance N-1 Retraitée'!A:A,"2811*",'Balance N-1 Retraitée'!H:H)-SUMIF('Balance N-1 Retraitée'!A:A,"2811*",'Balance N-1 Retraitée'!G:G))-(SUMIF('Balance N-1 Retraitée'!A:A,"2911*",'Balance N-1 Retraitée'!H:H)-SUMIF('Balance N-1 Retraitée'!A:A,"2911*",'Balance N-1 Retraitée'!G:G)) -> 4305.63
B10: * Charges à repartir sur plusieurs exercices | C10: =SUMIF('Balance N Retraitée'!A:A,"212*",'Balance N Retraitée'!G:G)-SUMIF('Balance N Retraitée'!A:A,"212*",'Balance N Retraitée'!H:H) -> 0 | D10: =(SUMIF('Balance N Retraitée'!A:A,"2812*",'Balance N Retraitée'!H:H)-SUMIF('Balance N Retraitée'!A:A,"2812*",'Balance N Retraitée'!G:G))+(SUMIF('Balance N Retraitée'!A:A,"2912*",'Balance N Retraitée'!H:H)-SUMIF('Balance N Retraitée'!A:A,"2912*",'Balance N Retraitée'!G:G)) -> 0 | E10: =+C10-D10 -> 0 | G10: =(SUMIF('Balance N-1 Retraitée'!A:A,"212*",'Balance N-1 Retraitée'!G:G)-SUMIF('Balance N-1 Retraitée'!A:A,"212*",'Balance N-1 Retraitée'!H:H))-(SUMIF('Balance N-1 Retraitée'!A:A,"2812*",'Balance N-1 Retraitée'!H:H)-SUMIF('Balance N-1 Retraitée'!A:A,"2812*",'Balance N-1 Retraitée'!G:G))-(SUMIF('Balance N-1 Retraitée'!A:A,"2912*",'Balance N-1 Retraitée'!H:H)-SUMIF('Balance N-1 Retraitée'!A:A,"2912*",'Balance N-1 Retraitée'!G:G)) -> 0
A11: s | B11: * Primes de remboursement des obligations | C11: =SUMIF('Balance N Retraitée'!A:A,"213*",'Balance N Retraitée'!G:G)-SUMIF('Balance N Retraitée'!A:A,"213*",'Balance N Retraitée'!H:H) -> 0 | D11: =(SUMIF('Balance N Retraitée'!A:A,"2813*",'Balance N Retraitée'!H:H)-SUMIF('Balance N Retraitée'!A:A,"2813*",'Balance N Retraitée'!G:G))+(SUMIF('Balance N Retraitée'!A:A,"2913*",'Balance N Retraitée'!H:H)-SUMIF('Balance N Retraitée'!A:A,"2913*",'Balance N Retraitée'!G:G)) -> 0 | E11: =+C13-D13 -> 0 | G11: =(SUMIF('Balance N-1 Retraitée'!A:A,"213*",'Balance N-1 Retraitée'!G:G)-SUMIF('Balance N-1 Retraitée'!A:A,"213*",'Balance N-1 Retraitée'!H:H))-(SUMIF('Balance N-1 Retraitée'!A:A,"2813*",'Balance N-1 Retraitée'!H:H)-SUMIF('Balance N-1 Retraitée'!A:A,"2813*",'Balance N-1 Retraitée'!G:G))-(SUMIF('Balance N-1 Retraitée'!A:A,"2913*",'Balance N-1 Retraitée'!H:H)-SUMIF('Balance N-1 Retraitée'!A:A,"2913*",'Balance N-1 Retraitée'!G:G)) -> 0
A12: e | B12: IMMOBILISATIONS INCORPORELLES (B) | C12: =SUM(C13:C16) -> 0 | D12: =SUM(D13:D16) -> 0 | E12: =SUM(E13:E16) -> 0 | G12: =SUM(G13:G16) -> 0
A13: é | B13: * Immobilisation en recherche et développement | C13: =SUMIF('Balance N Retraitée'!A:A,"221*",'Balance N Retraitée'!G:G)-SUMIF('Balance N Retraitée'!A:A,"221*",'Balance N Retraitée'!H:H) -> 0 | D13: =(SUMIF('Balance N Retraitée'!A:A,"2821*",'Balance N Retraitée'!H:H)-SUMIF('Balance N Retraitée'!A:A,"2821*",'Balance N Retraitée'!G:G))+(SUMIF('Balance N Retraitée'!A:A,"2921*",'Balance N Retraitée'!H:H)-SUMIF('Balance N Retraitée'!A:A,"2921*",'Balance N Retraitée'!G:G)) -> 0 | E13: =+C13-D13 -> 0 | G13: =(SUMIF('Balance N-1 Retraitée'!A:A,"221*",'Balance N-1 Retraitée'!G:G)-SUMIF('Balance N-1 Retraitée'!A:A,"221*",'Balance N-1 Retraitée'!H:H))-(SUMIF('Balance N-1 Retraitée'!A:A,"2821*",'Balance N-1 Retraitée'!H:H)-SUMIF('Balance N-1 Retraitée'!A:A,"2821*",'Balance N-1 Retraitée'!G:G))-(SUMIF('Balance N-1 Retraitée'!A:A,"2921*",'Balance N-1 Retraitée'!H:H)-SUMIF('Balance N-1 Retraitée'!A:A,"2921*",'Balance N-1 Retraitée'!G:G)) -> 0
A14: s | B14: * Brevets, marques, droits et valeurs similaires | C14: =SUMIF('Balance N Retraitée'!A:A,"222*",'Balance N Retraitée'!G:G)-SUMIF('Balance N Retraitée'!A:A,"222*",'Balance N Retraitée'!H:H) -> 0 | D14: =(SUMIF('Balance N Retraitée'!A:A,"2822*",'Balance N Retraitée'!H:H)-SUMIF('Balance N Retraitée'!A:A,"2822*",'Balance N Retraitée'!G:G))+(SUMIF('Balance N Retraitée'!A:A,"2922*",'Balance N Retraitée'!H:H)-SUMIF('Balance N Retraitée'!A:A,"2922*",'Balance N Retraitée'!G:G)) -> 0 | E14: =+C14-D14 -> 0 | G14: =(SUMIF('Balance N-1 Retraitée'!A:A,"222*",'Balance N-1 Retraitée'!G:G)-SUMIF('Balance N-1 Retraitée'!A:A,"222*",'Balance N-1 Retraitée'!H:H))-(SUMIF('Balance N-1 Retraitée'!A:A,"2822*",'Balance N-1 Retraitée'!H:H)-SUMIF('Balance N-1 Retraitée'!A:A,"2822*",'Balance N-1 Retraitée'!G:G))-(SUMIF('Balance N-1 Retraitée'!A:A,"2922*",'Balance N-1 Retraitée'!H:H)-SUMIF('Balance N-1 Retraitée'!A:A,"2922*",'Balance N-1 Retraitée'!G:G)) -> 0
A15: i | B15: * Fonds commercial | C15: =SUMIF('Balance N Retraitée'!A:A,"223*",'Balance N Retraitée'!G:G)-SUMIF('Balance N Retraitée'!A:A,"223*",'Balance N Retraitée'!H:H) -> 0 | D15: =(SUMIF('Balance N Retraitée'!A:A,"2823*",'Balance N Retraitée'!H:H)-SUMIF('Balance N Retraitée'!A:A,"2823*",'Balance N Retraitée'!G:G))+(SUMIF('Balance N Retraitée'!A:A,"2923*",'Balance N Retraitée'!H:H)-SUMIF('Balance N Retraitée'!A:A,"2923*",'Balance N Retraitée'!G:G)) -> 0 | E15: =+C15-D15 -> 0 | G15: =(SUMIF('Balance N-1 Retraitée'!A:A,"223*",'Balance N-1 Retraitée'!G:G)-SUMIF('Balance N-1 Retraitée'!A:A,"223*",'Balance N-1 Retraitée'!H:H))-(SUMIF('Balance N-1 Retraitée'!A:A,"2823*",'Balance N-1 Retraitée'!H:H)-SUMIF('Balance N-1 Retraitée'!A:A,"2823*",'Balance N-1 Retraitée'!G:G))-(SUMIF('Balance N-1 Retraitée'!A:A,"2923*",'Balance N-1 Retraitée'!H:H)-SUMIF('Balance N-1 Retraitée'!A:A,"2923*",'Balance N-1 Retraitée'!G:G)) -> 0
A16: l | B16: * Autres immobilisations incorporelles | C16: =SUMIF('Balance N Retraitée'!A:A,"228*",'Balance N Retraitée'!G:G)-SUMIF('Balance N Retraitée'!A:A,"228*",'Balance N Retraitée'!H:H) -> 0 | D16: =(SUMIF('Balance N Retraitée'!A:A,"2828*",'Balance N Retraitée'!H:H)-SUMIF('Balance N Retraitée'!A:A,"2828*",'Balance N Retraitée'!G:G))+(SUMIF('Balance N Retraitée'!A:A,"2928*",'Balance N Retraitée'!H:H)-SUMIF('Balance N Retraitée'!A:A,"2928*",'Balance N Retraitée'!G:G)) -> 0 | E16: =+C16-D16 -> 0 | G16: =(SUMIF('Balance N-1 Retraitée'!A:A,"228*",'Balance N-1 Retraitée'!G:G)-SUMIF('Balance N-1 Retraitée'!A:A,"228*",'Balance N-1 Retraitée'!H:H))-(SUMIF('Balance N-1 Retraitée'!A:A,"2828*",'Balance N-1 Retraitée'!H:H)-SUMIF('Balance N-1 Retraitée'!A:A,"2828*",'Balance N-1 Retraitée'!G:G))-(SUMIF('Balance N-1 Retraitée'!A:A,"2928*",'Balance N-1 Retraitée'!H:H)-SUMIF('Balance N-1 Retraitée'!A:A,"2928*",'Balance N-1 Retraitée'!G:G)) -> 0
A17: i | B17: IMMOBILISATIONS CORPORELLES (C) | C17: =SUM(C18:C24) -> 1588527.6 | D17: =SUM(D18:D24) -> 171177.26 | E17: =SUM(E18:E24) -> 1417350.3 | G17: =SUM(G18:G24) -> 0
A18: b | B18: * Terrains | C18: =SUMIF('Balance N Retraitée'!A:A,"231*",'Balance N Retraitée'!G:G)-SUMIF('Balance N Retraitée'!A:A,"231*",'Balance N Retraitée'!H:H) -> 0 | D18: =(SUMIF('Balance N Retraitée'!A:A,"2831*",'Balance N Retraitée'!H:H)-SUMIF('Balance N Retraitée'!A:A,"2831*",'Balance N Retraitée'!G:G))+(SUMIF('Balance N Retraitée'!A:A,"2931*",'Balance N Retraitée'!H:H)-SUMIF('Balance N Retraitée'!A:A,"2931*",'Balance N Retraitée'!G:G)) -> 0 | E18: =+C18-D18 -> 0 | G18: =(SUMIF('Balance N-1 Retraitée'!A:A,"231*",'Balance N-1 Retraitée'!G:G)-SUMIF('Balance N-1 Retraitée'!A:A,"231*",'Balance N-1 Retraitée'!H:H))-(SUMIF('Balance N-1 Retraitée'!A:A,"2831*",'Balance N-1 Retraitée'!H:H)-SUMIF('Balance N-1 Retraitée'!A:A,"2831*",'Balance N-1 Retraitée'!G:G))-(SUMIF('Balance N-1 Retraitée'!A:A,"2931*",'Balance N-1 Retraitée'!H:H)-SUMIF('Balance N-1 Retraitée'!A:A,"2931*",'Balance N-1 Retraitée'!G:G)) -> 0
A19: o | B19: * Constructions | C19: =SUMIF('Balance N Retraitée'!A:A,"232*",'Balance N Retraitée'!G:G)-SUMIF('Balance N Retraitée'!A:A,"232*",'Balance N Retraitée'!H:H) -> 9700 | D19: =(SUMIF('Balance N Retraitée'!A:A,"2832*",'Balance N Retraitée'!H:H)-SUMIF('Balance N Retraitée'!A:A,"2832*",'Balance N Retraitée'!G:G))+(SUMIF('Balance N Retraitée'!A:A,"2932*",'Balance N Retraitée'!H:H)-SUMIF('Balance N Retraitée'!A:A,"2932*",'Balance N Retraitée'!G:G)) -> 1215 | E19: =+C19-D19 -> 8485 | G19: =(SUMIF('Balance N-1 Retraitée'!A:A,"232*",'Balance N-1 Retraitée'!G:G)-SUMIF('Balance N-1 Retraitée'!A:A,"232*",'Balance N-1 Retraitée'!H:H))-(SUMIF('Balance N-1 Retraitée'!A:A,"2832*",'Balance N-1 Retraitée'!H:H)-SUMIF('Balance N-1 Retraitée'!A:A,"2832*",'Balance N-1 Retraitée'!G:G))-(SUMIF('Balance N-1 Retraitée'!A:A,"2932*",'Balance N-1 Retraitée'!H:H)-SUMIF('Balance N-1 Retraitée'!A:A,"2932*",'Balance N-1 Retraitée'!G:G)) -> 0
A20: m | B20: * Installations techniques, matériel et outillage | C20: =SUMIF('Balance N Retraitée'!A:A,"233*",'Balance N Retraitée'!G:G)-SUMIF('Balance N Retraitée'!A:A,"233*",'Balance N Retraitée'!H:H) -> 0 | D20: =(SUMIF('Balance N Retraitée'!A:A,"2833*",'Balance N Retraitée'!H:H)-SUMIF('Balance N Retraitée'!A:A,"2833*",'Balance N Retraitée'!G:G))+(SUMIF('Balance N Retraitée'!A:A,"2933*",'Balance N Retraitée'!H:H)-SUMIF('Balance N Retraitée'!A:A,"2933*",'Balance N Retraitée'!G:G)) -> 0 | E20: =+C20-D20 -> 0 | G20: =(SUMIF('Balance N-1 Retraitée'!A:A,"233*",'Balance N-1 Retraitée'!G:G)-SUMIF('Balance N-1 Retraitée'!A:A,"233*",'Balance N-1 Retraitée'!H:H))-(SUMIF('Balance N-1 Retraitée'!A:A,"2833*",'Balance N-1 Retraitée'!H:H)-SUMIF('Balance N-1 Retraitée'!A:A,"2833*",'Balance N-1 Retraitée'!G:G))-(SUMIF('Balance N-1 Retraitée'!A:A,"2933*",'Balance N-1 Retraitée'!H:H)-SUMIF('Balance N-1 Retraitée'!A:A,"2933*",'Balance N-1 Retraitée'!G:G)) -> 0
A21: m | B21: * Matériel transport | C21: =SUMIF('Balance N Retraitée'!A:A,"234*",'Balance N Retraitée'!G:G)-SUMIF('Balance N Retraitée'!A:A,"234*",'Balance N Retraitée'!H:H) -> 1578827.6 | D21: =(SUMIF('Balance N Retraitée'!A:A,"2834*",'Balance N Retraitée'!H:H)-SUMIF('Balance N Retraitée'!A:A,"2834*",'Balance N Retraitée'!G:G))+(SUMIF('Balance N Retraitée'!A:A,"2934*",'Balance N Retraitée'!H:H)-SUMIF('Balance N Retraitée'!A:A,"2934*",'Balance N Retraitée'!G:G)) -> 169962.26 | E21: =+C21-D21 -> 1408865.3 | G21: =(SUMIF('Balance N-1 Retraitée'!A:A,"234*",'Balance N-1 Retraitée'!G:G)-SUMIF('Balance N-1 Retraitée'!A:A,"234*",'Balance N-1 Retraitée'!H:H))-(SUMIF('Balance N-1 Retraitée'!A:A,"2834*",'Balance N-1 Retraitée'!H:H)-SUMIF('Balance N-1 Retraitée'!A:A,"2834*",'Balance N-1 Retraitée'!G:G))-(SUMIF('Balance N-1 Retraitée'!A:A,"2934*",'Balance N-1 Retraitée'!H:H)-SUMIF('Balance N-1 Retraitée'!A:A,"2934*",'Balance N-1 Retraitée'!G:G)) -> 0
A22: I | B22: * Mobilier, matériel de bureau et aménagements divers | C22: =SUMIF('Balance N Retraitée'!A:A,"235*",'Balance N Retraitée'!G:G)-SUMIF('Balance N Retraitée'!A:A,"235*",'Balance N Retraitée'!H:H) -> 0 | D22: =(SUMIF('Balance N Retraitée'!A:A,"2835*",'Balance N Retraitée'!H:H)-SUMIF('Balance N Retraitée'!A:A,"2835*",'Balance N Retraitée'!G:G))+(SUMIF('Balance N Retraitée'!A:A,"2935*",'Balance N Retraitée'!H:H)-SUMIF('Balance N Retraitée'!A:A,"2935*",'Balance N Retraitée'!G:G)) -> 0 | E22: =+C22-D22 -> 0 | G22: =(SUMIF('Balance N-1 Retraitée'!A:A,"235*",'Balance N-1 Retraitée'!G:G)-SUMIF('Balance N-1 Retraitée'!A:A,"235*",'Balance N-1 Retraitée'!H:H))-(SUMIF('Balance N-1 Retraitée'!A:A,"2835*",'Balance N-1 Retraitée'!H:H)-SUMIF('Balance N-1 Retraitée'!A:A,"2835*",'Balance N-1 Retraitée'!G:G))-(SUMIF('Balance N-1 Retraitée'!A:A,"2935*",'Balance N-1 Retraitée'!H:H)-SUMIF('Balance N-1 Retraitée'!A:A,"2935*",'Balance N-1 Retraitée'!G:G)) -> 0
B23: * Autres immobilisations corporelles | C23: =SUMIF('Balance N Retraitée'!A:A,"236*",'Balance N Retraitée'!G:G)-SUMIF('Balance N Retraitée'!A:A,"236*",'Balance N Retraitée'!H:H) -> 0 | D23: =(SUMIF('Balance N Retraitée'!A:A,"2836*",'Balance N Retraitée'!H:H)-SUMIF('Balance N Retraitée'!A:A,"2836*",'Balance N Retraitée'!G:G))+(SUMIF('Balance N Retraitée'!A:A,"2936*",'Balance N Retraitée'!H:H)-SUMIF('Balance N Retraitée'!A:A,"2936*",'Balance N Retraitée'!G:G)) -> 0 | E23: =+C23-D23 -> 0 | G23: =(SUMIF('Balance N-1 Retraitée'!A:A,"236*",'Balance N-1 Retraitée'!G:G)-SUMIF('Balance N-1 Retraitée'!A:A,"236*",'Balance N-1 Retraitée'!H:H))-(SUMIF('Balance N-1 Retraitée'!A:A,"2836*",'Balance N-1 Retraitée'!H:H)-SUMIF('Balance N-1 Retraitée'!A:A,"2836*",'Balance N-1 Retraitée'!G:G))-(SUMIF('Balance N-1 Retraitée'!A:A,"2936*",'Balance N-1 Retraitée'!H:H)-SUMIF('Balance N-1 Retraitée'!A:A,"2936*",'Balance N-1 Retraitée'!G:G)) -> 0
A24: s | B24: * Immobilisations corporelles en cours | C24: =SUMIF('Balance N Retraitée'!A:A,"238*",'Balance N Retraitée'!G:G)-SUMIF('Balance N Retraitée'!A:A,"238*",'Balance N Retraitée'!H:H) -> 0 | D24: =(SUMIF('Balance N Retraitée'!A:A,"2838*",'Balance N Retraitée'!H:H)-SUMIF('Balance N Retraitée'!A:A,"2838*",'Balance N Retraitée'!G:G))+(SUMIF('Balance N Retraitée'!A:A,"2938*",'Balance N Retraitée'!H:H)-SUMIF('Balance N Retraitée'!A:A,"2938*",'Balance N Retraitée'!G:G)) -> 0 | E24: =+C24-D24 -> 0 | G24: =(SUMIF('Balance N-1 Retraitée'!A:A,"238*",'Balance N-1 Retraitée'!G:G)-SUMIF('Balance N-1 Retraitée'!A:A,"238*",'Balance N-1 Retraitée'!H:H))-(SUMIF('Balance N-1 Retraitée'!A:A,"2838*",'Balance N-1 Retraitée'!H:H)-SUMIF('Balance N-1 Retraitée'!A:A,"2838*",'Balance N-1 Retraitée'!G:G))-(SUMIF('Balance N-1 Retraitée'!A:A,"2938*",'Balance N-1 Retraitée'!H:H)-SUMIF('Balance N-1 Retraitée'!A:A,"2938*",'Balance N-1 Retraitée'!G:G)) -> 0
A25: r | B25: IMMOBILISATIONS FINANCIERES (D) | C25: =SUM(C26:C29) -> 0 | D25: =SUM(D26:D29) -> 0 | E25: =SUM(E26:E29) -> 0 | G25: =SUM(G26:G29) -> 0
A26: u | B26: * Prêts immobilisés | C26: =SUMIF('Balance N Retraitée'!A:A,"241*",'Balance N Retraitée'!G:G)-SUMIF('Balance N Retraitée'!A:A,"241*",'Balance N Retraitée'!H:H) -> 0 | D26: =(SUMIF('Balance N Retraitée'!A:A,"2941*",'Balance N Retraitée'!H:H)-SUMIF('Balance N Retraitée'!A:A,"2941*",'Balance N Retraitée'!G:G)) -> 0 | E26: =+C26-D26 -> 0 | G26: =(SUMIF('Balance N-1 Retraitée'!A:A,"241*",'Balance N-1 Retraitée'!G:G)-SUMIF('Balance N-1 Retraitée'!A:A,"241*",'Balance N-1 Retraitée'!H:H))-(SUMIF('Balance N-1 Retraitée'!A:A,"2941*",'Balance N-1 Retraitée'!H:H)-SUMIF('Balance N-1 Retraitée'!A:A,"2941*",'Balance N-1 Retraitée'!G:G)) -> 0
A27: e | B27: * Autres créances financières | C27: =SUMIF('Balance N Retraitée'!A:A,"248*",'Balance N Retraitée'!G:G)-SUMIF('Balance N Retraitée'!A:A,"248*",'Balance N Retraitée'!H:H) -> 0 | D27: =(SUMIF('Balance N Retraitée'!A:A,"2948*",'Balance N Retraitée'!H:H)-SUMIF('Balance N Retraitée'!A:A,"2948*",'Balance N Retraitée'!G:G)) -> 0 | E27: =+C27-D27 -> 0 | G27: =(SUMIF('Balance N-1 Retraitée'!A:A,"248*",'Balance N-1 Retraitée'!G:G)-SUMIF('Balance N-1 Retraitée'!A:A,"248*",'Balance N-1 Retraitée'!H:H))-(SUMIF('Balance N-1 Retraitée'!A:A,"2948*",'Balance N-1 Retraitée'!H:H)-SUMIF('Balance N-1 Retraitée'!A:A,"2948*",'Balance N-1 Retraitée'!G:G)) -> 0
A28: l | B28: * Titres de participation | C28: =SUMIF('Balance N Retraitée'!A:A,"251*",'Balance N Retraitée'!G:G)-SUMIF('Balance N Retraitée'!A:A,"251*",'Balance N Retraitée'!H:H) -> 0 | D28: =(SUMIF('Balance N Retraitée'!A:A,"2951*",'Balance N Retraitée'!H:H)-SUMIF('Balance N Retraitée'!A:A,"2951*",'Balance N Retraitée'!G:G)) -> 0 | E28: =+C28-D28 -> 0 | G28: =(SUMIF('Balance N-1 Retraitée'!A:A,"251*",'Balance N-1 Retraitée'!G:G)-SUMIF('Balance N-1 Retraitée'!A:A,"251*",'Balance N-1 Retraitée'!H:H))-(SUMIF('Balance N-1 Retraitée'!A:A,"2951*",'Balance N-1 Retraitée'!H:H)-SUMIF('Balance N-1 Retraitée'!A:A,"2951*",'Balance N-1 Retraitée'!G:G)) -> 0
A29: a | B29: * Autres titres immobilisés | C29: =SUMIF('Balance N Retraitée'!A:A,"258*",'Balance N Retraitée'!G:G)-SUMIF('Balance N Retraitée'!A:A,"258*",'Balance N Retraitée'!H:H) -> 0 | D29: =(SUMIF('Balance N Retraitée'!A:A,"2958*",'Balance N Retraitée'!H:H)-SUMIF('Balance N Retraitée'!A:A,"2958*",'Balance N Retraitée'!G:G)) -> 0 | E29: =+C29-D29 -> 0 | G29: =(SUMIF('Balance N-1 Retraitée'!A:A,"258*",'Balance N-1 Retraitée'!G:G)-SUMIF('Balance N-1 Retraitée'!A:A,"258*",'Balance N-1 Retraitée'!H:H))-(SUMIF('Balance N-1 Retraitée'!A:A,"2958*",'Balance N-1 Retraitée'!H:H)-SUMIF('Balance N-1 Retraitée'!A:A,"2958*",'Balance N-1 Retraitée'!G:G)) -> 0
A30: V | B30: ECARTS DE CONVERSION -ACTIF (E) | C30: 0 | E30: =SUM(E31:E32) -> 0 | G30: =SUM(G31:G32) -> 0
B31: * Diminution des créances immobilisées | C31: =SUMIF('Balance N Retraitée'!A:A,"271*",'Balance N Retraitée'!G:G)-SUMIF('Balance N Retraitée'!A:A,"271*",'Balance N Retraitée'!H:H) -> 0 | E31: =C31 -> 0 | G31: =SUMIF('Balance N-1 Retraitée'!A:A,"271*",'Balance N-1 Retraitée'!G:G)-SUMIF('Balance N-1 Retraitée'!A:A,"271*",'Balance N-1 Retraitée'!H:H) -> 0
B32: * Augmentation des dettes financières | C32: =SUMIF('Balance N Retraitée'!A:A,"272*",'Balance N Retraitée'!G:G)-SUMIF('Balance N Retraitée'!A:A,"272*",'Balance N Retraitée'!H:H) -> 0 | E32: =C32 -> 0 | G32: =SUMIF('Balance N-1 Retraitée'!A:A,"272*",'Balance N-1 Retraitée'!G:G)-SUMIF('Balance N-1 Retraitée'!A:A,"272*",'Balance N-1 Retraitée'!H:H) -> 0
B33: TOTAL I (A+B+C+D+E) | C33: =+C8+C12+C17+C25+C30 -> 1593527.6 | D33: =+D8+D12+D17+D25+D30 -> 173538.13 | E33: =+E8+E12+E17+E25+E30 -> 1419989.4 | G33: =+G8+G12+G17+G25+G30 -> 4305.63
B35: STOCKS (F) | C35: =SUM(C36:C40) -> 0 | D35: =SUM(D36:D40) -> 0 | E35: =SUM(E36:E40) -> 0 | G35: =SUM(G36:G40) -> 0
B36: * Marchandises | C36: =SUMIF('Balance N Retraitée'!A:A,"311*",'Balance N Retraitée'!G:G)-SUMIF('Balance N Retraitée'!A:A,"311*",'Balance N Retraitée'!H:H) -> 0 | D36: =SUMIF('Balance N Retraitée'!A:A,"3911*",'Balance N Retraitée'!H:H)-SUMIF('Balance N Retraitée'!A:A,"3911*",'Balance N Retraitée'!G:G) -> 0 | E36: =+C36-D36 -> 0 | G36: =(SUMIF('Balance N-1 Retraitée'!A:A,"311*",'Balance N-1 Retraitée'!G:G)-SUMIF('Balance N-1 Retraitée'!A:A,"311*",'Balance N-1 Retraitée'!H:H))-(SUMIF('Balance N-1 Retraitée'!A:A,"3911*",'Balance N-1 Retraitée'!H:H)-SUMIF('Balance N-1 Retraitée'!A:A,"3911*",'Balance N-1 Retraitée'!G:G)) -> 0
B37: * Matières et fournitures, consommables | C37: =SUMIF('Balance N Retraitée'!A:A,"312*",'Balance N Retraitée'!G:G)-SUMIF('Balance N Retraitée'!A:A,"312*",'Balance N Retraitée'!H:H) -> 0 | D37: =SUMIF('Balance N Retraitée'!A:A,"3912*",'Balance N Retraitée'!H:H)-SUMIF('Balance N Retraitée'!A:A,"3912*",'Balance N Retraitée'!G:G) -> 0 | E37: =+C37-D37 -> 0 | G37: =(SUMIF('Balance N-1 Retraitée'!A:A,"312*",'Balance N-1 Retraitée'!G:G)-SUMIF('Balance N-1 Retraitée'!A:A,"312*",'Balance N-1 Retraitée'!H:H))-(SUMIF('Balance N-1 Retraitée'!A:A,"3912*",'Balance N-1 Retraitée'!H:H)-SUMIF('Balance N-1 Retraitée'!A:A,"3912*",'Balance N-1 Retraitée'!G:G)) -> 0
B38: * Produits en cours | C38: =SUMIF('Balance N Retraitée'!A:A,"313*",'Balance N Retraitée'!G:G)-SUMIF('Balance N Retraitée'!A:A,"313*",'Balance N Retraitée'!H:H) -> 0 | D38: =SUMIF('Balance N Retraitée'!A:A,"3913*",'Balance N Retraitée'!H:H)-SUMIF('Balance N Retraitée'!A:A,"3913*",'Balance N Retraitée'!G:G) -> 0 | E38: =+C38-D38 -> 0 | G38: =(SUMIF('Balance N-1 Retraitée'!A:A,"313*",'Balance N-1 Retraitée'!G:G)-SUMIF('Balance N-1 Retraitée'!A:A,"313*",'Balance N-1 Retraitée'!H:H))-(SUMIF('Balance N-1 Retraitée'!A:A,"3913*",'Balance N-1 Retraitée'!H:H)-SUMIF('Balance N-1 Retraitée'!A:A,"3913*",'Balance N-1 Retraitée'!G:G)) -> 0
B39: * produits intermédiaires et produits résiduels | C39: =SUMIF('Balance N Retraitée'!A:A,"314*",'Balance N Retraitée'!G:G)-SUMIF('Balance N Retraitée'!A:A,"314*",'Balance N Retraitée'!H:H) -> 0 | D39: =SUMIF('Balance N Retraitée'!A:A,"3914*",'Balance N Retraitée'!H:H)-SUMIF('Balance N Retraitée'!A:A,"3914*",'Balance N Retraitée'!G:G) -> 0 | E39: =+C39-D39 -> 0 | G39: =(SUMIF('Balance N-1 Retraitée'!A:A,"314*",'Balance N-1 Retraitée'!G:G)-SUMIF('Balance N-1 Retraitée'!A:A,"314*",'Balance N-1 Retraitée'!H:H))-(SUMIF('Balance N-1 Retraitée'!A:A,"3914*",'Balance N-1 Retraitée'!H:H)-SUMIF('Balance N-1 Retraitée'!A:A,"3914*",'Balance N-1 Retraitée'!G:G)) -> 0
B40: * Produits finis | C40: =SUMIF('Balance N Retraitée'!A:A,"315*",'Balance N Retraitée'!G:G)-SUMIF('Balance N Retraitée'!A:A,"315*",'Balance N Retraitée'!H:H) -> 0 | D40: =SUMIF('Balance N Retraitée'!A:A,"3915*",'Balance N Retraitée'!H:H)-SUMIF('Balance N Retraitée'!A:A,"3915*",'Balance N Retraitée'!G:G) -> 0 | E40: =+C40-D40 -> 0 | G40: =(SUMIF('Balance N-1 Retraitée'!A:A,"315*",'Balance N-1 Retraitée'!G:G)-SUMIF('Balance N-1 Retraitée'!A:A,"315*",'Balance N-1 Retraitée'!H:H))-(SUMIF('Balance N-1 Retraitée'!A:A,"3915*",'Balance N-1 Retraitée'!H:H)-SUMIF('Balance N-1 Retraitée'!A:A,"3915*",'Balance N-1 Retraitée'!G:G)) -> 0
B41: CREANCES DE L'ACTIF CIRCULANT (G) | C41: =SUM(C42:C48) -> 308800.72 | D41: =SUM(D42:D48) -> 0 | E41: =SUM(E42:E48) -> 308800.72 | G41: =SUM(G42:G48) -> 34.53
B42: * Fournis. débiteurs, avances et acomptes | C42: =SUMIF('Balance N Retraitée'!A:A,"341*",'Balance N Retraitée'!G:G)-SUMIF('Balance N Retraitée'!A:A,"341*",'Balance N Retraitée'!H:H) -> 0 | D42: =SUMIF('Balance N Retraitée'!A:A,"3941*",'Balance N Retraitée'!H:H)-SUMIF('Balance N Retraitée'!A:A,"3941*",'Balance N Retraitée'!G:G) -> 0 | E42: =+C42-D42 -> 0 | G42: =(SUMIF('Balance N-1 Retraitée'!A:A,"341*",'Balance N-1 Retraitée'!G:G)-SUMIF('Balance N-1 Retraitée'!A:A,"341*",'Balance N-1 Retraitée'!H:H))-(SUMIF('Balance N-1 Retraitée'!A:A,"3941*",'Balance N-1 Retraitée'!H:H)-SUMIF('Balance N-1 Retraitée'!A:A,"3941*",'Balance N-1 Retraitée'!G:G)) -> 0
B43: * Clients et comptes rattachés | C43: =SUMIF('Balance N Retraitée'!A:A,"342*",'Balance N Retraitée'!G:G)-SUMIF('Balance N Retraitée'!A:A,"342*",'Balance N Retraitée'!H:H) -> 288000 | D43: =SUMIF('Balance N Retraitée'!A:A,"3942*",'Balance N Retraitée'!H:H)-SUMIF('Balance N Retraitée'!A:A,"3942*",'Balance N Retraitée'!G:G) -> 0 | E43: =+C43-D43 -> 288000 | G43: =(SUMIF('Balance N-1 Retraitée'!A:A,"342*",'Balance N-1 Retraitée'!G:G)-SUMIF('Balance N-1 Retraitée'!A:A,"342*",'Balance N-1 Retraitée'!H:H))-(SUMIF('Balance N-1 Retraitée'!A:A,"3942*",'Balance N-1 Retraitée'!H:H)-SUMIF('Balance N-1 Retraitée'!A:A,"3942*",'Balance N-1 Retraitée'!G:G)) -> 0
B44: * Personnel | C44: =SUMIF('Balance N Retraitée'!A:A,"343*",'Balance N Retraitée'!G:G)-SUMIF('Balance N Retraitée'!A:A,"343*",'Balance N Retraitée'!H:H) -> 0 | D44: =SUMIF('Balance N Retraitée'!A:A,"3943*",'Balance N Retraitée'!H:H)-SUMIF('Balance N Retraitée'!A:A,"3943*",'Balance N Retraitée'!G:G) -> 0 | E44: =+C44-D44 -> 0 | G44: =(SUMIF('Balance N-1 Retraitée'!A:A,"343*",'Balance N-1 Retraitée'!G:G)-SUMIF('Balance N-1 Retraitée'!A:A,"343*",'Balance N-1 Retraitée'!H:H))-(SUMIF('Balance N-1 Retraitée'!A:A,"3943*",'Balance N-1 Retraitée'!H:H)-SUMIF('Balance N-1 Retraitée'!A:A,"3943*",'Balance N-1 Retraitée'!G:G)) -> 0
B45: * Etat | C45: =SUMIF('Balance N Retraitée'!A:A,"345*",'Balance N Retraitée'!G:G)-SUMIF('Balance N Retraitée'!A:A,"345*",'Balance N Retraitée'!H:H) -> 20800.72 | D45: =SUMIF('Balance N Retraitée'!A:A,"3945*",'Balance N Retraitée'!H:H)-SUMIF('Balance N Retraitée'!A:A,"3945*",'Balance N Retraitée'!G:G) -> 0 | E45: =+C45-D45 -> 20800.72 | G45: =(SUMIF('Balance N-1 Retraitée'!A:A,"345*",'Balance N-1 Retraitée'!G:G)-SUMIF('Balance N-1 Retraitée'!A:A,"345*",'Balance N-1 Retraitée'!H:H))-(SUMIF('Balance N-1 Retraitée'!A:A,"3945*",'Balance N-1 Retraitée'!H:H)-SUMIF('Balance N-1 Retraitée'!A:A,"3945*",'Balance N-1 Retraitée'!G:G)) -> 34.53
B46: * Comptes d'associés | C46: =SUMIF('Balance N Retraitée'!A:A,"346*",'Balance N Retraitée'!G:G)-SUMIF('Balance N Retraitée'!A:A,"346*",'Balance N Retraitée'!H:H) -> 0 | D46: =SUMIF('Balance N Retraitée'!A:A,"3946*",'Balance N Retraitée'!H:H)-SUMIF('Balance N Retraitée'!A:A,"3946*",'Balance N Retraitée'!G:G) -> 0 | E46: =+C46-D46 -> 0 | G46: =(SUMIF('Balance N-1 Retraitée'!A:A,"346*",'Balance N-1 Retraitée'!G:G)-SUMIF('Balance N-1 Retraitée'!A:A,"346*",'Balance N-1 Retraitée'!H:H))-(SUMIF('Balance N-1 Retraitée'!A:A,"3946*",'Balance N-1 Retraitée'!H:H)-SUMIF('Balance N-1 Retraitée'!A:A,"3946*",'Balance N-1 Retraitée'!G:G)) -> 0
B47: * Autres débiteurs | C47: =SUMIF('Balance N Retraitée'!A:A,"348*",'Balance N Retraitée'!G:G)-SUMIF('Balance N Retraitée'!A:A,"348*",'Balance N Retraitée'!H:H) -> 0 | D47: =SUMIF('Balance N Retraitée'!A:A,"3948*",'Balance N Retraitée'!H:H)-SUMIF('Balance N Retraitée'!A:A,"3948*",'Balance N Retraitée'!G:G) -> 0 | E47: =+C47-D47 -> 0 | G47: =(SUMIF('Balance N-1 Retraitée'!A:A,"348*",'Balance N-1 Retraitée'!G:G)-SUMIF('Balance N-1 Retraitée'!A:A,"348*",'Balance N-1 Retraitée'!H:H))-(SUMIF('Balance N-1 Retraitée'!A:A,"3948*",'Balance N-1 Retraitée'!H:H)-SUMIF('Balance N-1 Retraitée'!A:A,"3948*",'Balance N-1 Retraitée'!G:G)) -> 0
B48: * Comptes de régularisation-Actif | C48: =SUMIF('Balance N Retraitée'!A:A,"349*",'Balance N Retraitée'!G:G)-SUMIF('Balance N Retraitée'!A:A,"349*",'Balance N Retraitée'!H:H) -> 0 | D48: =SUMIF('Balance N Retraitée'!A:A,"3949*",'Balance N Retraitée'!H:H)-SUMIF('Balance N Retraitée'!A:A,"3949*",'Balance N Retraitée'!G:G) -> 0 | E48: =+C48-D48 -> 0 | G48: =(SUMIF('Balance N-1 Retraitée'!A:A,"349*",'Balance N-1 Retraitée'!G:G)-SUMIF('Balance N-1 Retraitée'!A:A,"349*",'Balance N-1 Retraitée'!H:H))-(SUMIF('Balance N-1 Retraitée'!A:A,"3949*",'Balance N-1 Retraitée'!H:H)-SUMIF('Balance N-1 Retraitée'!A:A,"3949*",'Balance N-1 Retraitée'!G:G)) -> 0
B49: TITRES VALEURS DE PLACEMENT ( H) | C49: =SUMIF('Balance N Retraitée'!A:A,"35*",'Balance N Retraitée'!G:G)-SUMIF('Balance N Retraitée'!A:A,"35*",'Balance N Retraitée'!H:H) -> 0 | D49: =SUMIF('Balance N Retraitée'!A:A,"3912*",'Balance N Retraitée'!H:H)-SUMIF('Balance N Retraitée'!A:A,"3912*",'Balance N Retraitée'!G:G) -> 0 | E49: =C49-D49 -> 0 | G49: =(SUMIF('Balance N-1 Retraitée'!A:A,"35*",'Balance N-1 Retraitée'!G:G)-SUMIF('Balance N-1 Retraitée'!A:A,"35*",'Balance N-1 Retraitée'!H:H))-(SUMIF('Balance N-1 Retraitée'!A:A,"395*",'Balance N-1 Retraitée'!H:H)-SUMIF('Balance N-1 Retraitée'!A:A,"395*",'Balance N-1 Retraitée'!G:G)) -> 0
B50: ECARTS DE CONVERSION-ACTIF ( I ) | C50: =C51 -> 0 | E50: =E51 -> 0 | G50: =G51 -> 0
B51: . (Eléments circulants) | C51: =SUMIF('Balance N Retraitée'!A:A,"37*",'Balance N Retraitée'!G:G)-SUMIF('Balance N Retraitée'!A:A,"37*",'Balance N Retraitée'!H:H) -> 0 | E51: =+C51-D51 -> 0 | G51: =(SUMIF('Balance N-1 Retraitée'!A:A,"37*",'Balance N-1 Retraitée'!G:G)-SUMIF('Balance N-1 Retraitée'!A:A,"37*",'Balance N-1 Retraitée'!H:H)) -> 0
B52: TOTAL II ( F+G+H+I ) | C52: =C35+C41+C49+C50 -> 308800.72 | D52: =D35+D41+D49+D50 -> 0 | E52: =E35+E41+E49+E50 -> 308800.72 | G52: =G35+G41+G49+G50 -> 34.53
C53: =SUMIF('Balance N Retraitée'!A:A,"311*",'Balance N Retraitée'!G:G)-SUMIF('Balance N Retraitée'!A:A,"311*",'Balance N Retraitée'!H:H) -> 0 | G53: =(SUMIF('Balance N-1 Retraitée'!A:A,"311*",'Balance N-1 Retraitée'!G:G)-SUMIF('Balance N-1 Retraitée'!A:A,"311*",'Balance N-1 Retraitée'!H:H))-(SUMIF('Balance N-1 Retraitée'!A:A,"3911*",'Balance N-1 Retraitée'!G:G)-SUMIF('Balance N-1 Retraitée'!A:A,"3911*",'Balance N-1 Retraitée'!H:H)) -> 0
B54: TRESORERIE-ACTIF | C54: =SUM(C55:C57) -> 492.54 | D54: =SUM(D55:D57) -> 0 | E54: =SUM(E55:E57) -> 492.54 | G54: =SUM(G55:G57) -> 311745.67
B55: * Chéques et valeurs à encaisser | C55: =SUMIF('Balance N Retraitée'!A:A,"511*",'Balance N Retraitée'!G:G)-SUMIF('Balance N Retraitée'!A:A,"511*",'Balance N Retraitée'!H:H) -> 0 | D55: =SUMIF('Balance N Retraitée'!A:A,"5911*",'Balance N Retraitée'!H:H)-SUMIF('Balance N Retraitée'!A:A,"5911*",'Balance N Retraitée'!G:G) -> 0 | E55: =+C55-D55 -> 0 | G55: =(SUMIF('Balance N-1 Retraitée'!A:A,"511*",'Balance N-1 Retraitée'!G:G)-SUMIF('Balance N-1 Retraitée'!A:A,"511*",'Balance N-1 Retraitée'!H:H))-(SUMIF('Balance N-1 Retraitée'!A:A,"5911*",'Balance N-1 Retraitée'!H:H)-SUMIF('Balance N-1 Retraitée'!A:A,"5911*",'Balance N-1 Retraitée'!G:G)) -> 0
B56: * Banques, TG et CCP | C56: =SUMIF('Balance N Retraitée'!A:A,"514*",'Balance N Retraitée'!G:G)+SUMIF('Balance N Retraitée'!A:A,"554*",'Balance N Retraitée'!G:G) -> 323.11 | D56: =SUMIF('Balance N Retraitée'!A:A,"5914*",'Balance N Retraitée'!H:H)-SUMIF('Balance N Retraitée'!A:A,"5914*",'Balance N Retraitée'!G:G) -> 0 | E56: =+C56-D56 -> 323.11 | G56: =(SUMIF('Balance N-1 Retraitée'!A:A,"514*",'Balance N-1 Retraitée'!G:G)+SUMIF('Balance N-1 Retraitée'!A:A,"554*",'Balance N-1 Retraitée'!G:G))-(SUMIF('Balance N-1 Retraitée'!A:A,"5914*",'Balance N-1 Retraitée'!H:H)-SUMIF('Balance N-1 Retraitée'!A:A,"5914*",'Balance N-1 Retraitée'!G:G)) -> 222845.67
B57: * Caisse, Régie d'avances et accréditifs | C57: =SUMIF('Balance N Retraitée'!A:A,"516*",'Balance N Retraitée'!G:G)-SUMIF('Balance N Retraitée'!A:A,"516*",'Balance N Retraitée'!H:H) -> 169.43 | D57: =SUMIF('Balance N Retraitée'!A:A,"5911*",'Balance N Retraitée'!H:H)-SUMIF('Balance N Retraitée'!A:A,"5911*",'Balance N Retraitée'!G:G) -> 0 | E57: =+C57-D57 -> 169.43 | G57: =(SUMIF('Balance N-1 Retraitée'!A:A,"516*",'Balance N-1 Retraitée'!G:G)-SUMIF('Balance N-1 Retraitée'!A:A,"516*",'Balance N-1 Retraitée'!H:H))-(SUMIF('Balance N-1 Retraitée'!A:A,"5916*",'Balance N-1 Retraitée'!H:H)-SUMIF('Balance N-1 Retraitée'!A:A,"5916*",'Balance N-1 Retraitée'!G:G)) -> 88900
B58: TOTAL III | C58: =C54 -> 492.54 | D58: =D54 -> 0 | E58: =E54 -> 492.54 | G58: =G54 -> 311745.67
B60: TOTAL GENERAL I+II+III | C60: =C33+C52+C58 -> 1902820.8 | D60: =D33+D52+D58 -> 173538.13 | E60: =E33+E52+E58 -> 1729282.7 | G60: =G33+G52+G58 -> 316085.83
E61: =+E60-E122 -> 0 | G61: =+G60-G122 -> 0
A63: Tableau n° 1
C64: BILAN (PASSIF)
C65: (modèle normal) | E65: Exercice clos le : | G65: =G3 -> 31/12/2022
B66: PASSIF | E66: Exercice | G66: Exercice
B67: CAPITAUX PROPRES | C67: =SUM(C68:C70) -> 0
B68: * Capital social ou personnel (1) | E68: =SUMIF('Balance N Retraitée'!$A:$A,"111*",'Balance N Retraitée'!$H:$H)-SUMIF('Balance N Retraitée'!$A:$A,"111*",'Balance N Retraitée'!$G:$G)-E69 -> 100000 | G68: =SUMIF('Balance N-1 Retraitée'!$A:$A,"111*",'Balance N-1 Retraitée'!$H:$H)-SUMIF('Balance N-1 Retraitée'!$A:$A,"111*",'Balance N-1 Retraitée'!$G:$G)-G69 -> 100000
B69: * Moins : actionnaires, caital souscrit non applé | E69: =SUMIF('Balance N Retraitée'!$A:$A,"1119*",'Balance N Retraitée'!$H:$H)-SUMIF('Balance N Retraitée'!$A:$A,"1119*",'Balance N Retraitée'!$G:$G) -> 0 | G69: =SUMIF('Balance N-1 Retraitée'!$A:$A,"1119*",'Balance N-1 Retraitée'!$H:$H)-SUMIF('Balance N-1 Retraitée'!$A:$A,"1119*",'Balance N-1 Retraitée'!$G:$G) -> 0
B70: * Capital appelé, dont versé
B71: * Primes d'émission, de fusion, d'apport | E71: =SUMIF('Balance N Retraitée'!$A:$A,"112*",'Balance N Retraitée'!$H:$H)-SUMIF('Balance N Retraitée'!$A:$A,"112*",'Balance N Retraitée'!$G:$G) -> 0 | G71: =SUMIF('Balance N-1 Retraitée'!$A:$A,"112*",'Balance N-1 Retraitée'!$H:$H)-SUMIF('Balance N-1 Retraitée'!$A:$A,"112*",'Balance N-1 Retraitée'!$G:$G) -> 0
B72: * Ecart de réévaluation | E72: =SUMIF('Balance N Retraitée'!$A:$A,"113*",'Balance N Retraitée'!$H:$H)-SUMIF('Balance N Retraitée'!$A:$A,"113*",'Balance N Retraitée'!$G:$G) -> 0 | G72: =SUMIF('Balance N-1 Retraitée'!$A:$A,"113*",'Balance N-1 Retraitée'!$H:$H)-SUMIF('Balance N-1 Retraitée'!$A:$A,"113*",'Balance N-1 Retraitée'!$G:$G) -> 0
B73: * Réserve légale | E73: =SUMIF('Balance N Retraitée'!$A:$A,"114*",'Balance N Retraitée'!$H:$H)-SUMIF('Balance N Retraitée'!$A:$A,"114*",'Balance N Retraitée'!$G:$G) -> 0 | G73: =SUMIF('Balance N-1 Retraitée'!$A:$A,"114*",'Balance N-1 Retraitée'!$H:$H)-SUMIF('Balance N-1 Retraitée'!$A:$A,"114*",'Balance N-1 Retraitée'!$G:$G) -> 0
B74: * Autres Réserves | E74: =SUMIF('Balance N Retraitée'!$A:$A,"115*",'Balance N Retraitée'!$H:$H)-SUMIF('Balance N Retraitée'!$A:$A,"115*",'Balance N Retraitée'!$G:$G) -> 0 | G74: =SUMIF('Balance N-1 Retraitée'!$A:$A,"115*",'Balance N-1 Retraitée'!$H:$H)-SUMIF('Balance N-1 Retraitée'!$A:$A,"115*",'Balance N-1 Retraitée'!$G:$G) -> 0
B75: * Report à nouveau (2) | E75: =SUMIF('Balance N Retraitée'!$A:$A,"116*",'Balance N Retraitée'!$H:$H)-SUMIF('Balance N Retraitée'!$A:$A,"116*",'Balance N Retraitée'!$G:$G) -> -18918.67 | G75: =SUMIF('Balance N-1 Retraitée'!$A:$A,"116*",'Balance N-1 Retraitée'!$H:$H)-SUMIF('Balance N-1 Retraitée'!$A:$A,"116*",'Balance N-1 Retraitée'!$G:$G) -> 0
B76: * Résultats nets en instance d'affectation (2) | E76: =SUMIF('Balance N Retraitée'!$A:$A,"118*",'Balance N Retraitée'!$H:$H)-SUMIF('Balance N Retraitée'!$A:$A,"118*",'Balance N Retraitée'!$G:$G) -> 0 | G76: =SUMIF('Balance N-1 Retraitée'!$A:$A,"118*",'Balance N-1 Retraitée'!$H:$H)-SUMIF('Balance N-1 Retraitée'!$A:$A,"118*",'Balance N-1 Retraitée'!$G:$G) -> 0
B77: * Résultat net de l'exercice (2) | E77: =+'T2 CPC'!F72 -> 21452.44 | G77: =+'T2 CPC'!G72 -> -18918.67
D78: Total des capitaux propres (A) | E78: =SUM(E68:E77) -> 102533.77 | G78: =SUM(G68:G77) -> 81081.33
B79: CAPITAUX PROPRES ASSIMILES | C79: =SUM(C80:C82) -> 0 | D79: (B) | E79: =SUM(E80:E85) -> 0 | G79: =SUM(G80:G85) -> 0
B80: * Subvensions d'investissement | E80: =SUMIF('Balance N Retraitée'!$A:$A,"131*",'Balance N Retraitée'!$H:$H)-SUMIF('Balance N Retraitée'!$A:$A,"131*",'Balance N Retraitée'!$G:$G) -> 0 | G80: =SUMIF('Balance N-1 Retraitée'!$A:$A,"131*",'Balance N-1 Retraitée'!$H:$H)-SUMIF('Balance N-1 Retraitée'!$A:$A,"131*",'Balance N-1 Retraitée'!$G:$G) -> 0
B81: * Provisions réglementées | E81: =SUMIF('Balance N Retraitée'!$A:$A,"135*",'Balance N Retraitée'!$H:$H)-SUMIF('Balance N Retraitée'!$A:$A,"135*",'Balance N Retraitée'!$G:$G) -> 0 | G81: =SUMIF('Balance N-1 Retraitée'!$A:$A,"135*",'Balance N-1 Retraitée'!$H:$H)-SUMIF('Balance N-1 Retraitée'!$A:$A,"135*",'Balance N-1 Retraitée'!$G:$G) -> 0
B86: DETTES DE FINANCEMENT | C86: =SUM(C87:C89) -> 0 | D86: (C) | E86: =SUM(E87:E92) -> 1005415.6 | G86: =SUM(G87:G92) -> 0
B87: * Emprunts obligataires | E87: =SUMIF('Balance N Retraitée'!$A:$A,"141*",'Balance N Retraitée'!$H:$H)-SUMIF('Balance N Retraitée'!$A:$A,"141*",'Balance N Retraitée'!$G:$G) -> 0 | G87: =SUMIF('Balance N-1 Retraitée'!$A:$A,"141*",'Balance N-1 Retraitée'!$H:$H)-SUMIF('Balance N-1 Retraitée'!$A:$A,"141*",'Balance N-1 Retraitée'!$G:$G) -> 0
B88: * Autres dettes de financement | E88: =SUMIF('Balance N Retraitée'!$A:$A,"148*",'Balance N Retraitée'!$H:$H)-SUMIF('Balance N Retraitée'!$A:$A,"148*",'Balance N Retraitée'!$G:$G) -> 1005415.6 | G88: =SUMIF('Balance N-1 Retraitée'!$A:$A,"148*",'Balance N-1 Retraitée'!$H:$H)-SUMIF('Balance N-1 Retraitée'!$A:$A,"148*",'Balance N-1 Retraitée'!$G:$G) -> 0
B93: PROVISIONS DURABLES POUR RISQUE ET CHARGES | C93: =SUM(C94:C96) -> 0 | D93: (D) | E93: =SUM(E94:E96) -> 0 | G93: =SUM(G94:G96) -> 0
B94: * Provisions pour risques | E94: =SUMIF('Balance N Retraitée'!$A:$A,"151*",'Balance N Retraitée'!$H:$H)-SUMIF('Balance N Retraitée'!$A:$A,"151*",'Balance N Retraitée'!$G:$G) -> 0 | G94: =SUMIF('Balance N-1 Retraitée'!$A:$A,"151*",'Balance N-1 Retraitée'!$H:$H)-SUMIF('Balance N-1 Retraitée'!$A:$A,"151*",'Balance N-1 Retraitée'!$G:$G) -> 0
B95: * Provisions pour charges | E95: =SUMIF('Balance N Retraitée'!$A:$A,"155*",'Balance N Retraitée'!$H:$H)-SUMIF('Balance N Retraitée'!$A:$A,"155*",'Balance N Retraitée'!$G:$G) -> 0 | G95: =SUMIF('Balance N-1 Retraitée'!$A:$A,"155*",'Balance N-1 Retraitée'!$H:$H)-SUMIF('Balance N-1 Retraitée'!$A:$A,"155*",'Balance N-1 Retraitée'!$G:$G) -> 0
B97: ECRATS DE CONVERSION - PASSIF | C97: =SUM(C98:C100) -> 0 | D97: (E) | E97: =SUM(E98:E100) -> 0 | G97: =SUM(G98:G100) -> 0
B98: * Augmentation des créances immobilisées | E98: =SUMIF('Balance N Retraitée'!$A:$A,"171*",'Balance N Retraitée'!$H:$H)-SUMIF('Balance N Retraitée'!$A:$A,"171*",'Balance N Retraitée'!$G:$G) -> 0 | G98: =SUMIF('Balance N-1 Retraitée'!$A:$A,"171*",'Balance N-1 Retraitée'!$H:$H)-SUMIF('Balance N-1 Retraitée'!$A:$A,"171*",'Balance N-1 Retraitée'!$G:$G) -> 0
B99: * Diminution des dettes de financement | E99: =SUMIF('Balance N Retraitée'!$A:$A,"172*",'Balance N Retraitée'!$H:$H)-SUMIF('Balance N Retraitée'!$A:$A,"172*",'Balance N Retraitée'!$G:$G) -> 0 | G99: =SUMIF('Balance N-1 Retraitée'!$A:$A,"172*",'Balance N-1 Retraitée'!$H:$H)-SUMIF('Balance N-1 Retraitée'!$A:$A,"172*",'Balance N-1 Retraitée'!$G:$G) -> 0
D101: Total I ( A + B + C + D + E ) | E101: =+E78+E79+E86+E93+E97 -> 1107949.4 | G101: =+G78+G79+G86+G93+G97 -> 81081.33
B103: DETTES DU PASSIF CIRCULANT | C103: =SUM(C104:C106) -> 0 | D103: (F) | E103: =SUM(E104:E111) -> 621333.33 | G103: =SUM(G104:G111) -> 235004.5
B104: * Fournisseurs et comptes rattachés | E104: =SUMIF('Balance N Retraitée'!$A:$A,"441*",'Balance N Retraitée'!$H:$H)-SUMIF('Balance N Retraitée'!$A:$A,"441*",'Balance N Retraitée'!$G:$G) -> 7573.2 | G104: =SUMIF('Balance N-1 Retraitée'!$A:$A,"441*",'Balance N-1 Retraitée'!$H:$H)-SUMIF('Balance N-1 Retraitée'!$A:$A,"441*",'Balance N-1 Retraitée'!$G:$G) -> 0
B105: * Clients créditeurs, avances et acomptes | E105: =SUMIF('Balance N Retraitée'!$A:$A,"442*",'Balance N Retraitée'!$H:$H)-SUMIF('Balance N Retraitée'!$A:$A,"442*",'Balance N Retraitée'!$G:$G) -> 0 | G105: =SUMIF('Balance N-1 Retraitée'!$A:$A,"442*",'Balance N-1 Retraitée'!$H:$H)-SUMIF('Balance N-1 Retraitée'!$A:$A,"442*",'Balance N-1 Retraitée'!$G:$G) -> 0
B106: * Personnel | E106: =SUMIF('Balance N Retraitée'!$A:$A,"443*",'Balance N Retraitée'!$H:$H)-SUMIF('Balance N Retraitée'!$A:$A,"443*",'Balance N Retraitée'!$G:$G) -> 0 | G106: =SUMIF('Balance N-1 Retraitée'!$A:$A,"443*",'Balance N-1 Retraitée'!$H:$H)-SUMIF('Balance N-1 Retraitée'!$A:$A,"443*",'Balance N-1 Retraitée'!$G:$G) -> 0
B107: * Organismes sociaux | E107: =SUMIF('Balance N Retraitée'!$A:$A,"444*",'Balance N Retraitée'!$H:$H)-SUMIF('Balance N Retraitée'!$A:$A,"444*",'Balance N Retraitée'!$G:$G) -> 796.02 | G107: =SUMIF('Balance N-1 Retraitée'!$A:$A,"444*",'Balance N-1 Retraitée'!$H:$H)-SUMIF('Balance N-1 Retraitée'!$A:$A,"444*",'Balance N-1 Retraitée'!$G:$G) -> 1391.5
B108: * Etat | E108: =SUMIF('Balance N Retraitée'!$A:$A,"445*",'Balance N Retraitée'!$H:$H)-SUMIF('Balance N Retraitée'!$A:$A,"445*",'Balance N Retraitée'!$G:$G) -> 53001.82 | G108: =SUMIF('Balance N-1 Retraitée'!$A:$A,"445*",'Balance N-1 Retraitée'!$H:$H)-SUMIF('Balance N-1 Retraitée'!$A:$A,"445*",'Balance N-1 Retraitée'!$G:$G) -> 88
B109: * Comptes d'associés | E109: =SUMIF('Balance N Retraitée'!$A:$A,"446*",'Balance N Retraitée'!$H:$H)-SUMIF('Balance N Retraitée'!$A:$A,"446*",'Balance N Retraitée'!$G:$G) -> 559962.29 | G109: =SUMIF('Balance N-1 Retraitée'!$A:$A,"446*",'Balance N-1 Retraitée'!$H:$H)-SUMIF('Balance N-1 Retraitée'!$A:$A,"446*",'Balance N-1 Retraitée'!$G:$G) -> 233525
B110: * Autres créanciers | E110: =SUMIF('Balance N Retraitée'!$A:$A,"448*",'Balance N Retraitée'!$H:$H)-SUMIF('Balance N Retraitée'!$A:$A,"448*",'Balance N Retraitée'!$G:$G) -> 0 | G110: =SUMIF('Balance N-1 Retraitée'!$A:$A,"448*",'Balance N-1 Retraitée'!$H:$H)-SUMIF('Balance N-1 Retraitée'!$A:$A,"448*",'Balance N-1 Retraitée'!$G:$G) -> 0
B111: * Comptes de régularisation passif | E111: =SUMIF('Balance N Retraitée'!$A:$A,"449*",'Balance N Retraitée'!$H:$H)-SUMIF('Balance N Retraitée'!$A:$A,"449*",'Balance N Retraitée'!$G:$G) -> 0 | G111: =SUMIF('Balance N-1 Retraitée'!$A:$A,"449*",'Balance N-1 Retraitée'!$H:$H)-SUMIF('Balance N-1 Retraitée'!$A:$A,"449*",'Balance N-1 Retraitée'!$G:$G) -> 0
B112: AUTRES PROVISIONS POUR RISQUES ET CHARGES | D112: (G) | E112: =SUMIF('Balance N Retraitée'!$A:$A,"45*",'Balance N Retraitée'!$H:$H)-SUMIF('Balance N Retraitée'!$A:$A,"45*",'Balance N Retraitée'!$G:$G) -> 0 | G112: =SUMIF('Balance N-1 Retraitée'!$A:$A,"45*",'Balance N-1 Retraitée'!$H:$H)-SUMIF('Balance N-1 Retraitée'!$A:$A,"45*",'Balance N-1 Retraitée'!$G:$G) -> 0
B113: ECARTS DE CONVERSION - PASSIF (Eléments circulants) | D113: (H) | E113: =SUMIF('Balance N Retraitée'!$A:$A,"47*",'Balance N Retraitée'!$H:$H)-SUMIF('Balance N Retraitée'!$A:$A,"47*",'Balance N Retraitée'!$G:$G) -> 0 | G113: =SUMIF('Balance N-1 Retraitée'!$A:$A,"47*",'Balance N-1 Retraitée'!$H:$H)-SUMIF('Balance N-1 Retraitée'!$A:$A,"47*",'Balance N-1 Retraitée'!$G:$G) -> 0
D114: Total II (F + G + H ) | E114: =+E103+E112+E113 -> 621333.33 | G114: =+G103+G112+G113 -> 235004.5
...

Sheet T2 CPC
A1: Tableau n° 2
A2: COMPTE DE PRODUITS ET CHARGES (hors taxes)
A3: (modèle normal)
D4: Exercice du : | E4: =+Couverture!C15 -> 44562 | F4: =+Couverture!E15 -> 31/12/2022
D5: OPERATIONS
D6: Propres à l'exercice | E6: concernant les | F6: TOTAUX DE | G6: TOTAUX DE
C7: NATURE | E7: exercices précédent | F7: L'EXERCICE | G7: L'EXERCICE
G8: PRECEDENT
D10: 1 | E10: 2 | F10: 3=2+1
A11: E | B11: I | C11: PRODUITS D'EXPLOITATION | D11: =SUM(D12:D18) -> 381666.67 | E11: =SUM(E12:E18) -> 0 | F11: =SUM(F12:F18) -> 381666.67 | G11: =SUM(G12:G18) -> 0
A12: X | C12: * Ventes de marchandises (en l'état) | D12: =SUMIF('Balance N Retraitée'!A:A,"711*",'Balance N Retraitée'!H:H)-SUMIF('Balance N Retraitée'!A:A,"711*",'Balance N Retraitée'!G:G)-E12 -> 0 | E12: =SUMIF('Balance N Retraitée'!A:A,"7118*",'Balance N Retraitée'!H:H)-SUMIF('Balance N Retraitée'!A:A,"7118*",'Balance N Retraitée'!G:G) -> 0 | F12: =+D12+E12 -> 0 | G12: =SUMIF('Balance N-1 Retraitée'!A:A,"711*",'Balance N-1 Retraitée'!H:H)-SUMIF('Balance N-1 Retraitée'!A:A,"711*",'Balance N-1 Retraitée'!G:G) -> 0
A13: P | C13: * Ventes de biens et services produits chiffre d'affaires | D13: =SUMIF('Balance N Retraitée'!A:A,"712*",'Balance N Retraitée'!H:H)-SUMIF('Balance N Retraitée'!A:A,"712*",'Balance N Retraitée'!G:G) -> 381666.67 | E13: =(SUMIF('Balance N Retraitée'!A:A,"7128*",'Balance N Retraitée'!H:H)-SUMIF('Balance N Retraitée'!A:A,"7128*",'Balance N Retraitée'!G:G))+(SUMIF('Balance N Retraitée'!A:A,"71298*",'Balance N Retraitée'!H:H)-SUMIF('Balance N Retraitée'!A:A,"71298*",'Balance N Retraitée'!G:G)) -> 0 | F13: =+D13+E13 -> 381666.67 | G13: =SUMIF('Balance N-1 Retraitée'!A:A,"712*",'Balance N-1 Retraitée'!H:H)-SUMIF('Balance N-1 Retraitée'!A:A,"712*",'Balance N-1 Retraitée'!G:G) -> 0
A14: L | C14: * Variation des stocks de produits (1) | D14: =SUMIF('Balance N Retraitée'!A:A,"713*",'Balance N Retraitée'!H:H)-SUMIF('Balance N Retraitée'!A:A,"713*",'Balance N Retraitée'!G:G)-E14 -> 0 | F14: =+D14+E14 -> 0 | G14: =SUMIF('Balance N-1 Retraitée'!A:A,"713*",'Balance N-1 Retraitée'!H:H)-SUMIF('Balance N-1 Retraitée'!A:A,"713*",'Balance N-1 Retraitée'!G:G) -> 0
A15: O | C15: * Immobilisations produites par l'entreprise pour elle-même | D15: =SUMIF('Balance N Retraitée'!A:A,"714*",'Balance N Retraitée'!H:H)-SUMIF('Balance N Retraitée'!A:A,"714*",'Balance N Retraitée'!G:G)-E15 -> 0 | E15: =SUMIF('Balance N Retraitée'!A:A,"7148*",'Balance N Retraitée'!H:H)-SUMIF('Balance N Retraitée'!A:A,"7148*",'Balance N Retraitée'!G:G) -> 0 | F15: =+D15+E15 -> 0 | G15: =SUMIF('Balance N-1 Retraitée'!A:A,"714*",'Balance N-1 Retraitée'!H:H)-SUMIF('Balance N-1 Retraitée'!A:A,"714*",'Balance N-1 Retraitée'!G:G) -> 0
A16: I | C16: * Subventions d'exploitation | D16: =SUMIF('Balance N Retraitée'!A:A,"716*",'Balance N Retraitée'!H:H)-SUMIF('Balance N Retraitée'!A:A,"716*",'Balance N Retraitée'!G:G)-E16 -> 0 | E16: =SUMIF('Balance N Retraitée'!A:A,"7168*",'Balance N Retraitée'!H:H)-SUMIF('Balance N Retraitée'!A:A,"7168*",'Balance N Retraitée'!G:G) -> 0 | F16: =+D16+E16 -> 0 | G16: =SUMIF('Balance N-1 Retraitée'!A:A,"716*",'Balance N-1 Retraitée'!H:H)-SUMIF('Balance N-1 Retraitée'!A:A,"716*",'Balance N-1 Retraitée'!G:G) -> 0
A17: T | C17: * Autres produits d'exploitation | D17: =SUMIF('Balance N Retraitée'!A:A,"718*",'Balance N Retraitée'!H:H)-SUMIF('Balance N Retraitée'!A:A,"718*",'Balance N Retraitée'!G:G)-E17 -> 0 | E17: =SUMIF('Balance N Retraitée'!A:A,"7188*",'Balance N Retraitée'!H:H)-SUMIF('Balance N Retraitée'!A:A,"7188*",'Balance N Retraitée'!G:G) -> 0 | F17: =+D17+E17 -> 0 | G17: =SUMIF('Balance N-1 Retraitée'!A:A,"718*",'Balance N-1 Retraitée'!H:H)-SUMIF('Balance N-1 Retraitée'!A:A,"718*",'Balance N-1 Retraitée'!G:G) -> 0
A18: A | C18: * Reprises d'exploitation; Transsferts de charges | D18: =SUMIF('Balance N Retraitée'!A:A,"719*",'Balance N Retraitée'!H:H)-SUMIF('Balance N Retraitée'!A:A,"719*",'Balance N Retraitée'!G:G)-E18 -> 0 | E18: =SUMIF('Balance N Retraitée'!A:A,"7198*",'Balance N Retraitée'!H:H)-SUMIF('Balance N Retraitée'!A:A,"7198*",'Balance N Retraitée'!G:G) -> 0 | F18: =+D18+E18 -> 0 | G18: =SUMIF('Balance N-1 Retraitée'!A:A,"719*",'Balance N-1 Retraitée'!H:H)-SUMIF('Balance N-1 Retraitée'!A:A,"719*",'Balance N-1 Retraitée'!G:G) -> 0
A19: T | C19: Total I | D19: =ROUND(SUM(D12:D18),2) -> 381666.67 | E19: =ROUND(SUM(E12:E18),2) -> 0 | F19: =ROUND(SUM(F12:F18),2) -> 381666.67 | G19: =ROUND(SUM(G12:G18),2) -> 0
A20: I | B20: II | C20: CHARGES D'EXPLOITATION | D20: =SUM(D21:D27) -> 313873.12 | E20: =SUM(E21:E27) -> 0 | F20: =SUM(F21:F27) -> 313873.12 | G20: =SUM(G21:G27) -> 18918.67
A21: O | C21: * Achats revendus(2) de marchandises | D21: =SUMIF('Balance N Retraitée'!A:A,"611*",'Balance N Retraitée'!G:G)-SUMIF('Balance N Retraitée'!A:A,"611*",'Balance N Retraitée'!H:H)-E21 -> 0 | E21: =SUMIF('Balance N Retraitée'!A:A,"6118*",'Balance N Retraitée'!G:G)-SUMIF('Balance N Retraitée'!A:A,"6118*",'Balance N Retraitée'!H:H) -> 0 | F21: =+D21+E21 -> 0 | G21: =SUMIF('Balance N-1 Retraitée'!A:A,"611*",'Balance N-1 Retraitée'!G:G)-SUMIF('Balance N-1 Retraitée'!A:A,"611*",'Balance N-1 Retraitée'!H:H) -> 0
A22: N | C22: * Achats consommés(2) de matières et fournitures | D22: =SUMIF('Balance N Retraitée'!A:A,"612*",'Balance N Retraitée'!G:G)-SUMIF('Balance N Retraitée'!A:A,"612*",'Balance N Retraitée'!H:H)-E22 -> 0 | E22: =(SUMIF('Balance N Retraitée'!A:A,"6128*",'Balance N Retraitée'!G:G)-SUMIF('Balance N Retraitée'!A:A,"6128*",'Balance N Retraitée'!H:H))+(SUMIF('Balance N Retraitée'!A:A,"61298*",'Balance N Retraitée'!G:G)-SUMIF('Balance N Retraitée'!A:A,"61298*",'Balance N Retraitée'!H:H)) -> 0 | F22: =+D22+E22 -> 0 | G22: =SUMIF('Balance N-1 Retraitée'!A:A,"612*",'Balance N-1 Retraitée'!G:G)-SUMIF('Balance N-1 Retraitée'!A:A,"612*",'Balance N-1 Retraitée'!H:H) -> 0
C23: * Autres charges externes | D23: =SUMIF('Balance N Retraitée'!A:A,"613*",'Balance N Retraitée'!G:G)-SUMIF('Balance N Retraitée'!A:A,"613*",'Balance N Retraitée'!H:H)+SUMIF('Balance N Retraitée'!A:A,"614*",'Balance N Retraitée'!G:G)-SUMIF('Balance N Retraitée'!A:A,"614*",'Balance N Retraitée'!H:H)-E23 -> 78665.81 | E23: =SUMIF('Balance N Retraitée'!A:A,"6148*",'Balance N Retraitée'!G:G)-SUMIF('Balance N Retraitée'!A:A,"6148*",'Balance N Retraitée'!H:H) -> 0 | F23: =+D23+E23 -> 78665.81 | G23: =SUMIF('Balance N-1 Retraitée'!A:A,"613*",'Balance N-1 Retraitée'!G:G)-SUMIF('Balance N-1 Retraitée'!A:A,"613*",'Balance N-1 Retraitée'!H:H)+SUMIF('Balance N-1 Retraitée'!A:A,"614*",'Balance N-1 Retraitée'!G:G)-SUMIF('Balance N-1 Retraitée'!A:A,"614*",'Balance N-1 Retraitée'!H:H) -> 5353.3
C24: * Impôts et taxes | D24: =SUMIF('Balance N Retraitée'!A:A,"616*",'Balance N Retraitée'!G:G)-SUMIF('Balance N Retraitée'!A:A,"616*",'Balance N Retraitée'!H:H)-E24 -> 28187 | E24: =SUMIF('Balance N Retraitée'!A:A,"6168*",'Balance N Retraitée'!G:G)-SUMIF('Balance N Retraitée'!A:A,"6168*",'Balance N Retraitée'!H:H) -> 0 | F24: =+D24+E24 -> 28187 | G24: =SUMIF('Balance N-1 Retraitée'!A:A,"616*",'Balance N-1 Retraitée'!G:G)-SUMIF('Balance N-1 Retraitée'!A:A,"616*",'Balance N-1 Retraitée'!H:H) -> 0
C25: * Charges de personnel | D25: =SUMIF('Balance N Retraitée'!A:A,"617*",'Balance N Retraitée'!G:G)-SUMIF('Balance N Retraitée'!A:A,"617*",'Balance N Retraitée'!H:H)-E25 -> 34176.55 | E25: =SUMIF('Balance N Retraitée'!A:A,"6178*",'Balance N Retraitée'!G:G)-SUMIF('Balance N Retraitée'!A:A,"6178*",'Balance N Retraitée'!H:H) -> 0 | F25: =+D25+E25 -> 34176.55 | G25: =SUMIF('Balance N-1 Retraitée'!A:A,"617*",'Balance N-1 Retraitée'!G:G)-SUMIF('Balance N-1 Retraitée'!A:A,"617*",'Balance N-1 Retraitée'!H:H) -> 12871
C26: * Autres charges d'exploitation | D26: =SUMIF('Balance N Retraitée'!A:A,"618*",'Balance N Retraitée'!G:G)-SUMIF('Balance N Retraitée'!A:A,"618*",'Balance N Retraitée'!H:H)-E26 -> 0 | E26: =SUMIF('Balance N Retraitée'!A:A,"6188*",'Balance N Retraitée'!G:G)-SUMIF('Balance N Retraitée'!A:A,"6188*",'Balance N Retraitée'!H:H) -> 0 | F26: =+D26+E26 -> 0 | G26: =SUMIF('Balance N-1 Retraitée'!A:A,"618*",'Balance N-1 Retraitée'!G:G)-SUMIF('Balance N-1 Retraitée'!A:A,"618*",'Balance N-1 Retraitée'!H:H) -> 0
C27: * Dotations d'exploitation | D27: =SUMIF('Balance N Retraitée'!A:A,"619*",'Balance N Retraitée'!G:G)-SUMIF('Balance N Retraitée'!A:A,"619*",'Balance N Retraitée'!H:H)-E27 -> 172843.76 | E27: =SUMIF('Balance N Retraitée'!A:A,"6198*",'Balance N Retraitée'!G:G)-SUMIF('Balance N Retraitée'!A:A,"6198*",'Balance N Retraitée'!H:H) -> 0 | F27: =+D27+E27 -> 172843.76 | G27: =SUMIF('Balance N-1 Retraitée'!A:A,"619*",'Balance N-1 Retraitée'!G:G)-SUMIF('Balance N-1 Retraitée'!A:A,"619*",'Balance N-1 Retraitée'!H:H) -> 694.37
C28: Total II | D28: =SUM(D21:D27) -> 313873.12 | E28: =SUM(E21:E27) -> 0 | F28: =SUM(F21:F27) -> 313873.12 | G28: =SUM(G21:G27) -> 18918.67
B29: III | C29: RESULTAT D'EXPLOITATION (I-II) | D29: =ROUND(D19-D28,2) -> 67793.55 | E29: =ROUND(E19-E28,2) -> 0 | F29: =ROUND(F19-F28,2) -> 67793.55 | G29: =ROUND(G19-G28,2) -> -18918.67
B30: IV | C30: PRODUITS FINANCIERS | D30: =SUM(D31:D34) -> 0 | E30: =SUM(E31:E34) -> 0 | F30: =SUM(F31:F34) -> 0 | G30: =SUM(G31:G34) -> 0
A31: F | C31: * Produits des titres de partic. et autres titres immobilisés | D31: =SUMIF('Balance N Retraitée'!A:A,"732*",'Balance N Retraitée'!H:H)-SUMIF('Balance N Retraitée'!A:A,"732*",'Balance N Retraitée'!G:G)-E31 -> 0 | E31: =SUMIF('Balance N Retraitée'!A:A,"7328*",'Balance N Retraitée'!H:H)-SUMIF('Balance N Retraitée'!A:A,"7328*",'Balance N Retraitée'!G:G) -> 0 | F31: =+D31+E31 -> 0 | G31: =SUMIF('Balance N-1 Retraitée'!A:A,"732*",'Balance N-1 Retraitée'!H:H)-SUMIF('Balance N-1 Retraitée'!A:A,"732*",'Balance N-1 Retraitée'!G:G) -> 0
A32: I | C32: * Gains de change | D32: =SUMIF('Balance N Retraitée'!A:A,"733*",'Balance N Retraitée'!H:H)-SUMIF('Balance N Retraitée'!A:A,"733*",'Balance N Retraitée'!G:G)-E32 -> 0 | E32: =SUMIF('Balance N Retraitée'!A:A,"7338*",'Balance N Retraitée'!H:H)-SUMIF('Balance N Retraitée'!A:A,"7338*",'Balance N Retraitée'!G:G) -> 0 | F32: =+D32+E32 -> 0 | G32: =SUMIF('Balance N-1 Retraitée'!A:A,"733*",'Balance N-1 Retraitée'!H:H)-SUMIF('Balance N-1 Retraitée'!A:A,"733*",'Balance N-1 Retraitée'!G:G) -> 0
A33: N | C33: * Interêts et autres produits financiers | D33: =SUMIF('Balance N Retraitée'!A:A,"738*",'Balance N Retraitée'!H:H)-SUMIF('Balance N Retraitée'!A:A,"738*",'Balance N Retraitée'!G:G)-E33 -> 0 | E33: =SUMIF('Balance N Retraitée'!A:A,"7388*",'Balance N Retraitée'!H:H)-SUMIF('Balance N Retraitée'!A:A,"7388*",'Balance N Retraitée'!G:G) -> 0 | F33: =+D33+E33 -> 0 | G33: =SUMIF('Balance N-1 Retraitée'!A:A,"738*",'Balance N-1 Retraitée'!H:H)-SUMIF('Balance N-1 Retraitée'!A:A,"738*",'Balance N-1 Retraitée'!G:G) -> 0
A34: A | C34: * Reprises financier; transferts de charges | D34: =SUMIF('Balance N Retraitée'!A:A,"739*",'Balance N Retraitée'!H:H)-SUMIF('Balance N Retraitée'!A:A,"739*",'Balance N Retraitée'!G:G)-E34 -> 0 | E34: =SUMIF('Balance N Retraitée'!A:A,"7398*",'Balance N Retraitée'!H:H)-SUMIF('Balance N Retraitée'!A:A,"7398*",'Balance N Retraitée'!G:G) -> 0 | F34: =+D34+E34 -> 0 | G34: =SUMIF('Balance N-1 Retraitée'!A:A,"739*",'Balance N-1 Retraitée'!H:H)-SUMIF('Balance N-1 Retraitée'!A:A,"739*",'Balance N-1 Retraitée'!G:G) -> 0
A35: N | C35: Total IV | D35: =SUM(D31:D34) -> 0 | E35: =SUM(E31:E34) -> 0 | F35: =SUM(F31:F34) -> 0 | G35: =SUM(G31:G34) -> 0
A36: C | B36: V | C36: CHARGES FINANCIERES | D36: =SUM(D37:D40) -> 43957.11 | E36: =SUM(E37:E40) -> 0 | F36: =SUM(F37:F40) -> 43957.11 | G36: =SUM(G37:G40) -> 0
A37: I | C37: * Charges d'interêts | D37: =SUMIF('Balance N Retraitée'!A:A,"631*",'Balance N Retraitée'!G:G)-SUMIF('Balance N Retraitée'!A:A,"631*",'Balance N Retraitée'!H:H)-E37 -> 43957.11 | E37: =SUMIF('Balance N Retraitée'!A:A,"6318*",'Balance N Retraitée'!G:G)-SUMIF('Balance N Retraitée'!A:A,"6318*",'Balance N Retraitée'!H:H) -> 0 | F37: =+D37+E37 -> 43957.11 | G37: =SUMIF('Balance N-1 Retraitée'!A:A,"631*",'Balance N-1 Retraitée'!G:G)-SUMIF('Balance N-1 Retraitée'!A:A,"631*",'Balance N-1 Retraitée'!H:H) -> 0
A38: E | C38: * Pertes de change | D38: =SUMIF('Balance N Retraitée'!A:A,"633*",'Balance N Retraitée'!G:G)-SUMIF('Balance N Retraitée'!A:A,"633*",'Balance N Retraitée'!H:H)-E38 -> 0 | E38: =SUMIF('Balance N Retraitée'!A:A,"6338*",'Balance N Retraitée'!G:G)-SUMIF('Balance N Retraitée'!A:A,"6338*",'Balance N Retraitée'!H:H) -> 0 | F38: =+D38+E38 -> 0 | G38: =SUMIF('Balance N-1 Retraitée'!A:A,"633*",'Balance N-1 Retraitée'!G:G)-SUMIF('Balance N-1 Retraitée'!A:A,"633*",'Balance N-1 Retraitée'!H:H) -> 0
A39: R | C39: * Autres charges financières | D39: =SUMIF('Balance N Retraitée'!A:A,"638*",'Balance N Retraitée'!G:G)-SUMIF('Balance N Retraitée'!A:A,"638*",'Balance N Retraitée'!H:H)-E39 -> 0 | E39: =SUMIF('Balance N Retraitée'!A:A,"6388*",'Balance N Retraitée'!G:G)-SUMIF('Balance N Retraitée'!A:A,"6388*",'Balance N Retraitée'!H:H) -> 0 | F39: =+D39+E39 -> 0 | G39: =SUMIF('Balance N-1 Retraitée'!A:A,"638*",'Balance N-1 Retraitée'!G:G)-SUMIF('Balance N-1 Retraitée'!A:A,"638*",'Balance N-1 Retraitée'!H:H) -> 0
C40: * Dotations finacières | D40: =SUMIF('Balance N Retraitée'!A:A,"639*",'Balance N Retraitée'!G:G)-SUMIF('Balance N Retraitée'!A:A,"639*",'Balance N Retraitée'!H:H)-E40 -> 0 | E40: =SUMIF('Balance N Retraitée'!A:A,"6398*",'Balance N Retraitée'!G:G)-SUMIF('Balance N Retraitée'!A:A,"6398*",'Balance N Retraitée'!H:H) -> 0 | F40: =+D40+E40 -> 0 | G40: =SUMIF('Balance N-1 Retraitée'!A:A,"639*",'Balance N-1 Retraitée'!G:G)-SUMIF('Balance N-1 Retraitée'!A:A,"639*",'Balance N-1 Retraitée'!H:H) -> 0
C41: Total V | D41: =SUM(D37:D40) -> 43957.11 | E41: =SUM(E37:E40) -> 0 | F41: =SUM(F37:F40) -> 43957.11 | G41: =SUM(G37:G40) -> 0
B42: VI | C42: RESULTAT FINANCIER (IV-V) | D42: =ROUND((D35-D41),2) -> -43957.11 | E42: =ROUND((E35-E41),2) -> 0 | F42: =ROUND((F35-F41),2) -> -43957.11 | G42: =ROUND((G35-G41),2) -> 0
B43: VII | C43: RESULTAT COURANT (III+VI) | D43: =+D29+D42 -> 23836.44 | E43: =+E29+E42 -> 0 | F43: =+F29+F42 -> 23836.44 | G43: =+G29+G42 -> -18918.67
C44: 1) Variation de stocks :stock final - stock initial ; augmentation (+) ; diminution (-)
C45: 2) Achats revendu ou consommés : achats -variation de stocks
A47: Tableau n° 2
A49: COMPTE DE PRODUITS ET CHARGES (hors taxes) (suite)
A50: (modèle normal)
D51: =+D4 -> Exercice du : | E51: =E4 -> 44562 | F51: =F4 -> 31/12/2022
D52: OPERATIONS
C53: NATURE | D53: Propres à l'exercice | E53: exercices précédents | F53: TOTAUX DE L'EXERCICE | G53: TOTAUX DE L'EXERCICE
D54: 1 | E54: 2 | F54: .3=2+1 | G54: PRECEDENT
B55: VII | C55: RESULTAT COURANT (reports) | D55: =D43 -> 23836.44 | E55: =E43 -> 0 | F55: =+F43 -> 23836.44 | G55: =+G43 -> -18918.67
B56: VIII | C56: PRODUITS NON COURANTS | D56: =SUM(D57:D61) -> 0 | E56: =SUM(E57:E61) -> 0 | F56: =SUM(F57:F61) -> 0 | G56: =SUM(G57:G61) -> 0
A57: N | C57: * Produits des cessions d'immobilisations | D57: =SUMIF('Balance N Retraitée'!A:A,"751*",'Balance N Retraitée'!H:H)-SUMIF('Balance N Retraitée'!A:A,"751*",'Balance N Retraitée'!G:G)-E57 -> 0 | E57: =SUMIF('Balance N Retraitée'!A:A,"7518*",'Balance N Retraitée'!H:H)-SUMIF('Balance N Retraitée'!A:A,"7518*",'Balance N Retraitée'!G:G) -> 0 | F57: =+D57+E57 -> 0 | G57: =SUMIF('Balance N-1 Retraitée'!A:A,"751*",'Balance N-1 Retraitée'!H:H)-SUMIF('Balance N-1 Retraitée'!A:A,"751*",'Balance N-1 Retraitée'!G:G) -> 0
A58: O | C58: * Subventions d'équilibre | D58: =SUMIF('Balance N Retraitée'!A:A,"756*",'Balance N Retraitée'!H:H)-SUMIF('Balance N Retraitée'!A:A,"756*",'Balance N Retraitée'!G:G)-E58 -> 0 | E58: =SUMIF('Balance N Retraitée'!A:A,"7568*",'Balance N Retraitée'!H:H)-SUMIF('Balance N Retraitée'!A:A,"7568*",'Balance N Retraitée'!G:G) -> 0 | F58: =+D58+E58 -> 0 | G58: =SUMIF('Balance N-1 Retraitée'!A:A,"756*",'Balance N-1 Retraitée'!H:H)-SUMIF('Balance N-1 Retraitée'!A:A,"756*",'Balance N-1 Retraitée'!G:G) -> 0
A59: N | C59: * Reprises sur subventions d'investissement | D59: =SUMIF('Balance N Retraitée'!A:A,"757*",'Balance N Retraitée'!H:H)-SUMIF('Balance N Retraitée'!A:A,"757*",'Balance N Retraitée'!G:G)-E59 -> 0 | E59: =SUMIF('Balance N Retraitée'!A:A,"7578*",'Balance N Retraitée'!H:H)-SUMIF('Balance N Retraitée'!A:A,"7578*",'Balance N Retraitée'!G:G) -> 0 | F59: =+D59+E59 -> 0 | G59: =SUMIF('Balance N-1 Retraitée'!A:A,"757*",'Balance N-1 Retraitée'!H:H)-SUMIF('Balance N-1 Retraitée'!A:A,"757*",'Balance N-1 Retraitée'!G:G) -> 0
A60: - | C60: * Autres produits non courants | D60: =SUMIF('Balance N Retraitée'!A:A,"758*",'Balance N Retraitée'!H:H)-SUMIF('Balance N Retraitée'!A:A,"758*",'Balance N Retraitée'!G:G)-E60 -> 0 | E60: =SUMIF('Balance N Retraitée'!A:A,"7588*",'Balance N Retraitée'!H:H)-SUMIF('Balance N Retraitée'!A:A,"7588*",'Balance N Retraitée'!G:G) -> 0 | F60: =+D60+E60 -> 0 | G60: =SUMIF('Balance N-1 Retraitée'!A:A,"758*",'Balance N-1 Retraitée'!H:H)-SUMIF('Balance N-1 Retraitée'!A:A,"758*",'Balance N-1 Retraitée'!G:G) -> 0
A61: C | C61: * Reprises non courantes ; transferts de charges | D61: =SUMIF('Balance N Retraitée'!A:A,"759*",'Balance N Retraitée'!H:H)-SUMIF('Balance N Retraitée'!A:A,"759*",'Balance N Retraitée'!G:G)-E61 -> 0 | E61: =SUMIF('Balance N Retraitée'!A:A,"7598*",'Balance N Retraitée'!H:H)-SUMIF('Balance N Retraitée'!A:A,"7598*",'Balance N Retraitée'!G:G) -> 0 | F61: =+D61+E61 -> 0 | G61: =SUMIF('Balance N-1 Retraitée'!A:A,"759*",'Balance N-1 Retraitée'!H:H)-SUMIF('Balance N-1 Retraitée'!A:A,"759*",'Balance N-1 Retraitée'!G:G) -> 0
A62: O | C62: Total VIII | D62: =ROUND(SUM(D57:D61),2) -> 0 | E62: =ROUND(SUM(E57:E61),2) -> 0 | F62: =ROUND(SUM(F57:F61),2) -> 0 | G62: =ROUND(SUM(G57:G61),2) -> 0
A63: U | B63: IX | C63: CHARGES NON COURANTES | D63: =SUM(D64:D67) -> 0 | E63: =SUM(E64:E67) -> 0 | F63: =SUM(F64:F67) -> 0 | G63: =SUM(G64:G67) -> 0
A64: R | C64: * Valeurs nettes d'amortissements des immobilisations cédées | D64: =SUMIF('Balance N Retraitée'!A:A,"651*",'Balance N Retraitée'!G:G)-SUMIF('Balance N Retraitée'!A:A,"651*",'Balance N Retraitée'!H:H)-E64 -> 0 | E64: =SUMIF('Balance N Retraitée'!A:A,"6518*",'Balance N Retraitée'!G:G)-SUMIF('Balance N Retraitée'!A:A,"6518*",'Balance N Retraitée'!H:H) -> 0 | F64: =+D64+E64 -> 0 | G64: =SUMIF('Balance N-1 Retraitée'!A:A,"651*",'Balance N-1 Retraitée'!G:G)-SUMIF('Balance N-1 Retraitée'!A:A,"651*",'Balance N-1 Retraitée'!H:H) -> 0
A65: A | C65: * Subventions accordées | D65: =SUMIF('Balance N Retraitée'!A:A,"656*",'Balance N Retraitée'!G:G)-SUMIF('Balance N Retraitée'!A:A,"656*",'Balance N Retraitée'!H:H)-E65 -> 0 | E65: =SUMIF('Balance N Retraitée'!A:A,"6568*",'Balance N Retraitée'!G:G)-SUMIF('Balance N Retraitée'!A:A,"6568*",'Balance N Retraitée'!H:H) -> 0 | F65: =+D65+E65 -> 0 | G65: =SUMIF('Balance N-1 Retraitée'!A:A,"656*",'Balance N-1 Retraitée'!G:G)-SUMIF('Balance N-1 Retraitée'!A:A,"656*",'Balance N-1 Retraitée'!H:H) -> 0
A66: N | C66: * Autres charges non courantes | D66: =SUMIF('Balance N Retraitée'!A:A,"658*",'Balance N Retraitée'!G:G)-SUMIF('Balance N Retraitée'!A:A,"658*",'Balance N Retraitée'!H:H)-E66 -> 0 | E66: =+SUMIF('Balance N Retraitée'!A:A,"6588*",'Balance N Retraitée'!G:G)-SUMIF('Balance N Retraitée'!A:A,"6588*",'Balance N Retraitée'!H:H) -> 0 | F66: =+D66+E66 -> 0 | G66: =SUMIF('Balance N-1 Retraitée'!A:A,"658*",'Balance N-1 Retraitée'!G:G)-SUMIF('Balance N-1 Retraitée'!A:A,"658*",'Balance N-1 Retraitée'!H:H) -> 0
A67: T | C67: * Dotations non courantes aux amortissements et aux provisions | D67: =SUMIF('Balance N Retraitée'!A:A,"659*",'Balance N Retraitée'!G:G)-SUMIF('Balance N Retraitée'!A:A,"659*",'Balance N Retraitée'!H:H)-E67 -> 0 | E67: =SUMIF('Balance N Retraitée'!A:A,"6598*",'Balance N Retraitée'!G:G)-SUMIF('Balance N Retraitée'!A:A,"6598*",'Balance N Retraitée'!H:H) -> 0 | F67: =+D67+E67 -> 0 | G67: =SUMIF('Balance N-1 Retraitée'!A:A,"659*",'Balance N-1 Retraitée'!G:G)-SUMIF('Balance N-1 Retraitée'!A:A,"659*",'Balance N-1 Retraitée'!H:H) -> 0
C68: Total IX | D68: =ROUND(SUM(D64:D67),2) -> 0 | E68: =ROUND(SUM(E64:E67),2) -> 0 | F68: =ROUND(SUM(F64:F67),2) -> 0 | G68: =ROUND(SUM(G64:G67),2) -> 0
B69: X | C69: RESULTAT NON COURANT (VIII-IX) | D69: =+D62-D68 -> 0 | E69: =+E62-E68 -> 0 | F69: =+F62-F68 -> 0 | G69: =+G62-G68 -> 0
B70: XI | C70: RESULTAT AVANT IMPÔTS (VII+X) | D70: =+D55+D69 -> 23836.44 | E70: =+E55+E69 -> 0 | F70: =+F55+F69 -> 23836.44 | G70: =+G55+G69 -> -18918.67
B71: XII | C71: IMPÔTS SUR LES BENEFICES | D71: =SUMIF('Balance N Retraitée'!A:A,"670*",'Balance N Retraitée'!G:G)-SUMIF('Balance N Retraitée'!A:A,"670*",'Balance N Retraitée'!H:H)-E71 -> 2384 | E71: =SUMIF('Balance N Retraitée'!A:A,"6708*",'Balance N Retraitée'!G:G)-SUMIF('Balance N Retraitée'!A:A,"6708*",'Balance N Retraitée'!H:H) -> 0 | F71: =+D71+E71 -> 2384 | G71: =SUMIF('Balance N-1 Retraitée'!A:A,"670*",'Balance N-1 Retraitée'!G:G)-SUMIF('Balance N-1 Retraitée'!A:A,"670*",'Balance N-1 Retraitée'!H:H) -> 0
B72: XIII | C72: RESULTAT NET (XI-XII) | D72: =D70-D71 -> 21452.44 | E72: =E70-E71 -> 0 | F72: =+F70-F71 -> 21452.44 | G72: =+G70-G71 -> -18918.67
B75: XIV | C75: TOTAL DES PRODUITS (I+IV+VIII) | D75: =ROUND(D19+D35+D62,2) -> 381666.67 | E75: =ROUND(E19+E35+E62,2) -> 0 | F75: =ROUND(F19+F35+F62,2) -> 381666.67 | G75: =ROUND(G19+G35+G62,2) -> 0
B76: XV | C76: TOTAL DES CHARGES (II+V+IX+XIII) | D76: =ROUND(D28+D41+D68+D71,2) -> 360214.23 | E76: =ROUND(E28+E41+E68+E71,2) -> 0 | F76: =ROUND(F28+F41+F68+F71,2) -> 360214.23 | G76: =ROUND(G28+G41+G68+G71,2) -> 18918.67
B77: XVI | C77: RESULTAT NET (total des produits-total des charges) | D77: =ROUND(D75-D76,2) -> 21452.44 | E77: =ROUND(E75-E76,2) -> 0 | F77: =ROUND(F75-F76,2) -> 21452.44 | G77: =ROUND(G75-G76,2) -> -18918.67

Sheet T3 B12-res fis
A1: Tableau n° 3 | C1: Etat B12
A3: PASSAGE DU RESULTAT NET COMPTABLE AU RESULTAT NET FISCAL
A5: Au | B5: ='T2 CPC'!F4 -> 31/12/2022
A6: INTITULES | B6: MONTANT | C6: MONTANT
A7: I. RESULTAT NET COMPTABLE
A8: * Bénéfice net | B8: =IF('T2 CPC'!F72>0,'T2 CPC'!F72,0) -> 21452.44
A9: * Perte nette | C9: =IF('T2 CPC'!F72<0,-'T2 CPC'!F72,0) -> 0
A10: II. REINTEGRATIONS FISCALES
A11: 1. Courantes | B11: =SUM(B12:B13) -> 0
A12: Excédent voiture de tourisme | B12: 0 | C12: 0
B13: 0 | C13: 0
B14: 0 | C14: 0
B15: 0 | C15: 0
B16: 0 | C16: 0
B17: 0 | C17: 0
A18: 2. Non courantes | B18: =SUM(B19:B24) -> 2384
A19: Impôt sur les sociétés | B19: =+Cellule_11416 -> 2384 | C19: 0
A20: Pénalités | B20: 0 | C20: 0
A21: Autres charges non courantes | B21: 0 | C21: 0
B22: 0 | C22: 0
B23: 0 | C23: 0
B24: 0 | C24: 0
A25: II. DEDUCTIONS FISCALES
A26: 1. Courantes | C26: =SUM(C27:C28) -> 0
A27: Abattement sur dividendes | B27: 0 | C27: 0
A28: Abattement sur cession de titres | B28: 0 | C28: 0
B29: 0 | C29: 0
B30: 0 | C30: 0
B31: 0 | C31: 0
B32: 0 | C32: 0
A33: 2. Non courantes
A34: Reprise sur autres Provisions | B34: 0 | C34: 0
B35: 0 | C35: 0
B36: 0 | C36: 0
B37: 0 | C37: 0
B38: 0 | C38: 0
B39: 0 | C39: 0
A40: Total | B40: =+B18+B11+B8 -> 23836.44 | C40: =+C33+C26+C9 -> 0
A41: IV. RESULTAT BRUT FISCAL | C41: Montants
A42: Bénéfice brut si T1> T2 (A) | B42: =IF(B40-C40>=0,B40-C40,0) -> 23836.44
A43: Déficit brut fiscal si T2> T1 (B) | C43: =IF(B40-C40<=0,C40-B40,0) -> 0 | E43: IS | F43: =IF(C50*0.35<0,0,C50*0.3) -> 0
A44: V. REPORTS DEFICITAIRES IMPUTES (C) (1) | B44: =SUM(B45:B48) -> 0
A45: * Exercice n-4 | E45: CM | F45: =+ROUNDDOWN(('T2 CPC'!F12+'T2 CPC'!F13+'T2 CPC'!F32+'T2 CPC'!F33+'T2 CPC'!F58+'T2 CPC'!F59+'T2 CPC'!F60),-1)*0.5% -> 1908.3
A46: * Exercice n-3
A47: * Exercice n-2 | E47: Montant de l'IS | F47: =MAX(F43,F45) -> 1908.3
A48: * Exercice n-1
A49: VI. RESULTAT NET FISCAL
A50: Bénéfice net fiscal (A-C) | B50: =IF(B42=0,0,B42-B44) -> 23836.44
A51: ou déficit net fiscal (B)
A52: VII. CUMUL DES AMORTISSEMENTS FISCALEMENT DIFFERES | C52: Montants
A54: VIII. CUMUL DES DEFICITS FISCAUX RESTANT A REPORTER
A55: * Exercice n-4 | B55: 0
A56: * Exercice n-3 | B56: 0
A57: * Exercice n-2 | B57: =+Cellule_11434 -> 18918.67
A58: * Exercice n-1
A60: (1) Dans la limite du montant du bénéfice brut fiscal (A)

Sheet T4 B2-immo
A1: Tableau n° 4 | I1: Etat B2
B3: TABLEAU DES IMMOBILISATIONS AUTRES QUE FINANCIERES
G5: Exercice clos le | I5: =Couverture!E15 -> 31/12/2022
B6: MONTANT BRUT | C6: AUGMENTATION | F6: DIMINUTION | I6: MONTANT | J6: Ecart
A7: NATURE | D7: Production par l'entreprise | I7: BRUT
B8: DEBUT EXERCICE | C8: Acquisition | D8: pour elle-même | E8: Virement | F8: Cession | G8: Retrait | H8: Virement | I8: FIN EXERCICE
A9: IMMOBILISATION EN NON-VALEURS | B9: =SUM(B10:B12) -> 5000 | C9: =SUM(C10:C12) -> 0 | D9: =SUM(D10:D12) -> 0 | E9: =SUM(E10:E12) -> 0 | F9: =SUM(F10:F12) -> 0 | G9: =SUM(G10:G12) -> 0 | H9: =SUM(H10:H12) -> 0 | I9: =SUM(I10:I12) -> 5000 | J9: =SUM(J10:J12) -> 0
A10: * Frais préliminaires | B10: =SUMIF('Balance N-1 Retraitée'!A:A,"211*",'Balance N-1 Retraitée'!G:G)-SUMIF('Balance N-1 Retraitée'!A:A,"211*",'Balance N-1 Retraitée'!H:H) -> 5000 | C10: 0 | D10: 0 | E10: 0 | F10: =+SUMIF('Balance N Retraitée'!A:A,"211*",'Balance N Retraitée'!F:F)-G10-H10 -> 0 | G10: 0 | H10: 0 | I10: =B10+SUM(C10:E10)-SUM(F10:H10) -> 5000 | J10: =SUMIF('Balance N Retraitée'!A:A,"211*",'Balance N Retraitée'!G:G)-SUMIF('Balance N Retraitée'!A:A,"211*",'Balance N Retraitée'!H:H)-I10 -> 0
A11: * Charges à répartir sur plusieurs exercices | B11: =SUMIF('Balance N-1 Retraitée'!A:A,"212*",'Balance N-1 Retraitée'!G:G)-SUMIF('Balance N-1 Retraitée'!A:A,"212*",'Balance N-1 Retraitée'!H:H) -> 0 | C11: =SUMIF('Balance N Retraitée'!A:A,"212*",'Balance N Retraitée'!E:E)-D11-E11 -> 0 | D11: 0 | E11: 0 | F11: =+SUMIF('Balance N Retraitée'!A:A,"212*",'Balance N Retraitée'!F:F)-G11-H11 -> 0 | G11: 0 | H11: 0 | I11: =B11+SUM(C11:E11)-SUM(F11:H11) -> 0 | J11: =SUMIF('Balance N Retraitée'!A:A,"212*",'Balance N Retraitée'!G:G)-SUMIF('Balance N Retraitée'!A:A,"212*",'Balance N Retraitée'!H:H)-I11 -> 0
A12: * Primes de remboursement obligations | B12: =SUMIF('Balance N-1 Retraitée'!A:A,"213*",'Balance N-1 Retraitée'!G:G)-SUMIF('Balance N-1 Retraitée'!A:A,"213*",'Balance N-1 Retraitée'!H:H) -> 0 | C12: =SUMIF('Balance N Retraitée'!A:A,"213*",'Balance N Retraitée'!E:E)-D12-E12 -> 0 | D12: 0 | E12: 0 | F12: =+SUMIF('Balance N Retraitée'!A:A,"213*",'Balance N Retraitée'!F:F)-G12-H12 -> 0 | G12: 0 | H12: 0 | I12: =B12+SUM(C12:E12)-SUM(F12:H12) -> 0 | J12: =SUMIF('Balance N Retraitée'!A:A,"213*",'Balance N Retraitée'!G:G)-SUMIF('Balance N Retraitée'!A:A,"213*",'Balance N Retraitée'!H:H)-I12 -> 0
B13: 0 | C13: =SUMIF('Balance N Retraitée'!A:A,"213*",'Balance N Retraitée'!E:E)-D13-E13 -> 0 | D13: 0 | E13: 0 | F13: =+SUMIF('Balance N Retraitée'!A:A,"213*",'Balance N Retraitée'!F:F)-G13-H13 -> 0 | G13: 0 | H13: 0 | I13: =B13+SUM(C13:E13)-SUM(F13:H13) -> 0
A14: * IMMOBILISATIONS INCORPORELLES | B14: =SUM(B15:B18) -> 0 | C14: =SUM(C15:C18) -> 0 | D14: =SUMIF('Balance N Retraitée'!A:A,"713*",'Balance N Retraitée'!H:H)-SUMIF('Balance N Retraitée'!A:A,"713*",'Balance N Retraitée'!G:G)-E14 -> 0 | E14: =SUMIF('Balance N Retraitée'!A:A,"7138*",'Balance N Retraitée'!H:H)-SUMIF('Balance N Retraitée'!A:A,"7138*",'Balance N Retraitée'!G:G) -> 0 | F14: =SUM(F15:F18) -> 0 | G14: =SUM(G15:G18) -> 0 | H14: =SUMIF('Balance N-1 Retraitée'!A:A,"713*",'Balance N-1 Retraitée'!H:H)-SUMIF('Balance N-1 Retraitée'!A:A,"713*",'Balance N-1 Retraitée'!G:G) -> 0 | I14: =SUM(I15:I18) -> 0 | J14: =SUM(J15:J18) -> 0
A15: * Immobilisation en recherche et développement | B15: =SUMIF('Balance N-1 Retraitée'!A:A,"221*",'Balance N-1 Retraitée'!G:G)-SUMIF('Balance N-1 Retraitée'!A:A,"221*",'Balance N-1 Retraitée'!H:H) -> 0 | C15: =SUMIF('Balance N Retraitée'!A:A,"221*",'Balance N Retraitée'!E:E)-D15-E15 -> 0 | D15: 0 | E15: 0 | F15: =+SUMIF('Balance N Retraitée'!A:A,"221*",'Balance N Retraitée'!F:F)-G15-H15 -> 0 | G15: 0 | H15: 0 | I15: =B15+SUM(C15:E15)-SUM(F15:H15) -> 0 | J15: =SUMIF('Balance N Retraitée'!A:A,"221*",'Balance N Retraitée'!G:G)-SUMIF('Balance N Retraitée'!A:A,"221*",'Balance N Retraitée'!H:H)-I15 -> 0
A16: * Brevets, marques, droits et valeurs similaires | B16: =SUMIF('Balance N-1 Retraitée'!A:A,"222*",'Balance N-1 Retraitée'!G:G)-SUMIF('Balance N-1 Retraitée'!A:A,"222*",'Balance N-1 Retraitée'!H:H) -> 0 | C16: =SUMIF('Balance N Retraitée'!A:A,"222*",'Balance N Retraitée'!E:E)-D16-E16 -> 0 | D16: 0 | E16: 0 | F16: =+SUMIF('Balance N Retraitée'!A:A,"222*",'Balance N Retraitée'!F:F)-G16-H16 -> 0 | G16: 0 | H16: 0 | I16: =B16+SUM(C16:E16)-SUM(F16:H16) -> 0 | J16: =SUMIF('Balance N Retraitée'!A:A,"222*",'Balance N Retraitée'!G:G)-SUMIF('Balance N Retraitée'!A:A,"222*",'Balance N Retraitée'!H:H)-I16 -> 0
A17: * Fonds commercial | B17: =SUMIF('Balance N-1 Retraitée'!A:A,"223*",'Balance N-1 Retraitée'!G:G)-SUMIF('Balance N-1 Retraitée'!A:A,"223*",'Balance N-1 Retraitée'!H:H) -> 0 | C17: =SUMIF('Balance N Retraitée'!A:A,"223*",'Balance N Retraitée'!E:E)-D17-E17 -> 0 | D17: 0 | E17: 0 | F17: =+SUMIF('Balance N Retraitée'!A:A,"223*",'Balance N Retraitée'!F:F)-G17-H17 -> 0 | G17: 0 | H17: 0 | I17: =B17+SUM(C17:E17)-SUM(F17:H17) -> 0 | J17: =SUMIF('Balance N Retraitée'!A:A,"223*",'Balance N Retraitée'!G:G)-SUMIF('Balance N Retraitée'!A:A,"223*",'Balance N Retraitée'!H:H)-I17 -> 0
A18: *Autres immobilisations incorporelles | B18: =SUMIF('Balance N-1 Retraitée'!A:A,"228*",'Balance N-1 Retraitée'!G:G)-SUMIF('Balance N-1 Retraitée'!A:A,"228*",'Balance N-1 Retraitée'!H:H) -> 0 | C18: =SUMIF('Balance N Retraitée'!A:A,"228*",'Balance N Retraitée'!E:E)-D18-E18 -> 0 | D18: 0 | E18: 0 | F18: =+SUMIF('Balance N Retraitée'!A:A,"228*",'Balance N Retraitée'!F:F)-G18-H18 -> 0 | G18: 0 | H18: 0 | I18: =B18+SUM(C18:E18)-SUM(F18:H18) -> 0 | J18: =SUMIF('Balance N Retraitée'!A:A,"228*",'Balance N Retraitée'!G:G)-SUMIF('Balance N Retraitée'!A:A,"228*",'Balance N Retraitée'!H:H)-I18 -> 0
A20: IMMOBILISATIONS CORPORELLES | B20: =SUM(B21:B28) -> 0 | C20: =SUM(C21:C28) -> 1588527.6 | D20: =SUM(D21:D28) -> 0 | E20: =SUM(E21:E28) -> 0 | F20: =SUM(F21:F28) -> 0 | G20: =SUM(G21:G28) -> 0 | H20: =SUM(H21:H28) -> 0 | I20: =SUM(I21:I28) -> 1588527.6 | J20: =SUM(J21:J28) -> 0
A21: * Terrains | B21: =SUMIF('Balance N-1 Retraitée'!A:A,"231*",'Balance N-1 Retraitée'!G:G)-SUMIF('Balance N-1 Retraitée'!A:A,"231*",'Balance N-1 Retraitée'!H:H) -> 0 | C21: =SUMIF('Balance N Retraitée'!A:A,"231*",'Balance N Retraitée'!E:E)-D21-E21 -> 0 | D21: 0 | E21: 0 | F21: =+SUMIF('Balance N Retraitée'!A:A,"231*",'Balance N Retraitée'!F:F)-G21-H21 -> 0 | G21: 0 | H21: 0 | I21: =B21+SUM(C21:E21)-SUM(F21:H21) -> 0 | J21: =SUMIF('Balance N Retraitée'!A:A,"231*",'Balance N Retraitée'!G:G)-SUMIF('Balance N Retraitée'!A:A,"231*",'Balance N Retraitée'!H:H)-I21 -> 0
A22: * Constructions | B22: =SUMIF('Balance N-1 Retraitée'!A:A,"232*",'Balance N-1 Retraitée'!G:G)-SUMIF('Balance N-1 Retraitée'!A:A,"232*",'Balance N-1 Retraitée'!H:H) -> 0 | C22: =SUMIF('Balance N Retraitée'!A:A,"232*",'Balance N Retraitée'!E:E)-D22-E22 -> 9700 | D22: 0 | E22: 0 | F22: =+SUMIF('Balance N Retraitée'!A:A,"232*",'Balance N Retraitée'!F:F)-G22-H22 -> 0 | G22: 0 | H22: 0 | I22: =B22+SUM(C22:E22)-SUM(F22:H22) -> 9700 | J22: =SUMIF('Balance N Retraitée'!A:A,"232*",'Balance N Retraitée'!G:G)-SUMIF('Balance N Retraitée'!A:A,"232*",'Balance N Retraitée'!H:H)-I22 -> 0
A23: * Installat. techniques,matériel et outillage | B23: =SUMIF('Balance N-1 Retraitée'!A:A,"233*",'Balance N-1 Retraitée'!G:G)-SUMIF('Balance N-1 Retraitée'!A:A,"233*",'Balance N-1 Retraitée'!H:H) -> 0 | C23: =SUMIF('Balance N Retraitée'!A:A,"233*",'Balance N Retraitée'!E:E)-D23-E23 -> 0 | D23: 0 | E23: 0 | F23: =+SUMIF('Balance N Retraitée'!A:A,"233*",'Balance N Retraitée'!F:F)-G23-H23 -> 0 | G23: 0 | H23: 0 | I23: =B23+SUM(C23:E23)-SUM(F23:H23) -> 0 | J23: =SUMIF('Balance N Retraitée'!A:A,"233*",'Balance N Retraitée'!G:G)-SUMIF('Balance N Retraitée'!A:A,"233*",'Balance N Retraitée'!H:H)-I23 -> 0
A24: * Matériel de transport | B24: =SUMIF('Balance N-1 Retraitée'!A:A,"234*",'Balance N-1 Retraitée'!G:G)-SUMIF('Balance N-1 Retraitée'!A:A,"234*",'Balance N-1 Retraitée'!H:H) -> 0 | C24: =SUMIF('Balance N Retraitée'!A:A,"234*",'Balance N Retraitée'!E:E)-D24-E24 -> 1578827.6 | D24: 0 | E24: 0 | F24: =SUMIF('Balance N Retraitée'!A:A,"234*",'Balance N Retraitée'!F:F)-G24-H24 -> 0 | G24: 0 | H24: 0 | I24: =B24+SUM(C24:E24)-SUM(F24:H24) -> 1578827.6 | J24: =SUMIF('Balance N Retraitée'!A:A,"234*",'Balance N Retraitée'!G:G)-SUMIF('Balance N Retraitée'!A:A,"234*",'Balance N Retraitée'!H:H)-I24 -> 0
A25: * Mobilier, matériel bureau et aménagements | B25: =SUMIF('Balance N-1 Retraitée'!A:A,"235*",'Balance N-1 Retraitée'!G:G)-SUMIF('Balance N-1 Retraitée'!A:A,"235*",'Balance N-1 Retraitée'!H:H) -> 0 | C25: =SUMIF('Balance N Retraitée'!A:A,"235*",'Balance N Retraitée'!E:E)-D25-E25 -> 0 | D25: 0 | E25: 0 | F25: =SUMIF('Balance N Retraitée'!A:A,"235*",'Balance N Retraitée'!F:F)-G25-H25 -> 0 | G25: 0 | H25: 0 | I25: =B25+SUM(C25:E25)-SUM(F25:H25) -> 0 | J25: =SUMIF('Balance N Retraitée'!A:A,"235*",'Balance N Retraitée'!G:G)-SUMIF('Balance N Retraitée'!A:A,"235*",'Balance N Retraitée'!H:H)-I25 -> 0
A26: * Autres immobilisations corporelles | B26: =SUMIF('Balance N-1 Retraitée'!A:A,"238*",'Balance N-1 Retraitée'!G:G)-SUMIF('Balance N-1 Retraitée'!A:A,"238*",'Balance N-1 Retraitée'!H:H) -> 0 | C26: =SUMIF('Balance N Retraitée'!A:A,"238*",'Balance N Retraitée'!E:E)-D26-E26 -> 0 | D26: 0 | E26: 0 | F26: =SUMIF('Balance N Retraitée'!A:A,"238*",'Balance N Retraitée'!F:F)-G26-H26 -> 0 | G26: 0 | H26: 0 | I26: =B26+SUM(C26:E26)-SUM(F26:H26) -> 0 | J26: =SUMIF('Balance N Retraitée'!A:A,"238*",'Balance N Retraitée'!G:G)-SUMIF('Balance N Retraitée'!A:A,"238*",'Balance N Retraitée'!H:H)-I26 -> 0
A27: * Immobilisations corporelles en cours | B27: =SUMIF('Balance N-1 Retraitée'!A:A,"239*",'Balance N-1 Retraitée'!G:G)-SUMIF('Balance N-1 Retraitée'!A:A,"239*",'Balance N-1 Retraitée'!H:H) -> 0 | C27: =SUMIF('Balance N Retraitée'!A:A,"239*",'Balance N Retraitée'!E:E)-D27-E27 -> 0 | D27: 0 | E27: 0 | F27: 0 | G27: 0 | H27: 0 | I27: =B27+SUM(C27:E27)-SUM(F27:H27) -> 0 | J27: =SUMIF('Balance N Retraitée'!A:A,"239*",'Balance N Retraitée'!G:G)-SUMIF('Balance N Retraitée'!A:A,"239*",'Balance N Retraitée'!H:H)-I27 -> 0
A28: * Matériel informatique | D28: 0 | E28: 0 | F28: 0 | G28: 0 | H28: 0 | J28: =SUMIF('Balance N Retraitée'!A:A,"239*",'Balance N Retraitée'!G:G)-SUMIF('Balance N Retraitée'!A:A,"239*",'Balance N Retraitée'!H:H)-I28 -> 0
A30: Total | B30: =B9+B14+B20 -> 5000 | C30: =C9+C14+C20 -> 1588527.6 | D30: =D9+D14+D20 -> 0 | E30: =E9+E14+E20 -> 0 | F30: =F9+F14+F20 -> 0 | G30: =G9+G14+G20 -> 0 | H30: =H9+H14+H20 -> 0 | I30: =I9+I14+I20 -> 1593527.6 | J30: =J9+J14+J20 -> 0

Sheet T5 ESG
B1: Tableau 5
A2: ETAT DES SOLDES DE GESTION (E.S.G)
A3: I. Tableau de formation des Résultats (T.F.R ) | E3: Exercice clos le : | G3: =Couverture!E15 -> 31/12/2022
E4: Exercice | G4: Exercice
G5: Précédent
B6: 1 | C6: + | D6: Ventes de Marchandises ( en l'état) | E6: =+'T2 CPC'!F12 -> 0 | G6: =+'T2 CPC'!G12 -> 0 | H6: =E6-G6 -> 0
B7: 2 | C7: - | D7: Achats revendus de marchandises | E7: =+'T2 CPC'!F21 -> 0 | G7: =+'T2 CPC'!G21 -> 0
A8: I | C8: = | D8: MARGE BRUTES VENTES EN L'ETAT | E8: =+E6-E7 -> 0 | G8: =+G6-G7 -> 0 | H8: =E8-G8 -> 0
A9: II | C9: + | D9: PRODUCTION DE L'EXERCICE (3+4+5) | E9: =+E10+E11+E12 -> 381666.67 | G9: =+G10+G11+G12 -> 0
B10: 3 | D10: Ventes de biens et services produits | E10: =+'T2 CPC'!F13 -> 381666.67 | G10: =+'T2 CPC'!G13 -> 0
B11: 4 | D11: Variation stocks produits | E11: =+'T2 CPC'!F14 -> 0 | G11: =+'T2 CPC'!G14 -> 0
B12: 5 | D12: Immobilisations produites par l'entreprise pour elle même | E12: =+'T2 CPC'!F15 -> 0 | G12: =+'T2 CPC'!G15 -> 0
A13: III | C13: - | D13: CONSOMMATIONS DE L'EXERCICE(6+7) | E13: =(E14+E15) -> 78665.81 | G13: =(G14+G15) -> 5353.3
B14: 6 | D14: Achats consommés de matières et fournitures | E14: =Cellule_11258 -> 0 | G14: =+'T2 CPC'!G22 -> 0 | H14: =SUMIF('Balance N-1 Retraitée'!A:A,"713*",'Balance N-1 Retraitée'!H:H)-SUMIF('Balance N-1 Retraitée'!A:A,"713*",'Balance N-1 Retraitée'!G:G) -> 0
B15: 7 | D15: Autres charges externes | E15: =+'T2 CPC'!F23 -> 78665.81 | G15: =+'T2 CPC'!G23 -> 5353.3
A16: IV | C16: = | D16: VALEUR AJOUTEE (I+II-III) | E16: =E8+E9-E13 -> 303000.86 | G16: =G8+G9-G13 -> -5353.3
B17: 8 | C17: + | D17: Subventions d'exploitation | E17: =+'T2 CPC'!F16 -> 0 | G17: =+'T2 CPC'!G16 -> 0
B18: 9 | C18: - | D18: Impôts et taxes | E18: =+'T2 CPC'!F24 -> 28187 | G18: =+'T2 CPC'!G24 -> 0
B19: 10 | C19: - | D19: Charges de personnel | E19: =+'T2 CPC'!F25 -> 34176.55 | G19: =+'T2 CPC'!G25 -> 12871
A20: V | C20: = | D20: EXCEDENT BRUT D'EXPLOITATION (EBE) | E20: =ROUND(E16+E17-E18-E19,2) -> 240637.31 | G20: =ROUND(G16+G17-G18-G19,2) -> -18224.3
D21: OU INSUFFISANCE BRUTE D'EXPLOITATION(IBE)
B22: 11 | C22: + | D22: Autres produits d'exploitation | E22: =+'T2 CPC'!F17 -> 0 | G22: =+'T2 CPC'!G17 -> 0
B23: 12 | C23: - | D23: Autres charges d'exploitation | E23: =+'T2 CPC'!F26 -> 0 | G23: =+'T2 CPC'!G26 -> 0
B24: 13 | C24: + | D24: Reprises d'exploitation, transferts de charges | E24: =+'T2 CPC'!F18 -> 0 | G24: =+'T2 CPC'!G18 -> 0
B25: 14 | C25: - | D25: Dotations d'exploitation | E25: =+'T2 CPC'!F27 -> 172843.76 | G25: =+'T2 CPC'!G27 -> 694.37
A26: VI | C26: = | D26: RESULTAT D'EXPLOITATION(+ou-) | E26: =+E20+E22-E23+E24-E25 -> 67793.55 | G26: =+G20+G22-G23+G24-G25 -> -18918.67
A27: VII | C27: +/- | D27: RESULTAT FINANCIER | E27: =+'T2 CPC'!F42 -> -43957.11 | G27: =+'T2 CPC'!G42 -> 0
A28: VIII | C28: = | D28: RESULTAT COURANT | E28: =+E26+E27 -> 23836.44 | G28: =+G26+G27 -> -18918.67
A29: IX | C29: +/- | D29: RESULTAT NON COURANT(+ou-) | E29: =+'T2 CPC'!F69 -> 0 | G29: =+'T2 CPC'!G69 -> 0
B30: 15 | C30: - | D30: Impôts sur les résultats | E30: =+'T2 CPC'!F71 -> 2384 | G30: =+'T2 CPC'!G71 -> 0
A32: X | C32: = | D32: RESULTAT NET DE L'EXERCICE | E32: =(+E28+E29-E30) -> 21452.44 | G32: =(+G28+G29-G30) -> -18918.67
A34: II. CAPACITE D'AUTOFINANCEMENT (C.A.F.) - AUTOFINANCEMENT
B35: 1 | D35: Résultat net de l'exercice
D36: Bénéfice + | E36: =IF(E32>0,E32,0) -> 21452.44 | G36: =IF(G32>0,G32,0) -> 0
D37: Perte - | E37: =IF(E32<0,E32,0) -> 0 | G37: =IF(G32<0,G32,0) -> -18918.67
B38: 2 | C38: + | D38: Dotations d'exploitation (1) | E38: =(SUMIF('Balance N Retraitée'!A:A,"619*",'Balance N Retraitée'!G:G)-SUMIF('Balance N Retraitée'!A:A,"619*",'Balance N Retraitée'!H:H))-((SUMIF('Balance N Retraitée'!A:A,"61957*",'Balance N Retraitée'!G:G)-SUMIF('Balance N Retraitée'!A:A,"61957*",'Balance N Retraitée'!H:H)))-((SUMIF('Balance N Retraitée'!A:A,"6196*",'Balance N Retraitée'!G:G)-SUMIF('Balance N Retraitée'!A:A,"6196*",'Balance N Retraitée'!H:H))) -> 172843.76 | G38: =(SUMIF('Balance N-1 Retraitée'!A:A,"619*",'Balance N-1 Retraitée'!G:G)-SUMIF('Balance N-1 Retraitée'!A:A,"619*",'Balance N-1 Retraitée'!H:H))-((SUMIF('Balance N-1 Retraitée'!A:A,"61957*",'Balance N-1 Retraitée'!G:G)-SUMIF('Balance N-1 Retraitée'!A:A,"61957*",'Balance N-1 Retraitée'!H:H)))-((SUMIF('Balance N-1 Retraitée'!A:A,"6196*",'Balance N-1 Retraitée'!G:G)-SUMIF('Balance N-1 Retraitée'!A:A,"6196*",'Balance N-1 Retraitée'!H:H))) -> 694.37
B39: 3 | C39: + | D39: Dotations financières (1) | E39: =(SUMIF('Balance N Retraitée'!A:A,"6391*",'Balance N Retraitée'!G:G)-SUMIF('Balance N Retraitée'!A:A,"6391*",'Balance N Retraitée'!H:H))+(SUMIF('Balance N Retraitée'!A:A,"6392*",'Balance N Retraitée'!G:G)-SUMIF('Balance N Retraitée'!A:A,"6392*",'Balance N Retraitée'!H:H))+(SUMIF('Balance N Retraitée'!A:A,"63935*",'Balance N Retraitée'!G:G)-SUMIF('Balance N Retraitée'!A:A,"63935*",'Balance N Retraitée'!H:H)) -> 0 | G39: =(SUMIF('Balance N-1 Retraitée'!A:A,"6391*",'Balance N-1 Retraitée'!G:G)-SUMIF('Balance N-1 Retraitée'!A:A,"6391*",'Balance N-1 Retraitée'!H:H))+(SUMIF('Balance N-1 Retraitée'!A:A,"6392*",'Balance N-1 Retraitée'!G:G)-SUMIF('Balance N-1 Retraitée'!A:A,"6392*",'Balance N-1 Retraitée'!H:H))+(SUMIF('Balance N-1 Retraitée'!A:A,"63935*",'Balance N-1 Retraitée'!G:G)-SUMIF('Balance N-1 Retraitée'!A:A,"63935*",'Balance N-1 Retraitée'!H:H)) -> 0
B40: 4 | C40: + | D40: Dotations non courantes(1) | E40: =(SUMIF('Balance N Retraitée'!A:A,"659*",'Balance N Retraitée'!G:G)-SUMIF('Balance N Retraitée'!A:A,"659*",'Balance N Retraitée'!H:H))-(SUMIF('Balance N Retraitée'!A:A,"65957*",'Balance N Retraitée'!G:G)-SUMIF('Balance N Retraitée'!A:A,"65957*",'Balance N Retraitée'!H:H))-(SUMIF('Balance N Retraitée'!A:A,"65963*",'Balance N Retraitée'!G:G)-SUMIF('Balance N Retraitée'!A:A,"65963*",'Balance N Retraitée'!H:H)) -> 0 | G40: =(SUMIF('Balance N-1 Retraitée'!A:A,"659*",'Balance N-1 Retraitée'!G:G)-SUMIF('Balance N-1 Retraitée'!A:A,"659*",'Balance N-1 Retraitée'!H:H))-(SUMIF('Balance N-1 Retraitée'!A:A,"65957*",'Balance N-1 Retraitée'!G:G)-SUMIF('Balance N-1 Retraitée'!A:A,"65957*",'Balance N-1 Retraitée'!H:H))-(SUMIF('Balance N-1 Retraitée'!A:A,"65963*",'Balance N-1 Retraitée'!G:G)-SUMIF('Balance N-1 Retraitée'!A:A,"65963*",'Balance N-1 Retraitée'!H:H)) -> 0
B41: 5 | C41: - | D41: Reprises d'exploitation(2) | E41: =(SUMIF('Balance N Retraitée'!A:A,"719*",'Balance N Retraitée'!G:G)-SUMIF('Balance N Retraitée'!A:A,"719*",'Balance N Retraitée'!H:H))-(SUMIF('Balance N Retraitée'!A:A,"71957*",'Balance N Retraitée'!G:G)-SUMIF('Balance N Retraitée'!A:A,"71957*",'Balance N Retraitée'!H:H))-(SUMIF('Balance N Retraitée'!A:A,"7196*",'Balance N Retraitée'!G:G)-SUMIF('Balance N Retraitée'!A:A,"7196*",'Balance N Retraitée'!H:H))-(SUMIF('Balance N Retraitée'!A:A,"7197*",'Balance N Retraitée'!G:G)-SUMIF('Balance N Retraitée'!A:A,"7197*",'Balance N Retraitée'!H:H)) -> 0 | G41: =(SUMIF('Balance N-1 Retraitée'!A:A,"719*",'Balance N-1 Retraitée'!G:G)-SUMIF('Balance N-1 Retraitée'!A:A,"719*",'Balance N-1 Retraitée'!H:H))-(SUMIF('Balance N-1 Retraitée'!A:A,"71957*",'Balance N-1 Retraitée'!G:G)-SUMIF('Balance N-1 Retraitée'!A:A,"71957*",'Balance N-1 Retraitée'!H:H))-(SUMIF('Balance N-1 Retraitée'!A:A,"7196*",'Balance N-1 Retraitée'!G:G)-SUMIF('Balance N-1 Retraitée'!A:A,"7196*",'Balance N-1 Retraitée'!H:H))-(SUMIF('Balance N-1 Retraitée'!A:A,"7197*",'Balance N-1 Retraitée'!G:G)-SUMIF('Balance N-1 Retraitée'!A:A,"7197*",'Balance N-1 Retraitée'!H:H)) -> 0
B42: 6 | C42: - | D42: Reprises financières(2) | E42: =(SUMIF('Balance N Retraitée'!A:A,"7391*",'Balance N Retraitée'!G:G)-SUMIF('Balance N Retraitée'!A:A,"7391*",'Balance N Retraitée'!H:H))+(SUMIF('Balance N Retraitée'!A:A,"7392*",'Balance N Retraitée'!G:G)-SUMIF('Balance N Retraitée'!A:A,"7392*",'Balance N Retraitée'!H:H))+(SUMIF('Balance N Retraitée'!A:A,"73935*",'Balance N Retraitée'!G:G)-SUMIF('Balance N Retraitée'!A:A,"73935*",'Balance N Retraitée'!H:H)) -> 0 | G42: =(SUMIF('Balance N-1 Retraitée'!A:A,"7391*",'Balance N-1 Retraitée'!G:G)-SUMIF('Balance N-1 Retraitée'!A:A,"7391*",'Balance N-1 Retraitée'!H:H))+(SUMIF('Balance N-1 Retraitée'!A:A,"7392*",'Balance N-1 Retraitée'!G:G)-SUMIF('Balance N-1 Retraitée'!A:A,"7392*",'Balance N-1 Retraitée'!H:H))+(SUMIF('Balance N-1 Retraitée'!A:A,"73935*",'Balance N-1 Retraitée'!G:G)-SUMIF('Balance N-1 Retraitée'!A:A,"73935*",'Balance N-1 Retraitée'!H:H)) -> 0
B43: 7 | C43: - | D43: Reprises non courantes(2) | E43: =(SUMIF('Balance N Retraitée'!A:A,"759*",'Balance N Retraitée'!G:G)-SUMIF('Balance N Retraitée'!A:A,"759*",'Balance N Retraitée'!H:H))-(SUMIF('Balance N Retraitée'!A:A,"75957*",'Balance N Retraitée'!G:G)-SUMIF('Balance N Retraitée'!A:A,"75957*",'Balance N Retraitée'!H:H))-(SUMIF('Balance N Retraitée'!A:A,"75963*",'Balance N Retraitée'!G:G)-SUMIF('Balance N Retraitée'!A:A,"75963*",'Balance N Retraitée'!H:H))-(SUMIF('Balance N Retraitée'!A:A,"7597*",'Balance N Retraitée'!G:G)-SUMIF('Balance N Retraitée'!A:A,"7597*",'Balance N Retraitée'!H:H)) -> 0 | G43: =(SUMIF('Balance N-1 Retraitée'!A:A,"759*",'Balance N-1 Retraitée'!G:G)-SUMIF('Balance N-1 Retraitée'!A:A,"759*",'Balance N-1 Retraitée'!H:H))-(SUMIF('Balance N-1 Retraitée'!A:A,"75957*",'Balance N-1 Retraitée'!G:G)-SUMIF('Balance N-1 Retraitée'!A:A,"75957*",'Balance N-1 Retraitée'!H:H))-(SUMIF('Balance N-1 Retraitée'!A:A,"75963*",'Balance N-1 Retraitée'!G:G)-SUMIF('Balance N-1 Retraitée'!A:A,"75963*",'Balance N-1 Retraitée'!H:H))-(SUMIF('Balance N-1 Retraitée'!A:A,"7597*",'Balance N-1 Retraitée'!G:G)-SUMIF('Balance N-1 Retraitée'!A:A,"7597*",'Balance N-1 Retraitée'!H:H)) -> 0
B44: 8 | C44: - | D44: Produits des cessions d'immobilisation | E44: =SUMIF('Balance N Retraitée'!A:A,"751*",'Balance N Retraitée'!H:H)-(SUMIF('Balance N Retraitée'!A:A,"751*",'Balance N Retraitée'!G:G)) -> 0 | G44: =SUMIF('Balance N-1 Retraitée'!A:A,"751*",'Balance N-1 Retraitée'!H:H)-(SUMIF('Balance N-1 Retraitée'!A:A,"751*",'Balance N-1 Retraitée'!G:G)) -> 0
B45: 9 | C45: + | D45: Valeurs nettes d'amortiss. des immo. cédées | E45: =(SUMIF('Balance N Retraitée'!A:A,"651*",'Balance N Retraitée'!G:G))-SUMIF('Balance N Retraitée'!A:A,"651*",'Balance N Retraitée'!H:H) -> 0 | G45: =(SUMIF('Balance N-1 Retraitée'!A:A,"651*",'Balance N-1 Retraitée'!G:G))-SUMIF('Balance N-1 Retraitée'!A:A,"651*",'Balance N-1 Retraitée'!H:H) -> 0
A46: I | D46: CAPACITE D'AUTOFINANCEMENT (C.A.F.) | E46: =SUM(E36:E40)-SUM(E41:E44)+E45 -> 194296.2 | G46: =SUM(G36:G40)-SUM(G41:G44)+G45 -> -18224.3
B47: 10 | D47: Distributions de bénéfices | E47: ='T14 C2-affec resu'!D13 -> 0 | G47: 0
A48: II | D48: AUTOFINANCEMENT | E48: =+E46-E47 -> 194296.2 | G48: =+G46-G47 -> -18224.3
A50: (1) à l'exclusion des dotations relatives aux actifs et passifs circulants et à la trésorerie
A51: (2) à l'exclusion des reprises relatives aux actifs et passifs circulants et à la trésorerie
A52: (3) Ycompris reprises sur subventions d'investissement

Sheet T6 TB11
A1: Tableau n° 6 | D1: Etat B11
A2: DETAIL DES POSTES DU C.P.C.
C3: Exercice clos le : | D3: ='T5 ESG'!$G$3 -> 31/12/2022
A4: POSTE | C4: Exercice | D4: Exercice Précédent
B5: CHARGES D'EXPLOITATION
A6: 611 | B6: Achats revendus de marchandises
B7: * Achats de marchandises | C7: =SUMIF('Balance N Retraitée'!A:A,"611*",'Balance N Retraitée'!G:G)-SUMIF('Balance N Retraitée'!A:A,"611*",'Balance N Retraitée'!H:H)-C8 -> 0 | D7: =SUMIF('Balance N-1 Retraitée'!A:A,"611*",'Balance N-1 Retraitée'!G:G)-SUMIF('Balance N-1 Retraitée'!A:A,"611*",'Balance N-1 Retraitée'!H:H)-D8 -> 0
B8: * Variation des stocks de marchandises (±) | C8: =SUMIF('Balance N Retraitée'!A:A,"6114*",'Balance N Retraitée'!G:G)-SUMIF('Balance N Retraitée'!A:A,"6114*",'Balance N Retraitée'!H:H) -> 0 | D8: =SUMIF('Balance N-1 Retraitée'!A:A,"6114*",'Balance N-1 Retraitée'!G:G)-SUMIF('Balance N-1 Retraitée'!A:A,"6114*",'Balance N-1 Retraitée'!H:H) -> 0
B9: Total | C9: =SUM(C7:C8) -> 0 | D9: =SUM(D7:D8) -> 0
A11: 612 | B11: Achats consommés de matières et fournitures
B12: * Achat de matières premières | C12: =SUMIF('Balance N Retraitée'!A:A,"6121*",'Balance N Retraitée'!G:G)-SUMIF('Balance N Retraitée'!A:A,"6121*",'Balance N Retraitée'!H:H) -> 0 | D12: =SUMIF('Balance N-1 Retraitée'!A:A,"6121*",'Balance N-1 Retraitée'!G:G)-SUMIF('Balance N-1 Retraitée'!A:A,"6121*",'Balance N-1 Retraitée'!H:H) -> 0
B13: * Variation des stocks de matières premières | C13: =SUMIF('Balance N Retraitée'!A:A,"61241*",'Balance N Retraitée'!G:G)-SUMIF('Balance N Retraitée'!A:A,"61241*",'Balance N Retraitée'!H:H) -> 0 | D13: =SUMIF('Balance N-1 Retraitée'!A:A,"61241*",'Balance N-1 Retraitée'!G:G)-SUMIF('Balance N-1 Retraitée'!A:A,"61241*",'Balance N-1 Retraitée'!H:H) -> 0
B14: * Achats de matières et fournitures consommables et d'emballage | C14: =SUMIF('Balance N Retraitée'!A:A,"6122*",'Balance N Retraitée'!G:G)-SUMIF('Balance N Retraitée'!A:A,"6122*",'Balance N Retraitée'!H:H)+SUMIF('Balance N Retraitée'!A:A,"6123*",'Balance N Retraitée'!G:G)-SUMIF('Balance N Retraitée'!A:A,"6123*",'Balance N Retraitée'!H:H) -> 0 | D14: =SUMIF('Balance N-1 Retraitée'!A:A,"6122*",'Balance N-1 Retraitée'!G:G)-SUMIF('Balance N-1 Retraitée'!A:A,"6122*",'Balance N-1 Retraitée'!H:H)+SUMIF('Balance N-1 Retraitée'!A:A,"6123*",'Balance N-1 Retraitée'!G:G)-SUMIF('Balance N-1 Retraitée'!A:A,"6123*",'Balance N-1 Retraitée'!H:H) -> 0
B15: * Variation des stocks de matières, fournitures et emballages (±) | C15: =SUMIF('Balance N Retraitée'!A:A,"61242*",'Balance N Retraitée'!G:G)-SUMIF('Balance N Retraitée'!A:A,"61242*",'Balance N Retraitée'!H:H) -> 0 | D15: =SUMIF('Balance N-1 Retraitée'!A:A,"61242*",'Balance N-1 Retraitée'!G:G)-SUMIF('Balance N-1 Retraitée'!A:A,"61242*",'Balance N-1 Retraitée'!H:H) -> 0
B16: * Achats non stockés de matières et de fournitures | C16: =SUMIF('Balance N Retraitée'!A:A,"6125*",'Balance N Retraitée'!G:G)-SUMIF('Balance N Retraitée'!A:A,"6125*",'Balance N Retraitée'!H:H) -> 0 | D16: =SUMIF('Balance N-1 Retraitée'!A:A,"6125*",'Balance N-1 Retraitée'!G:G)-SUMIF('Balance N-1 Retraitée'!A:A,"6125*",'Balance N-1 Retraitée'!H:H) -> 0
B17: * Achats de travaux, études et prestations de services | C17: =SUMIF('Balance N Retraitée'!A:A,"6126*",'Balance N Retraitée'!G:G)-SUMIF('Balance N Retraitée'!A:A,"6126*",'Balance N Retraitée'!H:H) -> 0 | D17: =SUMIF('Balance N-1 Retraitée'!A:A,"6126*",'Balance N-1 Retraitée'!G:G)-SUMIF('Balance N-1 Retraitée'!A:A,"6126*",'Balance N-1 Retraitée'!H:H) -> 0
B18: * Achats de matières et fournitures des exercices antérieurs | C18: =SUMIF('Balance N Retraitée'!A:A,"6128*",'Balance N Retraitée'!G:G)-SUMIF('Balance N Retraitée'!A:A,"6128*",'Balance N Retraitée'!H:H) -> 0 | D18: =SUMIF('Balance N-1 Retraitée'!A:A,"6128*",'Balance N-1 Retraitée'!G:G)-SUMIF('Balance N-1 Retraitée'!A:A,"6128*",'Balance N-1 Retraitée'!H:H) -> 0
B19: * R.R.R. obtenus sur achats consommés de matières et fournitures | C19: =SUMIF('Balance N Retraitée'!A:A,"6129*",'Balance N Retraitée'!G:G)-SUMIF('Balance N Retraitée'!A:A,"6129*",'Balance N Retraitée'!H:H) -> 0 | D19: =SUMIF('Balance N-1 Retraitée'!A:A,"6129*",'Balance N-1 Retraitée'!G:G)-SUMIF('Balance N-1 Retraitée'!A:A,"6129*",'Balance N-1 Retraitée'!H:H) -> 0
B20: Total | C20: =SUM(C12:C19) -> 0 | D20: =SUM(D12:D19) -> 0
A22: 613/614 | B22: Autres charges externes
B23: * Locations et charges locatives | C23: =SUMIF('Balance N Retraitée'!A:A,"6131*",'Balance N Retraitée'!G:G)-SUMIF('Balance N Retraitée'!A:A,"6131*",'Balance N Retraitée'!H:H) -> 12000 | D23: =SUMIF('Balance N-1 Retraitée'!A:A,"6131*",'Balance N-1 Retraitée'!G:G)-SUMIF('Balance N-1 Retraitée'!A:A,"6131*",'Balance N-1 Retraitée'!H:H) -> 5000
B24: * Redevances de crédit-bail | C24: =SUMIF('Balance N Retraitée'!A:A,"6132*",'Balance N Retraitée'!G:G)-SUMIF('Balance N Retraitée'!A:A,"6132*",'Balance N Retraitée'!H:H) -> 0 | D24: =SUMIF('Balance N-1 Retraitée'!A:A,"6132*",'Balance N-1 Retraitée'!G:G)-SUMIF('Balance N-1 Retraitée'!A:A,"6132*",'Balance N-1 Retraitée'!H:H) -> 0
B25: * Entretien et réparations | C25: =SUMIF('Balance N Retraitée'!A:A,"6133*",'Balance N Retraitée'!G:G)-SUMIF('Balance N Retraitée'!A:A,"6133*",'Balance N Retraitée'!H:H) -> 6438.04 | D25: =SUMIF('Balance N-1 Retraitée'!A:A,"6133*",'Balance N-1 Retraitée'!G:G)-SUMIF('Balance N-1 Retraitée'!A:A,"6133*",'Balance N-1 Retraitée'!H:H) -> 0
B26: * Primes d'assurances | C26: =SUMIF('Balance N Retraitée'!A:A,"6134*",'Balance N Retraitée'!G:G)-SUMIF('Balance N Retraitée'!A:A,"6134*",'Balance N Retraitée'!H:H) -> 49315.47 | D26: =SUMIF('Balance N-1 Retraitée'!A:A,"6134*",'Balance N-1 Retraitée'!G:G)-SUMIF('Balance N-1 Retraitée'!A:A,"6134*",'Balance N-1 Retraitée'!H:H) -> 0
B27: * Rémunérations du personnel extérieur à l'entreprise | C27: =SUMIF('Balance N Retraitée'!A:A,"6135*",'Balance N Retraitée'!G:G)-SUMIF('Balance N Retraitée'!A:A,"6135*",'Balance N Retraitée'!H:H) -> 0 | D27: =SUMIF('Balance N-1 Retraitée'!A:A,"6135*",'Balance N-1 Retraitée'!G:G)-SUMIF('Balance N-1 Retraitée'!A:A,"6135*",'Balance N-1 Retraitée'!H:H) -> 0
B28: * Rémunérations d'intermédiaires et honoraires | C28: =SUMIF('Balance N Retraitée'!A:A,"6136*",'Balance N Retraitée'!G:G)-SUMIF('Balance N Retraitée'!A:A,"6136*",'Balance N Retraitée'!H:H) -> 0 | D28: =SUMIF('Balance N-1 Retraitée'!A:A,"6136*",'Balance N-1 Retraitée'!G:G)-SUMIF('Balance N-1 Retraitée'!A:A,"6136*",'Balance N-1 Retraitée'!H:H) -> 0
B29: * Redevances pour brevets, marques, droits et valeurs similaires | C29: =SUMIF('Balance N Retraitée'!A:A,"6137*",'Balance N Retraitée'!G:G)-SUMIF('Balance N Retraitée'!A:A,"6137*",'Balance N Retraitée'!H:H) -> 0 | D29: =SUMIF('Balance N-1 Retraitée'!A:A,"6137*",'Balance N-1 Retraitée'!G:G)-SUMIF('Balance N-1 Retraitée'!A:A,"6137*",'Balance N-1 Retraitée'!H:H) -> 0
B30: * Transports | C30: =SUMIF('Balance N Retraitée'!A:A,"6142*",'Balance N Retraitée'!G:G)-SUMIF('Balance N Retraitée'!A:A,"6142*",'Balance N Retraitée'!H:H) -> 0 | D30: =SUMIF('Balance N-1 Retraitée'!A:A,"6142*",'Balance N-1 Retraitée'!G:G)-SUMIF('Balance N-1 Retraitée'!A:A,"6142*",'Balance N-1 Retraitée'!H:H) -> 0
B31: * Déplacements, missions et réceptions | C31: =SUMIF('Balance N Retraitée'!A:A,"6143*",'Balance N Retraitée'!G:G)-SUMIF('Balance N Retraitée'!A:A,"6143*",'Balance N Retraitée'!H:H) -> 0 | D31: =SUMIF('Balance N-1 Retraitée'!A:A,"6143*",'Balance N-1 Retraitée'!G:G)-SUMIF('Balance N-1 Retraitée'!A:A,"6143*",'Balance N-1 Retraitée'!H:H) -> 0
B32: * Reste du poste des autres charges externes | C32: =(SUMIF('Balance N Retraitée'!A:A,"613*",'Balance N Retraitée'!G:G)-SUMIF('Balance N Retraitée'!A:A,"613*",'Balance N Retraitée'!H:H))+(SUMIF('Balance N Retraitée'!A:A,"614*",'Balance N Retraitée'!G:G)-SUMIF('Balance N Retraitée'!A:A,"614*",'Balance N Retraitée'!H:H))-SUM(C23:C31) -> 10912.3 | D32: =(SUMIF('Balance N-1 Retraitée'!A:A,"613*",'Balance N-1 Retraitée'!G:G)-SUMIF('Balance N-1 Retraitée'!A:A,"613*",'Balance N-1 Retraitée'!H:H))+(SUMIF('Balance N-1 Retraitée'!A:A,"614*",'Balance N-1 Retraitée'!G:G)-SUMIF('Balance N-1 Retraitée'!A:A,"614*",'Balance N-1 Retraitée'!H:H))-SUM(D23:D31) -> 353.3
B33: Total | C33: =SUM(C23:C32) -> 78665.81 | D33: =SUM(D23:D32) -> 5353.3
A35: 617 | B35: Charges de personnel
B36: * Rémunération du personnel | C36: =SUMIF('Balance N Retraitée'!A:A,"617*",'Balance N Retraitée'!G:G)-SUMIF('Balance N Retraitée'!A:A,"617*",'Balance N Retraitée'!H:H)-C37 -> 28731 | D36: =SUMIF('Balance N-1 Retraitée'!A:A,"617*",'Balance N-1 Retraitée'!G:G)-SUMIF('Balance N-1 Retraitée'!A:A,"617*",'Balance N-1 Retraitée'!H:H)-D37 -> 10762
B37: * Charges sociales | C37: =SUMIF('Balance N Retraitée'!A:A,"6174*",'Balance N Retraitée'!G:G)-SUMIF('Balance N Retraitée'!A:A,"6174*",'Balance N Retraitée'!H:H) -> 5445.55 | D37: =SUMIF('Balance N-1 Retraitée'!A:A,"6174*",'Balance N-1 Retraitée'!G:G)-SUMIF('Balance N-1 Retraitée'!A:A,"6174*",'Balance N-1 Retraitée'!H:H) -> 2109
B38: * Reste du poste des charges de personnel | C38: =(SUMIF('Balance N Retraitée'!A:A,"617*",'Balance N Retraitée'!G:G)-SUMIF('Balance N Retraitée'!A:A,"617*",'Balance N Retraitée'!H:H))-SUM(C36:C37) -> 0 | D38: =(SUMIF('Balance N-1 Retraitée'!A:A,"617*",'Balance N-1 Retraitée'!G:G)-SUMIF('Balance N-1 Retraitée'!A:A,"617*",'Balance N-1 Retraitée'!H:H))-SUM(D36:D37) -> 0
B39: Total | C39: =SUM(C36:C38) -> 34176.55 | D39: =SUM(D36:D38) -> 12871
A41: 618 | B41: Autres charges d'exploitation
B42: * Jetons de présence | C42: =SUMIF('Balance N Retraitée'!A:A,"6181*",'Balance N Retraitée'!G:G)-SUMIF('Balance N Retraitée'!A:A,"6181*",'Balance N Retraitée'!H:H) -> 0 | D42: =SUMIF('Balance N-1 Retraitée'!A:A,"6181*",'Balance N-1 Retraitée'!G:G)-SUMIF('Balance N-1 Retraitée'!A:A,"6181*",'Balance N-1 Retraitée'!H:H) -> 0
B43: * Pertes sur créances irrécouvrabels | C43: =SUMIF('Balance N Retraitée'!A:A,"6182*",'Balance N Retraitée'!G:G)-SUMIF('Balance N Retraitée'!A:A,"6182*",'Balance N Retraitée'!H:H) -> 0 | D43: =SUMIF('Balance N-1 Retraitée'!A:A,"6182*",'Balance N-1 Retraitée'!G:G)-SUMIF('Balance N-1 Retraitée'!A:A,"6182*",'Balance N-1 Retraitée'!H:H) -> 0
B44: * Reste du poste des autres charges d'exploitation | C44: =SUMIF('Balance N Retraitée'!A:A,"618*",'Balance N Retraitée'!G:G)-SUMIF('Balance N Retraitée'!A:A,"618*",'Balance N Retraitée'!H:H)-C42-C43 -> 0 | D44: =SUMIF('Balance N-1 Retraitée'!A:A,"618*",'Balance N-1 Retraitée'!G:G)-SUMIF('Balance N-1 Retraitée'!A:A,"618*",'Balance N-1 Retraitée'!H:H)-D42-D43 -> 0
B45: Total | C45: =SUM(C42:C44) -> 0 | D45: =SUM(D42:D44) -> 0
B47: CHARGES FINANCIERS
A48: 638 | B48: Autres charges financières
B49: * Charges nettes sur cessions de titres et valeurs de placement | C49: =SUMIF('Balance N Retraitée'!A:A,"6385*",'Balance N Retraitée'!G:G)-SUMIF('Balance N Retraitée'!A:A,"6385*",'Balance N Retraitée'!H:H) -> 0 | D49: =SUMIF('Balance N-1 Retraitée'!A:A,"6385*",'Balance N-1 Retraitée'!G:G)-SUMIF('Balance N-1 Retraitée'!A:A,"6385*",'Balance N-1 Retraitée'!H:H) -> 0
B50: * Reste du poste des autres charges financières | C50: =SUMIF('Balance N Retraitée'!A:A,"638*",'Balance N Retraitée'!G:G)-SUMIF('Balance N Retraitée'!A:A,"638*",'Balance N Retraitée'!H:H)-C49 -> 0 | D50: =SUMIF('Balance N-1 Retraitée'!A:A,"638*",'Balance N-1 Retraitée'!G:G)-SUMIF('Balance N-1 Retraitée'!A:A,"638*",'Balance N-1 Retraitée'!H:H)-D49 -> 0
B51: Total | C51: =SUM(C49:C50) -> 0 | D51: =SUM(D49:D50) -> 0
B53: CHARGES NON COURANTES
A54: 658 | B54: Autres charges non courantes
B55: * Pénalités sur marchés et dédits | C55: =SUMIF('Balance N Retraitée'!A:A,"6581*",'Balance N Retraitée'!G:G)-SUMIF('Balance N Retraitée'!A:A,"6581*",'Balance N Retraitée'!H:H) -> 0 | D55: =SUMIF('Balance N-1 Retraitée'!A:A,"6581*",'Balance N-1 Retraitée'!G:G)-SUMIF('Balance N-1 Retraitée'!A:A,"6581*",'Balance N-1 Retraitée'!H:H) -> 0
B56: * Rappels d'impôts (autres qu'impôts sur les résultats) | C56: =SUMIF('Balance N Retraitée'!A:A,"6582*",'Balance N Retraitée'!G:G)-SUMIF('Balance N Retraitée'!A:A,"6582*",'Balance N Retraitée'!H:H) -> 0 | D56: =SUMIF('Balance N-1 Retraitée'!A:A,"6582*",'Balance N-1 Retraitée'!G:G)-SUMIF('Balance N-1 Retraitée'!A:A,"6582*",'Balance N-1 Retraitée'!H:H) -> 0
B57: * Pénalités et amendes fiscales | C57: =SUMIF('Balance N Retraitée'!A:A,"6583*",'Balance N Retraitée'!G:G)-SUMIF('Balance N Retraitée'!A:A,"6583*",'Balance N Retraitée'!H:H) -> 0 | D57: =SUMIF('Balance N-1 Retraitée'!A:A,"6583*",'Balance N-1 Retraitée'!G:G)-SUMIF('Balance N-1 Retraitée'!A:A,"6583*",'Balance N-1 Retraitée'!H:H) -> 0
B58: * Créances devenues irrècouvrabels | C58: =SUMIF('Balance N Retraitée'!A:A,"6585*",'Balance N Retraitée'!G:G)-SUMIF('Balance N Retraitée'!A:A,"6585*",'Balance N Retraitée'!H:H) -> 0 | D58: =SUMIF('Balance N-1 Retraitée'!A:A,"6585*",'Balance N-1 Retraitée'!G:G)-SUMIF('Balance N-1 Retraitée'!A:A,"6585*",'Balance N-1 Retraitée'!H:H) -> 0
B59: * Reste du poste des autres charges non courantes | C59: =ROUND(SUMIF('Balance N Retraitée'!A:A,"658*",'Balance N Retraitée'!G:G)-SUMIF('Balance N Retraitée'!A:A,"658*",'Balance N Retraitée'!H:H)-SUM(C55:C58),2) -> 0 | D59: =SUMIF('Balance N-1 Retraitée'!A:A,"658*",'Balance N-1 Retraitée'!G:G)-SUMIF('Balance N-1 Retraitée'!A:A,"658*",'Balance N-1 Retraitée'!H:H)-SUM(D55:D58) -> 0
B60: Total | C60: =SUM(C55:C59) -> 0 | D60: =SUM(D55:D59) -> 0
A63: Tableau n° 6
A64: DETAIL DES POSTES DU C.P.C.
A66: POSTE | C66: Exercice | D66: Exercice Précédent
B67: PRODUITS D'EXPLOITATION
A68: 711 | B68: * Ventes de marchandises
B69: * Ventes de marchandises au Maroc | C69: =SUMIF('Balance N Retraitée'!A:A,"7111*",'Balance N Retraitée'!H:H)-SUMIF('Balance N Retraitée'!A:A,"7111*",'Balance N Retraitée'!G:G) -> 0 | D69: =SUMIF('Balance N-1 Retraitée'!A:A,"7111*",'Balance N-1 Retraitée'!H:H)-SUMIF('Balance N-1 Retraitée'!A:A,"7111*",'Balance N-1 Retraitée'!G:G) -> 0
B70: * Ventes de marchandises à l'étranger | C70: =SUMIF('Balance N Retraitée'!A:A,"7113*",'Balance N Retraitée'!H:H)-SUMIF('Balance N Retraitée'!A:A,"7113*",'Balance N Retraitée'!G:G) -> 0 | D70: =SUMIF('Balance N-1 Retraitée'!A:A,"7113*",'Balance N-1 Retraitée'!H:H)-SUMIF('Balance N-1 Retraitée'!A:A,"7113*",'Balance N-1 Retraitée'!G:G) -> 0
B71: * Reste du poste des ventes de marchandises | C71: =SUMIF('Balance N Retraitée'!A:A,"711*",'Balance N Retraitée'!H:H)-SUMIF('Balance N Retraitée'!A:A,"711*",'Balance N Retraitée'!G:G)-C69-C70 -> 0 | D71: =SUMIF('Balance N-1 Retraitée'!A:A,"711*",'Balance N-1 Retraitée'!H:H)-SUMIF('Balance N-1 Retraitée'!A:A,"711*",'Balance N-1 Retraitée'!G:G)-D69-D70 -> 0
B72: Total | C72: =SUM(C69:C71) -> 0 | D72: =SUM(D69:D71) -> 0
A74: 712 | B74: * Ventes de biens et services produits
B75: *Ventes de marchandise au Maroc | C75: =SUMIF('Balance N Retraitée'!A:A,"7121*",'Balance N Retraitée'!H:H)-SUMIF('Balance N Retraitée'!A:A,"7121*",'Balance N Retraitée'!G:G) -> 0 | D75: =SUMIF('Balance N-1 Retraitée'!A:A,"7121*",'Balance N-1 Retraitée'!H:H)-SUMIF('Balance N-1 Retraitée'!A:A,"7121*",'Balance N-1 Retraitée'!G:G) -> 0
B76: *Ventes de marchandise à l'étranger | C76: =SUMIF('Balance N Retraitée'!A:A,"7122*",'Balance N Retraitée'!H:H)-SUMIF('Balance N Retraitée'!A:A,"7122*",'Balance N Retraitée'!G:G) -> 0 | D76: =SUMIF('Balance N-1 Retraitée'!A:A,"7122*",'Balance N-1 Retraitée'!H:H)-SUMIF('Balance N-1 Retraitée'!A:A,"7122*",'Balance N-1 Retraitée'!G:G) -> 0
B77: *Ventes des services au Maroc | C77: =SUMIF('Balance N Retraitée'!A:A,"7124*",'Balance N Retraitée'!H:H)-SUMIF('Balance N Retraitée'!A:A,"7124*",'Balance N Retraitée'!G:G) -> 381666.67 | D77: =SUMIF('Balance N-1 Retraitée'!A:A,"7124*",'Balance N-1 Retraitée'!H:H)-SUMIF('Balance N-1 Retraitée'!A:A,"7124*",'Balance N-1 Retraitée'!G:G) -> 0
B78: *Ventes des services à l'étranger | C78: =SUMIF('Balance N Retraitée'!A:A,"7125*",'Balance N Retraitée'!H:H)-SUMIF('Balance N Retraitée'!A:A,"7125*",'Balance N Retraitée'!G:G) -> 0 | D78: =SUMIF('Balance N-1 Retraitée'!A:A,"7125*",'Balance N-1 Retraitée'!H:H)-SUMIF('Balance N-1 Retraitée'!A:A,"7125*",'Balance N-1 Retraitée'!G:G) -> 0
B79: *Redevances pour brevets, marques, droits.. | C79: =SUMIF('Balance N Retraitée'!A:A,"7126*",'Balance N Retraitée'!H:H)-SUMIF('Balance N Retraitée'!A:A,"7126*",'Balance N Retraitée'!G:G) -> 0 | D79: =SUMIF('Balance N-1 Retraitée'!A:A,"7126*",'Balance N-1 Retraitée'!H:H)-SUMIF('Balance N-1 Retraitée'!A:A,"7126*",'Balance N-1 Retraitée'!G:G) -> 0
B80: * Reste du poste des ventes et services produits | C80: =SUMIF('Balance N Retraitée'!A:A,"712*",'Balance N Retraitée'!H:H)-SUMIF('Balance N Retraitée'!A:A,"712*",'Balance N Retraitée'!G:G)-SUM(C75:C79) -> 0 | D80: =SUMIF('Balance N-1 Retraitée'!A:A,"712*",'Balance N-1 Retraitée'!H:H)-SUMIF('Balance N-1 Retraitée'!A:A,"712*",'Balance N-1 Retraitée'!G:G)-SUM(D75:D79) -> 0
B81: Total | C81: =SUM(C75:C80) -> 381666.67 | D81: =SUM(D75:D80) -> 0
A83: 713 | B83: *Variation des stocks de produits
B84: * Variation des stocks des biens produits (+/-) | C84: =SUMIF('Balance N Retraitée'!A:A,"7132*",'Balance N Retraitée'!H:H)-SUMIF('Balance N Retraitée'!A:A,"7132*",'Balance N Retraitée'!G:G) -> 0 | D84: =SUMIF('Balance N-1 Retraitée'!A:A,"7132*",'Balance N-1 Retraitée'!H:H)-SUMIF('Balance N-1 Retraitée'!A:A,"7132*",'Balance N-1 Retraitée'!G:G) -> 0
B85: *Variation des stocks des services produits (+/-) | C85: =SUMIF('Balance N Retraitée'!A:A,"7134*",'Balance N Retraitée'!H:H)-SUMIF('Balance N Retraitée'!A:A,"7134*",'Balance N Retraitée'!G:G) -> 0 | D85: =SUMIF('Balance N-1 Retraitée'!A:A,"7134*",'Balance N-1 Retraitée'!H:H)-SUMIF('Balance N-1 Retraitée'!A:A,"7134*",'Balance N-1 Retraitée'!G:G) -> 0
B86: *Variation des stocks des produits en cours (+/-) | C86: =SUMIF('Balance N Retraitée'!A:A,"7131*",'Balance N Retraitée'!H:H)-SUMIF('Balance N Retraitée'!A:A,"7131*",'Balance N Retraitée'!G:G) -> 0 | D86: =SUMIF('Balance N-1 Retraitée'!A:A,"7131*",'Balance N-1 Retraitée'!H:H)-SUMIF('Balance N-1 Retraitée'!A:A,"7131*",'Balance N-1 Retraitée'!G:G) -> 0
B87: Total | C87: =SUM(C84:C86) -> 0 | D87: =SUM(D84:D86) -> 0
A89: 718 | B89: * Autres produits d'exploitation
B90: * Jetons de présence reçus | C90: =SUMIF('Balance N Retraitée'!A:A,"7181*",'Balance N Retraitée'!H:H)-SUMIF('Balance N Retraitée'!A:A,"7181*",'Balance N Retraitée'!G:G) -> 0 | D90: =SUMIF('Balance N-1 Retraitée'!A:A,"7181*",'Balance N-1 Retraitée'!H:H)-SUMIF('Balance N-1 Retraitée'!A:A,"7181*",'Balance N-1 Retraitée'!G:G) -> 0
B91: *Reste du poste (produits divers) | C91: =SUMIF('Balance N Retraitée'!A:A,"718*",'Balance N Retraitée'!H:H)-SUMIF('Balance N Retraitée'!A:A,"718*",'Balance N Retraitée'!G:G)-C90 -> 0 | D91: =SUMIF('Balance N-1 Retraitée'!A:A,"718*",'Balance N-1 Retraitée'!H:H)-SUMIF('Balance N-1 Retraitée'!A:A,"718*",'Balance N-1 Retraitée'!G:G)-D90 -> 0
B92: Total | C92: =SUM(C90:C91) -> 0 | D92: =SUM(D90:D91) -> 0
A94: 719 | B94: Reprises d'exploitation transferts de charges
B95: *Reprises | C95: =SUMIF('Balance N Retraitée'!A:A,"719*",'Balance N Retraitée'!H:H)-SUMIF('Balance N Retraitée'!A:A,"719*",'Balance N Retraitée'!G:G)-C96 -> 0 | D95: =SUMIF('Balance N-1 Retraitée'!A:A,"719*",'Balance N-1 Retraitée'!H:H)-SUMIF('Balance N-1 Retraitée'!A:A,"719*",'Balance N-1 Retraitée'!G:G)-D96 -> 0
B96: *Transferts de charges | C96: =SUMIF('Balance N Retraitée'!A:A,"7197*",'Balance N Retraitée'!H:H)-SUMIF('Balance N Retraitée'!A:A,"7197*",'Balance N Retraitée'!G:G) -> 0 | D96: =SUMIF('Balance N-1 Retraitée'!A:A,"7197*",'Balance N-1 Retraitée'!H:H)-SUMIF('Balance N-1 Retraitée'!A:A,"7197*",'Balance N-1 Retraitée'!G:G) -> 0
B97: Total | C97: =SUM(C95:C96) -> 0 | D97: =SUM(D95:D96) -> 0
B99: PRODUITS FINANCIERS
A100: 738 | B100: * Intérêts et autres produits financiers
B101: *Intérêts et produits assimilés | C101: =SUMIF('Balance N Retraitée'!A:A,"7381*",'Balance N Retraitée'!H:H)-SUMIF('Balance N Retraitée'!A:A,"7381*",'Balance N Retraitée'!G:G) -> 0 | D101: =SUMIF('Balance N-1 Retraitée'!A:A,"7381*",'Balance N-1 Retraitée'!H:H)-SUMIF('Balance N-1 Retraitée'!A:A,"7381*",'Balance N-1 Retraitée'!G:G) -> 0
B102: *Revenus des créances rattachées à des participations | C102: =SUMIF('Balance N Retraitée'!A:A,"7383*",'Balance N Retraitée'!H:H)-SUMIF('Balance N Retraitée'!A:A,"7383*",'Balance N Retraitée'!G:G) -> 0 | D102: =SUMIF('Balance N-1 Retraitée'!A:A,"7383*",'Balance N-1 Retraitée'!H:H)-SUMIF('Balance N-1 Retraitée'!A:A,"7383*",'Balance N-1 Retraitée'!G:G) -> 0
B103: *Produits nets sur cessions de titres et valeurs de placement | C103: =SUMIF('Balance N Retraitée'!A:A,"7385*",'Balance N Retraitée'!H:H)-SUMIF('Balance N Retraitée'!A:A,"7385*",'Balance N Retraitée'!G:G) -> 0 | D103: =SUMIF('Balance N-1 Retraitée'!A:A,"7385*",'Balance N-1 Retraitée'!H:H)-SUMIF('Balance N-1 Retraitée'!A:A,"7385*",'Balance N-1 Retraitée'!G:G) -> 0
B104: *Reste du poste intérêts et autres produits financiers | C104: =SUMIF('Balance N Retraitée'!A:A,"738*",'Balance N Retraitée'!H:H)-SUMIF('Balance N Retraitée'!A:A,"738*",'Balance N Retraitée'!G:G)-C101-C102-C103 -> 0 | D104: =SUMIF('Balance N-1 Retraitée'!A:A,"738*",'Balance N-1 Retraitée'!H:H)-SUMIF('Balance N-1 Retraitée'!A:A,"738*",'Balance N-1 Retraitée'!G:G)-D101-D102-D103 -> 0
B105: Total | C105: =SUM(C101:C104) -> 0 | D105: =SUM(D101:D104) -> 0

Sheet T7 CNCET B10-CB
A1: Tableau n° 7 | K1: Etat B10
E2: TABLEAU DES BIENS EN CREDIT-BAIL
I4: =+'B9-Eng fin'!C8 -> Exercice clos le : | K4: ='T5 ESG'!$G$3 -> 31/12/2022
B5: Date | C5: Durée | D5: Valeur | E5: Durée | F5: Cumul des | G5: Montant de | H5: redevances restantes | J5: Prix d'achat
B6: de la 1ère | C6: du contrat | D6: estimée du | E6: théorique | F6: exercices | G6: l'exercice | H6: à payer | J6: résiduel | K6: Observations
A7: Rubriques | B7: échéance | C7: en mois | D7: bien à la | E7: d'amortis- | F7: précédents | G7: des | H7: A moins | I7: A plus | J7: en fin de
D8: date du | E8: sement du | F8: des | G8: redevances | H8: d'un an | I8: d'un an | J8: contrat
D9: contrat | E9: bien | F9: redevances
A10: 1 | B10: 2 | C10: 3 | D10: 4 | E10: 5 | F10: 6 | G10: 7 | H10: 8 | I10: 9 | J10: 10 | K10: 11
F17: =SUM(F11:F16) -> 0 | G17: =SUM(G11:G16) -> 0 | H17: =SUM(H11:H16) -> 0 | I17: =SUM(I11:I16) -> 0 | J17: =SUM(J11:J16) -> 0
A19: Cadrage crédit bail avec détail CPC | G19: ='T6 TB11'!C24 -> 0
A21: Ecart | G21: =G17-G19 -> 0

Sheet T8 B2 BIS
A1: Tableau n° 8 | E1: Etat B2 Bis
A2: TABLEAU DES AMORTISSEMENTS
D4: Exercice clos le : | E4: ='T5 ESG'!$G$3 -> 31/12/2022
B5: Cumul début | C5: Dotation de | D5: Amortissements | E5: Cumul d'amor-
A6: NATURE | B6: exercice | C6: l'exercice | D6: sur immobilis- | E6: tissement fin
D7: sorties | E7: exercice
B8: 1 | C8: 2 | D8: 3 | E8: 4 = 1+2-3 | F8: Ecart
A9: IMMOBILISATION EN NON-VALEURS | B9: =SUM(B11:B13) -> 694.37 | C9: =SUM(C11:C13) -> 1666.5 | D9: =SUM(D11:D13) -> 0 | E9: =SUM(E10:E13) -> 2360.87 | F9: =SUM(F11:F13) -> 0
A11: * Frais préliminaires | B11: =SUMIF('Balance N-1 Retraitée'!A:A,"2811*",'Balance N-1 Retraitée'!H:H)-SUMIF('Balance N-1 Retraitée'!A:A,"2811*",'Balance N-1 Retraitée'!G:G) -> 694.37 | C11: =SUMIF('Balance N Retraitée'!A:A,"2811*",'Balance N Retraitée'!F:F)-694.37 -> 1666.5 | D11: =SUMIF('Balance N Retraitée'!A:A,"2811*",'Balance N Retraitée'!E:E) -> 0 | E11: =+B11+C11-D11 -> 2360.87 | F11: =SUMIF('Balance N Retraitée'!A:A,"2811*",'Balance N Retraitée'!H:H)-SUMIF('Balance N Retraitée'!A:A,"2811*",'Balance N Retraitée'!G:G)-E11 -> 0
A12: * Charges à répartir sur plusieurs exercices | B12: =SUMIF('Balance N-1 Retraitée'!A:A,"2812*",'Balance N-1 Retraitée'!H:H)-SUMIF('Balance N-1 Retraitée'!A:A,"2812*",'Balance N-1 Retraitée'!G:G) -> 0 | C12: =SUMIF('Balance N Retraitée'!A:A,"2812*",'Balance N Retraitée'!F:F) -> 0 | D12: =+SUMIF('Balance N Retraitée'!A:A,"2812*",'Balance N Retraitée'!E:E) -> 0 | E12: =+B12+C12-D12 -> 0 | F12: =SUMIF('Balance N Retraitée'!A:A,"2812*",'Balance N Retraitée'!H:H)-SUMIF('Balance N Retraitée'!A:A,"2812*",'Balance N Retraitée'!G:G)-E12 -> 0
A13: * Primes de remboursement des obligations | B13: =SUMIF('Balance N-1 Retraitée'!A:A,"2813*",'Balance N-1 Retraitée'!H:H)-SUMIF('Balance N-1 Retraitée'!A:A,"2813*",'Balance N-1 Retraitée'!G:G) -> 0 | C13: =SUMIF('Balance N Retraitée'!A:A,"2813*",'Balance N Retraitée'!F:F) -> 0 | D13: =+SUMIF('Balance N Retraitée'!A:A,"2813*",'Balance N Retraitée'!E:E) -> 0 | E13: =+B13+C13-D13 -> 0 | F13: =SUMIF('Balance N Retraitée'!A:A,"2813*",'Balance N Retraitée'!H:H)-SUMIF('Balance N Retraitée'!A:A,"2813*",'Balance N Retraitée'!G:G)-E13 -> 0
E14: =+B14+C14-D14 -> 0
E15: =SUMIF('Balance N Retraitée'!A:A,"7138*",'Balance N Retraitée'!H:H)-SUMIF('Balance N Retraitée'!A:A,"7138*",'Balance N Retraitée'!G:G) -> 0
A16: IMMOBILISATIONS INCORPORELLES | B16: =SUM(B18:B21) -> 0 | C16: =SUM(C18:C21) -> 0 | D16: =SUM(D18:D21) -> 0 | E16: =SUM(E18:E21) -> 0 | F16: =SUM(F18:F21) -> 0
A18: * Immobilisation en recherche et développement | B18: =SUMIF('Balance N-1 Retraitée'!A:A,"2821*",'Balance N-1 Retraitée'!H:H)-SUMIF('Balance N-1 Retraitée'!A:A,"2821*",'Balance N-1 Retraitée'!G:G) -> 0 | C18: =SUMIF('Balance N Retraitée'!A:A,"2821*",'Balance N Retraitée'!F:F) -> 0 | D18: =+SUMIF('Balance N Retraitée'!A:A,"2821*",'Balance N Retraitée'!E:E) -> 0 | E18: =+B18+C18-D18 -> 0 | F18: =SUMIF('Balance N Retraitée'!A:A,"2821*",'Balance N Retraitée'!H:H)-SUMIF('Balance N Retraitée'!A:A,"2821*",'Balance N Retraitée'!G:G)-E18 -> 0
A19: * Brevets, marques droits et valeurs similaires | B19: =SUMIF('Balance N-1 Retraitée'!A:A,"2822*",'Balance N-1 Retraitée'!H:H)-SUMIF('Balance N-1 Retraitée'!A:A,"2822*",'Balance N-1 Retraitée'!G:G) -> 0 | C19: =SUMIF('Balance N Retraitée'!A:A,"2822*",'Balance N Retraitée'!F:F) -> 0 | D19: =+SUMIF('Balance N Retraitée'!A:A,"2822*",'Balance N Retraitée'!E:E) -> 0 | E19: =+B19+C19-D19 -> 0 | F19: =SUMIF('Balance N Retraitée'!A:A,"2822*",'Balance N Retraitée'!H:H)-SUMIF('Balance N Retraitée'!A:A,"2822*",'Balance N Retraitée'!G:G)-E19 -> 0
A20: * Fonds commercial | B20: =SUMIF('Balance N-1 Retraitée'!A:A,"2823*",'Balance N-1 Retraitée'!H:H)-SUMIF('Balance N-1 Retraitée'!A:A,"2823*",'Balance N-1 Retraitée'!G:G) -> 0 | C20: =SUMIF('Balance N Retraitée'!A:A,"2823*",'Balance N Retraitée'!F:F) -> 0 | D20: =+SUMIF('Balance N Retraitée'!A:A,"2823*",'Balance N Retraitée'!E:E) -> 0 | E20: =+B20+C20-D20 -> 0 | F20: =SUMIF('Balance N Retraitée'!A:A,"2823*",'Balance N Retraitée'!H:H)-SUMIF('Balance N Retraitée'!A:A,"2823*",'Balance N Retraitée'!G:G)-E20 -> 0
A21: * Autres immobilisations incorporelles | B21: =SUMIF('Balance N-1 Retraitée'!A:A,"2828*",'Balance N-1 Retraitée'!H:H)-SUMIF('Balance N-1 Retraitée'!A:A,"2828*",'Balance N-1 Retraitée'!G:G) -> 0 | C21: =SUMIF('Balance N Retraitée'!A:A,"2828*",'Balance N Retraitée'!F:F) -> 0 | D21: =+SUMIF('Balance N Retraitée'!A:A,"2828*",'Balance N Retraitée'!E:E) -> 0 | E21: =+B21+C21-D21 -> 0 | F21: =SUMIF('Balance N Retraitée'!A:A,"2828*",'Balance N Retraitée'!H:H)-SUMIF('Balance N Retraitée'!A:A,"2828*",'Balance N Retraitée'!G:G)-E21 -> 0
A23: IMMOBILISATIONS CORPORELLES | B23: =SUM(B24:B31) -> 0 | C23: =SUM(C24:C31) -> 171177.26 | D23: =SUM(D24:D31) -> 0 | E23: =SUM(E24:E31) -> 171177.26 | F23: =SUM(F24:F31) -> 0
A25: * Terrains | B25: =SUMIF('Balance N-1 Retraitée'!A:A,"2831*",'Balance N-1 Retraitée'!H:H)-SUMIF('Balance N-1 Retraitée'!A:A,"2831*",'Balance N-1 Retraitée'!G:G) -> 0 | C25: =SUMIF('Balance N Retraitée'!A:A,"2831*",'Balance N Retraitée'!F:F) -> 0 | D25: =+SUMIF('Balance N Retraitée'!A:A,"2831*",'Balance N Retraitée'!E:E) -> 0 | E25: =+B25+C25-D25 -> 0 | F25: =SUMIF('Balance N Retraitée'!A:A,"2831*",'Balance N Retraitée'!H:H)-SUMIF('Balance N Retraitée'!A:A,"2831*",'Balance N Retraitée'!G:G)-E25 -> 0
A26: * Constructions | B26: =SUMIF('Balance N-1 Retraitée'!A:A,"2832*",'Balance N-1 Retraitée'!H:H)-SUMIF('Balance N-1 Retraitée'!A:A,"2832*",'Balance N-1 Retraitée'!G:G) -> 0 | C26: =SUMIF('Balance N Retraitée'!A:A,"2832*",'Balance N Retraitée'!F:F) -> 1215 | D26: =+SUMIF('Balance N Retraitée'!A:A,"2832*",'Balance N Retraitée'!E:E) -> 0 | E26: =+B26+C26-D26 -> 1215 | F26: =SUMIF('Balance N Retraitée'!A:A,"2832*",'Balance N Retraitée'!H:H)-SUMIF('Balance N Retraitée'!A:A,"2832*",'Balance N Retraitée'!G:G)-E26 -> 0
A27: * Installations techniques; matériel et outillage | B27: =SUMIF('Balance N-1 Retraitée'!A:A,"2833*",'Balance N-1 Retraitée'!H:H)-SUMIF('Balance N-1 Retraitée'!A:A,"2833*",'Balance N-1 Retraitée'!G:G) -> 0 | C27: =SUMIF('Balance N Retraitée'!A:A,"2833*",'Balance N Retraitée'!F:F) -> 0 | D27: =+SUMIF('Balance N Retraitée'!A:A,"2833*",'Balance N Retraitée'!E:E) -> 0 | E27: =+B27+C27-D27 -> 0 | F27: =SUMIF('Balance N Retraitée'!A:A,"2833*",'Balance N Retraitée'!H:H)-SUMIF('Balance N Retraitée'!A:A,"2833*",'Balance N Retraitée'!G:G)-E27 -> 0
A28: * Matériel de transport | B28: =SUMIF('Balance N-1 Retraitée'!A:A,"2834*",'Balance N-1 Retraitée'!H:H)-SUMIF('Balance N-1 Retraitée'!A:A,"2834*",'Balance N-1 Retraitée'!G:G) -> 0 | C28: =SUMIF('Balance N Retraitée'!A:A,"2834*",'Balance N Retraitée'!F:F) -> 169962.26 | D28: =+SUMIF('Balance N Retraitée'!A:A,"2834*",'Balance N Retraitée'!E:E) -> 0 | E28: =+B28+C28-D28 -> 169962.26 | F28: =SUMIF('Balance N Retraitée'!A:A,"2834*",'Balance N Retraitée'!H:H)-SUMIF('Balance N Retraitée'!A:A,"2834*",'Balance N Retraitée'!G:G)-E28 -> 0
A29: * Mobilier, matériel de bureau et aménagements | B29: =SUMIF('Balance N-1 Retraitée'!A:A,"2835*",'Balance N-1 Retraitée'!H:H)-SUMIF('Balance N-1 Retraitée'!A:A,"2835*",'Balance N-1 Retraitée'!G:G) -> 0 | C29: =SUMIF('Balance N Retraitée'!A:A,"2835*",'Balance N Retraitée'!F:F) -> 0 | D29: =+SUMIF('Balance N Retraitée'!A:A,"2835*",'Balance N Retraitée'!E:E) -> 0 | E29: =+B29+C29-D29 -> 0 | F29: =SUMIF('Balance N Retraitée'!A:A,"2835*",'Balance N Retraitée'!H:H)-SUMIF('Balance N Retraitée'!A:A,"2835*",'Balance N Retraitée'!G:G)-E29 -> 0
A30: * Autres immobilisations corporelles | B30: =SUMIF('Balance N-1 Retraitée'!A:A,"2838*",'Balance N-1 Retraitée'!H:H)-SUMIF('Balance N-1 Retraitée'!A:A,"2838*",'Balance N-1 Retraitée'!G:G) -> 0 | C30: =SUMIF('Balance N Retraitée'!A:A,"2838*",'Balance N Retraitée'!F:F) -> 0 | D30: =+SUMIF('Balance N Retraitée'!A:A,"2838*",'Balance N Retraitée'!E:E) -> 0 | E30: =+B30+C30-D30 -> 0 | F30: =SUMIF('Balance N Retraitée'!A:A,"2838*",'Balance N Retraitée'!H:H)-SUMIF('Balance N Retraitée'!A:A,"2838*",'Balance N Retraitée'!G:G)-E30 -> 0
A31: * Immobilisations corporelles en cours | B31: =SUMIF('Balance N-1 Retraitée'!A:A,"2839*",'Balance N-1 Retraitée'!H:H)-SUMIF('Balance N-1 Retraitée'!A:A,"2839*",'Balance N-1 Retraitée'!G:G) -> 0 | C31: =SUMIF('Balance N Retraitée'!A:A,"2839*",'Balance N Retraitée'!F:F) -> 0 | D31: =+SUMIF('Balance N Retraitée'!A:A,"2839*",'Balance N Retraitée'!E:E) -> 0 | E31: =+B31+C31-D31 -> 0 | F31: =SUMIF('Balance N Retraitée'!A:A,"2839*",'Balance N Retraitée'!H:H)-SUMIF('Balance N Retraitée'!A:A,"2839*",'Balance N Retraitée'!G:G)-E31 -> 0
A33: Total | B33: =B9+B16+B23 -> 694.37 | C33: =C9+C16+C23 -> 172843.76 | D33: =D9+D16+D23 -> 0 | E33: =E9+E16+E23 -> 173538.13

Sheet T9 B5-PROV
A1: Tableau n° 9 | I1: Etat B5
D2: TABLEAU DES PROVISIONS
G3: =+'T8 B2 BIS'!D4 -> Exercice clos le : | I3: ='T5 ESG'!$G$3 -> 31/12/2022
A4: NATURE | B4: Montant début | D4: DOTATIONS | G4: REPRISES | I4: Montant fin
B5: exercice | C5: D'exploitation | D5: financières | E5: Non courantes | F5: d'exploitation | G5: financières | H5: Non courantes | I5: exercice | J5: Ecart
A6: 1. Provisions pour
A7: dépréciation de
A8: l'actif immobilisé | B8: =SUMIF('Balance N-1 Retraitée'!A:A,"29*",'Balance N-1 Retraitée'!H:H)-SUMIF('Balance N-1 Retraitée'!A:A,"29*",'Balance N-1 Retraitée'!G:G) -> 0 | D8: =SUMIF('Balance N Retraitée'!$A:$A,"6392*",'Balance N Retraitée'!$G:$G)-SUMIF('Balance N Retraitée'!$A:$A,"6392*",'Balance N Retraitée'!$H:$H) -> 0 | E8: =SUMIF('Balance N Retraitée'!$A:$A,"65962*",'Balance N Retraitée'!$G:$G)-SUMIF('Balance N Retraitée'!$A:$A,"65962*",'Balance N Retraitée'!$H:$H) -> 0 | F8: =SUMIF('Balance N Retraitée'!$A:$A,"7194*",'Balance N Retraitée'!$G:$G)-SUMIF('Balance N Retraitée'!$A:$A,"7194*",'Balance N Retraitée'!$H:$H) -> 0 | G8: =SUMIF('Balance N Retraitée'!$A:$A,"7392*",'Balance N Retraitée'!$G:$G)-SUMIF('Balance N Retraitée'!$A:$A,"7392*",'Balance N Retraitée'!$H:$H) -> 0 | H8: =SUMIF('Balance N Retraitée'!$A:$A,"75962*",'Balance N Retraitée'!$G:$G)-SUMIF('Balance N Retraitée'!$A:$A,"75962*",'Balance N Retraitée'!$H:$H) -> 0 | I8: =B8+SUM(C8:E8)-SUM(F8:H8) -> 0 | J8: =SUMIF('Balance N Retraitée'!A:A,"29*",'Balance N Retraitée'!H:H)-SUMIF('Balance N Retraitée'!A:A,"29*",'Balance N Retraitée'!G:G)-I8 -> 0
A10: 2. Provisions régle- | B10: =SUMIF('Balance N-1 Retraitée'!A:A,"135*",'Balance N-1 Retraitée'!H:H)-SUMIF('Balance N-1 Retraitée'!A:A,"135*",'Balance N-1 Retraitée'!G:G) -> 0 | E10: =SUMIF('Balance N Retraitée'!$A:$A,"6594*",'Balance N Retraitée'!$G:$G)-SUMIF('Balance N Retraitée'!$A:$A,"6594*",'Balance N Retraitée'!$H:$H) -> 0 | H10: =SUMIF('Balance N Retraitée'!$A:$A,"7594*",'Balance N Retraitée'!$G:$G)-SUMIF('Balance N Retraitée'!$A:$A,"7594*",'Balance N Retraitée'!$H:$H) -> 0 | I10: =B10+SUM(C10:E10)-SUM(F10:H10) -> 0 | J10: =SUMIF('Balance N Retraitée'!A:A,"135*",'Balance N Retraitée'!H:H)-SUMIF('Balance N Retraitée'!A:A,"135*",'Balance N Retraitée'!G:G)-I10 -> 0
A11: mentées
A13: 3. Provisions dura- | B13: =SUMIF('Balance N-1 Retraitée'!A:A,"15*",'Balance N-1 Retraitée'!H:H)-SUMIF('Balance N-1 Retraitée'!A:A,"15*",'Balance N-1 Retraitée'!G:G) -> 0 | C13: =SUMIF('Balance N Retraitée'!$A:$A,"61955*",'Balance N Retraitée'!$G:$G)-SUMIF('Balance N Retraitée'!$A:$A,"61955*",'Balance N Retraitée'!$H:$H) -> 0 | D13: =SUMIF('Balance N Retraitée'!$A:$A,"63935*",'Balance N Retraitée'!$G:$G)-SUMIF('Balance N Retraitée'!$A:$A,"63935*",'Balance N Retraitée'!$H:$H) -> 0 | E13: =SUMIF('Balance N Retraitée'!$A:$A,"65955*",'Balance N Retraitée'!$G:$G)-SUMIF('Balance N Retraitée'!$A:$A,"65955*",'Balance N Retraitée'!$H:$H) -> 0 | F13: =SUMIF('Balance N Retraitée'!$A:$A,"71955*",'Balance N Retraitée'!$G:$G)-SUMIF('Balance N Retraitée'!$A:$A,"71955*",'Balance N Retraitée'!$H:$H) -> 0 | G13: =SUMIF('Balance N Retraitée'!$A:$A,"73935*",'Balance N Retraitée'!$G:$G)-SUMIF('Balance N Retraitée'!$A:$A,"73935*",'Balance N Retraitée'!$H:$H) -> 0 | H13: =SUMIF('Balance N Retraitée'!$A:$A,"75955*",'Balance N Retraitée'!$G:$G)-SUMIF('Balance N Retraitée'!$A:$A,"75955*",'Balance N Retraitée'!$H:$H) -> 0 | I13: =B13+SUM(C13:E13)-SUM(F13:H13) -> 0 | J13: =SUMIF('Balance N Retraitée'!A:A,"15*",'Balance N Retraitée'!H:H)-SUMIF('Balance N Retraitée'!A:A,"15*",'Balance N Retraitée'!G:G)-I13 -> 0
A14: bles pour risques
A15: et charges
A17: SOUS TOTAL (A) | B17: =SUM(B6:B16) -> 0 | C17: =SUM(C6:C16) -> 0 | D17: =SUM(D6:D16) -> 0 | E17: =SUM(E6:E16) -> 0 | F17: =SUM(F6:F16) -> 0 | G17: =SUM(G6:G16) -> 0 | H17: =SUM(H6:H16) -> 0 | I17: =SUM(I6:I16) -> 0 | J17: =SUM(J3:J16) -> 0
A19: 4. Provisions pour
A20: dépréciation de | B20: =SUMIF('Balance N-1 Retraitée'!A:A,"39*",'Balance N-1 Retraitée'!H:H)-SUMIF('Balance N-1 Retraitée'!A:A,"39*",'Balance N-1 Retraitée'!G:G) -> 0 | C20: =SUMIF('Balance N Retraitée'!$A:$A,"6196*",'Balance N Retraitée'!$G:$G)-SUMIF('Balance N Retraitée'!$A:$A,"6196*",'Balance N Retraitée'!$H:$H) -> 0 | D20: =SUMIF('Balance N Retraitée'!$A:$A,"6394*",'Balance N Retraitée'!$G:$G)-SUMIF('Balance N Retraitée'!$A:$A,"6394*",'Balance N Retraitée'!$H:$H) -> 0 | E20: =SUMIF('Balance N Retraitée'!$A:$A,"65963*",'Balance N Retraitée'!$G:$G)-SUMIF('Balance N Retraitée'!$A:$A,"65963*",'Balance N Retraitée'!$H:$H) -> 0 | F20: =SUMIF('Balance N Retraitée'!$A:$A,"7196*",'Balance N Retraitée'!$G:$G)-SUMIF('Balance N Retraitée'!$A:$A,"7196*",'Balance N Retraitée'!$H:$H) -> 0 | G20: =SUMIF('Balance N Retraitée'!$A:$A,"7394*",'Balance N Retraitée'!$G:$G)-SUMIF('Balance N Retraitée'!$A:$A,"7394*",'Balance N Retraitée'!$H:$H) -> 0 | H20: =SUMIF('Balance N Retraitée'!$A:$A,"75963*",'Balance N Retraitée'!$G:$G)-SUMIF('Balance N Retraitée'!$A:$A,"75963*",'Balance N Retraitée'!$H:$H) -> 0 | I20: =B20+SUM(C20:E20)-SUM(F20:H20) -> 0 | J20: =SUMIF('Balance N Retraitée'!A:A,"39*",'Balance N Retraitée'!H:H)-SUMIF('Balance N Retraitée'!A:A,"39*",'Balance N Retraitée'!G:G)-I20 -> 0
A21: l'actif circulant
A22: (hors trésorerie)
A24: 5. Autres
A25: Provisions pour | B25: =SUMIF('Balance N-1 Retraitée'!A:A,"45*",'Balance N-1 Retraitée'!H:H)-SUMIF('Balance N-1 Retraitée'!A:A,"45*",'Balance N-1 Retraitée'!G:G) -> 0 | C25: =SUMIF('Balance N Retraitée'!$A:$A,"61957*",'Balance N Retraitée'!$G:$G)-SUMIF('Balance N Retraitée'!$A:$A,"61957*",'Balance N Retraitée'!$H:$H) -> 0 | D25: =SUMIF('Balance N Retraitée'!$A:$A,"6393*",'Balance N Retraitée'!$G:$G)-SUMIF('Balance N Retraitée'!$A:$A,"6393*",'Balance N Retraitée'!$H:$H) -> 0 | E25: =SUMIF('Balance N Retraitée'!$A:$A,"65957*",'Balance N Retraitée'!$G:$G)-SUMIF('Balance N Retraitée'!$A:$A,"65957*",'Balance N Retraitée'!$H:$H) -> 0 | F25: =SUMIF('Balance N Retraitée'!$A:$A,"71957*",'Balance N Retraitée'!$G:$G)-SUMIF('Balance N Retraitée'!$A:$A,"71957*",'Balance N Retraitée'!$H:$H) -> 0 | G25: =SUMIF('Balance N Retraitée'!$A:$A,"7393*",'Balance N Retraitée'!$H:$H)-SUMIF('Balance N Retraitée'!$A:$A,"7393*",'Balance N Retraitée'!$G:$G) -> 0 | H25: =SUMIF('Balance N Retraitée'!$A:$A,"75957*",'Balance N Retraitée'!$G:$G)-SUMIF('Balance N Retraitée'!$A:$A,"75957*",'Balance N Retraitée'!$H:$H) -> 0 | I25: =B25+SUM(C25:E25)-SUM(F25:H25) -> 0 | J25: =SUMIF('Balance N Retraitée'!A:A,"45*",'Balance N Retraitée'!H:H)-SUMIF('Balance N Retraitée'!A:A,"45*",'Balance N Retraitée'!G:G)-I25 -> 0
A26: risques et charge
A28: 6. Provisions pour
A29: dépréciation des | B29: =SUMIF('Balance N-1 Retraitée'!A:A,"59*",'Balance N-1 Retraitée'!H:H)-SUMIF('Balance N-1 Retraitée'!A:A,"59*",'Balance N-1 Retraitée'!G:G) -> 0 | D29: =SUMIF('Balance N Retraitée'!$A:$A,"6396*",'Balance N Retraitée'!$G:$G)-SUMIF('Balance N Retraitée'!$A:$A,"6396*",'Balance N Retraitée'!$H:$H) -> 0 | G29: =SUMIF('Balance N Retraitée'!$A:$A,"7396*",'Balance N Retraitée'!$G:$G)-SUMIF('Balance N Retraitée'!$A:$A,"7396*",'Balance N Retraitée'!$H:$H) -> 0 | I29: =B29+SUM(C29:E29)-SUM(F29:H29) -> 0 | J29: =SUMIF('Balance N Retraitée'!A:A,"59*",'Balance N Retraitée'!H:H)-SUMIF('Balance N Retraitée'!A:A,"59*",'Balance N Retraitée'!G:G)-I29 -> 0
A30: comptes de
A31: trésorerie
A32: SOUS TOTAL (B) | B32: =SUM(B18:B31) -> 0 | C32: =SUM(C18:C31) -> 0 | D32: =SUM(D18:D31) -> 0 | E32: =SUM(E18:E31) -> 0 | F32: =SUM(F18:F31) -> 0 | G32: =SUM(G18:G31) -> 0 | I32: =SUM(I18:I31) -> 0 | J32: =SUM(J18:J31) -> 0
A33: TOTAL (A+B) | B33: =+B32+B17 -> 0 | C33: =+C32+C17 -> 0 | D33: =+D32+D17 -> 0 | E33: =+E32+E17 -> 0 | F33: =+F32+F17 -> 0 | G33: =+G32+G17 -> 0 | H33: =+H32+H17 -> 0 | I33: =+I32+I17 -> 0 | J33: =+J32+J17 -> 0

Sheet T10 B3-+-Value
A1: Tableau n° 10 | H1: Etat B3
A4: TABLEAU DES PLUS OU MOINS VALUES SUR CESSIONS OU RETRAITS
A5: D'IMMOBILISATIONS
G7: =+'T8 B2 BIS'!D4 -> Exercice clos le : | H7: ='T5 ESG'!$G$3 -> 31/12/2022
A8: Date de cession | B8: Compte | C8: Montant | D8: Amortissements | E8: Valeur nette | F8: Produit de | G8: Plus | H8: Moins
A9: ou de retrait | B9: principal | C9: brut | D9: cumulés | E9: d'amortissements | F9: cession | G9: values | H9: values
H10: =IF(E10>F10,E10-F10,0) -> 0
H11: =IF(E11>F11,E11-F11,0) -> 0
H12: =IF(E12>F12,E12-F12,0) -> 0
H13: =IF(E13>F13,E13-F13,0) -> 0
H14: =IF(E14>F14,E14-F14,0) -> 0
E15: =+C15-D15 -> 0 | G15: =IF(F15>E15,F15-E15,0) -> 0 | H15: =IF(E15>F15,E15-F15,0) -> 0
A16: TOTAL | B16: =SUM(B10:B15) -> 0 | C16: =SUM(C10:C15) -> 0 | D16: =SUM(D10:D15) -> 0 | E16: =SUM(E10:E15) -> 0 | F16: =SUM(F10:F15) -> 0 | G16: =SUM(G10:G15) -> 0 | H16: =SUM(H10:H15) -> 0
A19: Cadrage T4 Immobilisations | C19: ='T4 B2-immo'!F30+'T4 B2-immo'!G30 -> 0
A21: Cadrage T8 Amortissements | D21: ='T8 B2 BIS'!D33 -> 0
A23: Cadrage T2 CPC | E23: ='T2 CPC'!F64 -> 0 | F23: ='T2 CPC'!F57 -> 0
A25: Ecart | C25: =C16-SUM(C19:C23) -> 0 | D25: =D16-SUM(D19:D23) -> 0 | E25: =E16-SUM(E19:E23) -> 0 | F25: =F16-SUM(F19:F23) -> 0

Sheet T11 B4-Titres part
A1: Tableau n° 11 | J1: Etat B4
A3: TABLEAU DES TITRES DE PARTICIPATION
H5: =+'T8 B2 BIS'!D4 -> Exercice clos le : | J5: ='T5 ESG'!$G$3 -> 31/12/2022
A6: Raison sociale | B6: Secteur | C6: Capital | D6: Partici- | E6: Prix | F6: Valeur | G6: Extrait des derniers états de | J6: Produits
A7: de la | B7: d'activité | C7: social | D7: pation | E7: d'acquisition | F7: comptable | G7: synthèse de la société émettrice | J7: inscrits
A8: société émettrice | D8: au capital | E8: global | F8: nette | G8: Date de | H8: Situation | I8: résultat | J8: au C.P.C
D9: % | G9: clôture | H9: nette | I9: net | J9: de l'exercice
B10: 1 | C10: 2 | D10: 3 | E10: 4 | F10: 5 | G10: 6 | H10: 7 | I10: 8 | J10: 9
A15: TOTAL | E15: =SUM(E11:E14) -> 0 | F15: =SUM(F11:F14) -> 0 | J15: =SUM(J11:J14) -> 0
A18: Cadrage T1 Bilan | E18: ='T1 Bilan'!C28 -> 0 | F18: ='T1 Bilan'!E28 -> 0
A19: Cadrage T6 détail CPC | J19: ='T6 TB11'!C102 -> 0
A21: Ecart | E21: =E15-E18 -> 0 | F21: =F15-F18 -> 0 | J21: =J15-J19 -> 0

Sheet T12 B14-TVA
A1: Tableau n° 12 | E1: Etat B14
A4: DETAIL DE LA TAXE SUR LA VALEUR AJOUTEE
D6: =+'T7 CNCET B10-CB'!I4 -> Exercice clos le : | E6: ='T5 ESG'!$G$3 -> 31/12/2022
A7: NATURE | B7: solde au début | C7: Opérations | D7: Déclarations | E7: Solde fin d'exercice
B8: de l'exercice | C8: comptables | D8: T.V.A | E8: (1+2-3=4)
C9: de l'exercice | D9: de l'exercice
B10: 1 | C10: 2 | D10: 3 | F10: Ecart
A12: A. T.V.A. Facturée | B12: =SUMIF('Balance N-1 Retraitée'!A:A,"4455*",'Balance N-1 Retraitée'!H:H)-SUMIF('Balance N-1 Retraitée'!A:A,"4455*",'Balance N-1 Retraitée'!G:G) -> 0 | C12: =SUMIF('Balance N Retraitée'!A:A,"4455*",'Balance N Retraitée'!F:F) -> 76333.33 | D12: =SUMIF('Balance N Retraitée'!A:A,"4455*",'Balance N Retraitée'!E:E) -> 28334 | E12: =+B12+C12-D12 -> 47999.33 | F12: =SUMIF('Balance N Retraitée'!A:A,"4455*",'Balance N Retraitée'!H:H)-SUMIF('Balance N Retraitée'!A:A,"4455*",'Balance N Retraitée'!G:G)-E12 -> 0
A14: B. T.V.A. Récupérable | B14: =B16+B17 -> 0 | C14: =C16+C17 -> 46860.01 | D14: =D16+D17 -> 26059.29 | E14: =+B14+C14-D14 -> 20800.72 | F14: =SUMIF('Balance N Retraitée'!A:A,"3455*",'Balance N Retraitée'!G:G)-SUMIF('Balance N Retraitée'!A:A,"3455*",'Balance N Retraitée'!H:H)-E14 -> 0
A16: * sur charges | B16: =SUMIF('Balance N-1 Retraitée'!A:A,"34552*",'Balance N-1 Retraitée'!G:G)-SUMIF('Balance N-1 Retraitée'!A:A,"34552*",'Balance N-1 Retraitée'!H:H) -> 0 | C16: 42169.66 | D16: 22567.97 | E16: =+B16+C16-D16 -> 19601.69 | F16: =SUMIF('Balance N Retraitée'!A:A,"34552*",'Balance N Retraitée'!G:G)-SUMIF('Balance N Retraitée'!A:A,"34552*",'Balance N Retraitée'!H:H)-E16 -> -19601.69
A17: * sur immobilisations | B17: =SUMIF('Balance N-1 Retraitée'!A:A,"34551*",'Balance N-1 Retraitée'!G:G)-SUMIF('Balance N-1 Retraitée'!A:A,"34551*",'Balance N-1 Retraitée'!H:H) -> 0 | C17: 4690.35 | D17: 3491.32 | E17: =+B17+C17-D17 -> 1199.03 | F17: =SUMIF('Balance N Retraitée'!A:A,"34551*",'Balance N Retraitée'!G:G)-SUMIF('Balance N Retraitée'!A:A,"34551*",'Balance N Retraitée'!H:H)-E17 -> -1199.03
A21: C. T.V.A. due ou crédit de
A22: T.V.A = (A - B ) | B22: =+B12-B14 -> 0 | C22: =+C12-C14 -> 29473.32 | D22: =+D12-D14 -> 2274.71 | E22: =+E12-E14-E19 -> 27198.61
A27: Période | B27: TVA Facturée | C27: TVA Récupérable / Charges | D27: TVA Récupérable / Immobilisations
A28: Janvier
A29: Février
A30: Mars
A31: Avril
A32: Mai
A33: Juin
A34: Juillet
A35: Août
A36: Septembre
A37: Octobre
A38: Novembre
A39: Décembre
B40: =SUM(B28:B39) -> 0 | C40: =SUM(C28:C39) -> 0 | D40: =SUM(D28:D39) -> 0

Sheet T13 C1-rép cap
A1: Tableau n° 13 | J1: Etat C1
A3: ETAT DE REPARTITION DU CAPITAL SOCIAL
D4: Montant du capital DH | E4: 500000
H5: =+'T12 B14-TVA'!D6 -> Exercice clos le : | J5: ='T5 ESG'!$G$3 -> 31/12/2022
A7: Nom, prénom ou | E7: NOMBRE DE TITRES | G7: Valeur nominale | H7: MONTANT DU CAPITAL
A8: raison sociale | D8: Adresse | E8: Exercice | F8: Exercice | G8: de chaque | H8: Souscrit | I8: Appelé | J8: libéré
A9: des principaux | B9: N° IF | C9: N° CIN ou CE | E9: précédent | F9: actuel | G9: action ou part
A10: associés (1) | G10: sociale
A11: 1 | D11: 2 | E11: 3 | F11: 4 | G11: 5 | H11: 6 | I11: 7 | J11: 8
H13: =+F13*G13 -> 0 | I13: =+H13 -> 0 | J13: =+I13 -> 0
H14: =+F14*G14 -> 0 | I14: =+H14 -> 0 | J14: =+I14 -> 0
H15: =+F15*G15 -> 0 | I15: =+H15 -> 0 | J15: =+I15 -> 0
H16: =+F16*G16 -> 0 | I16: =+H16 -> 0 | J16: =+I16 -> 0
H17: =+F17*G17 -> 0 | I17: =+H17 -> 0 | J17: =+I17 -> 0
E18: =SUM(E12:E17) -> 0 | F18: =SUM(F12:F17) -> 0 | H18: =SUM(H12:H17) -> 0 | I18: =SUM(I12:I17) -> 0 | J18: =SUM(J12:J17) -> 0
A19: (1) Quand le nombre des associés est inférieur ou égal à 10, l'entreprise doit déclarer tous les participants au capital.
A20: Dans les autres cas il y a lieu de ne mentionner que les 10 principaux associés par ordre d'importance décroissante.
A23: Cadrage T1 Bilan | H23: ='T1 Bilan'!E68 -> 100000 | I23: ='T1 Bilan'!E68+'T1 Bilan'!E69 -> 100000
A25: Ecart | H25: =H18-H23 -> -100000 | I25: =I18-I23 -> -100000

Sheet T14 C2-affec resu
A1: Tableau n° 14 | D1: Etat C2
A4: TABLEAU D'AFFECTATION DES RESULTATS INTERVENUE AU COURS DE L'EXERCICE
D5: ETAT C2
C6: =+'T13 C1-rép cap'!H5 -> Exercice clos le : | D6: ='T5 ESG'!$G$3 -> 31/12/2022
B7: MONTANT | D7: MONTANT
A8: A. ORIGINE DES RESULTATS A AFFECTER | C8: B. AFFECTATION DES RESULTATS
A9: (Décision du AGO du …./…../……...)
C10: - Réserve légale
A11: - Report à nouveau | C11: - Autres réserves
A12: - Résultats nets en instance d'affectation | C12: - Tantièmes
A13: - Résultat net de l'exercice | C13: - Dividendes
A14: - Prélèvements sur les réserves | C14: - Autres affectations
A15: - Autres prélèvements | C15: - Report à nouveau
A18: TOTAL A | B18: =SUM(B11:B17) -> 0 | C18: TOTAL B | D18: =SUM(D10:D15) -> 0
D19: =D18-B18 -> 0
A20: TOTAL A = TOTAL B

Sheet T15 Encourag
A1: Tableau n°15
B2: ETAT POUR LE CALCUL DE L'IMPOT DU PAR LES ENTREPRISES BENEFICIANTS DES
B3: MESURES D'ENCOURAGEMENTS AUX INVESTISSEMENTS
B4: RUBRIQUES | C4: Ensemble des produits | D4: Ensemble des produits | E4: Ensemble des produits
D5: correspondant | E5: correspondant
D6: à la base imposable | E6: au numérateur taxable
B7: 1 | C7: 2 | D7: 3 | E7: 4
B8: * Ventes
A9: 1 | B9: * Ventes imposables
A10: 2 | B10: * Ventes exonérées à 100%
A11: 3 | B11: * Ventes exonérées à 50%
B12: Lotissement et promotion immobilière
A13: 4 | B13: * Ventes et locations imposables
A14: 5 | B14: * Ventes et locations exclus à 100%
A15: 6 | B15: * Ventes et locations exclus à 50%
B17: Prestations de services
A18: 7 | B18: Imposables
A19: 8 | B19: Exonérées à 100%
A20: 9 | B20: Exonérées à 50%
A21: 10 | B21: Produits accessoires. Produits financiers, dons et libéralités
A22: 11 | B22: Subventions d'équipement
A23: 12 | B23: Subventions d'équilibre
A24: 12a | B24: Imposables
A25: 12b | B25: Exonérées à 100%
A26: 12e | B26: Exonérées à 50%
A27: 13 | B27: Totaux partiels
A28: 14 | B28: Profits net global des cessions après abattement pondéré
A29: 15 | B29: Autres profils exceptionnels
A30: 16 | B30: Total général (lignes 13+ 14+ 15 ) | C30: =C27+C28+C29 -> 0 | D30: =D27+D28+D29 -> 0 | E30: =E27+E28+E29 -> 0
B32: (1) Faire figurer dans ces cases la moitié du montant figuant dans la colonne 3 - même ligne
B33: (2) Faire figurer dans ces cases la moitié du montant figuant dans la colonne 2 - même ligne
B34: Eléments de calcul de l'impôt :
B35: Base cotisation minimale : montant (ligne 13, col, 3)
B36: Cotisation minimale nette : cotisation brute x | C36: montant (ligne 13, col. 4)
C37: Base cotisation minimale
B38: Base imposable à l'I.S. : bénéfice fiscal x | C38: montant (ligne 16, col. 3)
C39: montant (ligne 16 col. 2)
B40: Impôt sur les société dû : impôt brut | C40: montant (ligne 16, col. 4)
C41: montant (ligne 16, col. 3)
C43: Total

Sheet T16 Amort
A2: Tableau n° 16
A4: ETAT DE DOTATIONS AUX AMORTISSEMENTS RELATIFS AUX IMMOBILISATIONS
E7: Montant Global | G7: =Cellule_1093 -> 356372.02
E8: Exercice clos le : | G8: =+'T14 C2-affec resu'!D6 -> 31/12/2022
E9: Amortissement de l'exercide du | G9: =Couverture!C15 -> 44562
E10: Amortissement de l'exercide au | G10: =Couverture!E15 -> 31/12/2022
A12: Immobilisation concernée | B12: Date d'entrée (1) | C12: Valeur à amortir (Prix d'acquisition (2)) | D12: Valeur à amortir (Valeur comptable après réévaluation) | E12: Amortissements antérieurs (3) | F12: Taux | G12: Durée (4) | H12: Amortissements normaux ou accélérés de l'exercice | I12: Total des amortissements à la fin de l'exercice (col. 4 + col. 7) | J12: Observations (5)
B13: 1 | C13: 2 | D13: 3 | E13: 4 | F13: 5 | G13: 6 | H13: 7 | I13: 8 | J13: 9
A14: FRAIS DECONSTITUTION | B14: 42653 | C14: 5000 | E14: 694.37 | F14: 0.3333 | G14: 3 | H14: =+C14*F14 -> 1666.5 | I14: =+E14+H14 -> 2360.87
A15: MAT ET OULILLAGE | B15: 42814 | C15: 5500 | E15: 825 | F15: 0.2 | G15: 5 | H15: =+C15*F15 -> 1100 | I15: =+H15 -> 1100
A16: MAT ET OULILLAGE | B16: 42831 | C16: 2400 | E16: 360 | F16: 0.2 | G16: 5 | H16: =+C16*F16 -> 480 | I16: =+E16+H16 -> 840
A17: MAT ET OULILLAGE | B17: 43089 | C17: 1800 | E17: 30 | F17: 0.2 | G17: 5 | H17: =+C17*F17 -> 360 | I17: =+H17 -> 360
A18: MAT DE TRANSPORST | B18: 42781 | C18: 109038 | E18: 18173 | F18: 0.2 | G18: 5 | H18: =+C18*F18 -> 21807.6 | I18: =+H18 -> 21807.6
A19: MAT DE TRANSPORST | B19: 42788 | C19: 116275 | E19: 19379.17 | F19: 0.2 | G19: 5 | H19: =+C19*F19 -> 23255 | I19: =+H19 -> 23255
A20: MAT DE TRANSPORST | B20: 42781 | C20: 116275 | E20: 19379.17 | F20: 0.2 | G20: 5 | H20: =+C20*F20 -> 23255 | I20: =+H20 -> 23255
A21: MAT DE TRANSPORST | B21: 42790 | C21: 109038 | E21: 18173 | F21: 0.2 | G21: 5 | H21: =+C21*F21 -> 21807.6 | I21: =+H21 -> 21807.6
A22: MAT DE TRANSPORST | B22: 42793 | C22: 116855 | E22: 19475.83 | F22: 0.2 | G22: 5 | H22: =+C22*F22 -> 23371 | I22: =+H22 -> 23371
A23: MAT DE TRANSPORST | B23: 42914 | C23: 124418 | E23: 12441.8 | F23: 0.2 | G23: 5 | H23: =+C23*F23 -> 24883.6 | I23: =+H23 -> 24883.6
A24: MAT DE TRANSPORST | B24: 42922 | C24: 97800 | E24: 11410 | F24: 0.2 | G24: 5 | H24: =+C24*F24 -> 19560 | I24: =+Cellule_1084_1 -> 19560
A25: MAT DE TRANSPORST | B25: 42922 | C25: 112900 | E25: 13171.67 | F25: 0.2 | G25: 5 | H25: =+C25*F25 -> 22580 | I25: =+Cellule_1084_2 -> 22580
A26: MAT DE TRANSPORST | B26: 42988 | C26: 186214.17 | E26: 27932.13 | F26: 0.2 | G26: 5 | H26: =+C26*F26 -> 37242.834 | I26: =+H26 -> 37242.834
A27: MAT DE TRANSPORST | B27: 43039 | C27: 97164 | E27: 3238.8 | F27: 0.2 | G27: 5 | H27: =+C27*F27 -> 19432.8 | I27: =+H27 -> 19432.8
A28: MAT DE TRANSPORST | B28: 43039 | C28: 97104 | E28: 3236.8 | F28: 0.2 | G28: 5 | H28: =+C28*F28 -> 19420.8 | I28: =+H28 -> 19420.8
A29: MAT DE TRANSPORST | B29: 43054 | C29: 90300 | E29: 2257.5 | F29: 0.2 | G29: 5 | H29: =+C29*F29 -> 18060 | I29: =+H29 -> 18060
A30: MAT DE TRANSPORST | B30: 43063 | C30: 101604.17 | E30: 1693.4 | F30: 0.2 | G30: 5 | H30: =+C30*F30 -> 20320.834 | I30: =+H30 -> 20320.834
A31: MAT DE TRANSPORST | B31: 31/112/17 | C31: 103842.24 | E31: 0 | F31: 0.2 | G31: 5 | H31: =+Cellule_1079_8*Cellule_1082_8 -> 20768.448 | I31: =+Cellule_1081_8+Cellule_1084_8 -> 20768.448
A32: MAT DE TRANSPORST | B32: 43106 | C32: 92500 | F32: 0.2 | G32: 5 | H32: =+Cellule_1079_9*Cellule_1082_9 -> 18500 | I32: =+Cellule_1081_9+Cellule_1084_9 -> 18500
A33: MATDE TRANSPORT | B33: 43106 | C33: 92500 | F33: 0.2 | G33: 5 | H33: =+Cellule_1079_10*Cellule_1082_10 -> 18500 | I33: =+Cellule_1081_10+Cellule_1084_10 -> 18500
B37: Totaux | C37: =SUM(C14:C35) -> 1778527.6 | D37: =SUM(D14:D35) -> 0 | E37: =SUM(E14:E35) -> 171871.64 | H37: =SUM(H14:H35) -> 356372.02 | I37: =SUM(I14:I35) -> 357426.39
B39: T4+T8 | C39: ='T4 B2-immo'!I9+'T4 B2-immo'!I14+'T4 B2-immo'!I20 -> 1593527.6 | E39: ='T8 B2 BIS'!B9+'T8 B2 BIS'!B16+'T8 B2 BIS'!B23 -> 694.37 | H39: ='T8 B2 BIS'!C9+'T8 B2 BIS'!C16+'T8 B2 BIS'!C23 -> 172843.76 | I39: ='T8 B2 BIS'!E9+'T8 B2 BIS'!E16+'T8 B2 BIS'!E23 -> 173538.13
B41: Ecart | C41: =C37-C39 -> 185000 | E41: =E37-E39 -> 171177.27 | H41: =H37-H39 -> 183528.26 | I41: =I37-I39 -> 183888.26

Sheet T17 + V Fusions
A1: Tableau n°17
B4: ETAT DES PLUS-VALUES CONSTATEES EN CAS DE FUSIONS
H6: Exercice clos le | J6: ='T16 Amort'!G8 -> 31/12/2022
B8: Eléments | C8: Valeur d'apport | D8: Valeur nette comptable | E8: Plus-value constatée et différée | F8: Fraction de la plus-value rapportée aux l' exercices antérieurs (cumul) (2) | G8: Fraction de la plus-value rapportée à l' exercices actuel | H8: Cumul des plus-values rapportées | I8: Solde des plus-values non imputées | J8: Observations
A9: 1 | B9: Terrains (1)
A10: 2 | B10: Constructions
A11: 3 | B11: Matériel et outillage
A12: 4 | B12: Matériel de transport
A13: 5 | B13: Agencements-installations
A14: 6 | B14: Brevets
A15: 7 | B15: Autres éléments amortissables
A16: 8 | B16: Titres de participation
A17: 9 | B17: Fonds de commerce
A18: 10 | B18: Autres éléments non amortissables
B19: TOTAL | C19: =SUM(C9:C18) -> 0 | D19: =SUM(D9:D18) -> 0 | E19: =SUM(E9:E18) -> 0 | F19: =SUM(F9:F18) -> 0 | G19: =SUM(G9:G18) -> 0 | H19: =SUM(H9:H18) -> 0 | I19: =SUM(I9:I18) -> 0
A20: (1) | B20: Imposition différée jusqu'à la date de cession
A21: (2) | B21: Fraction correspondant à l'imputation de la plus-value constatée lors de la fusion majorée le cas échéant du reliquat de la plus-value se rapportant à l'élément cédé au cours de l'exercice.

Sheet T18 Emprunts
A1: Tableau n° 18
A4: ETAT DES INTERETS DES EMPRUNTS CONTRACTES AUPRES DES ASSOCIES ET
A5: DES TIERS AUTRES QUE LES ORGANISMES DE BANQUE OU DE CREDIT
J7: ='T14 C2-affec resu'!C6 -> Exercice clos le : | L7: ='T5 ESG'!$G$3 -> 31/12/2022
A8: Noms prénoms | B8: Adresse | C8: N° C.I.N | D8: Montant | E8: Date du | F8: Durée | G8: Taux | H8: Charge | I8: Remboursement | K8: Remboursement
A9: ou raison | C9: ou | D9: du prêt | E9: prêt | F9: du prêt | G9: d'interêts | H9: financière | I9: Exercices | K9: Exercice Actuel | M9: Observations
A10: sociale | C10: Article I.S | F10: (en mois) | H10: globale | I10: antérieurs
I11: Principal | J11: Intérêts | K11: Principal | L11: Intérêts
A13: A. Associés
A18: B. Tiers
A23: TOTAL | D23: =SUM(D13:D21) -> 0 | H23: =SUM(H13:H21) -> 0 | I23: =SUM(I13:I21) -> 0 | J23: =SUM(J13:J21) -> 0 | K23: =SUM(K13:K21) -> 0 | L23: =SUM(L13:L21) -> 0

Sheet T19 Locations
A1: Tableau n° 19
C4: TABLEAU DES LOCATIONS ET BAUX AUTRES QUE LE CREDIT-BAIL
G6: ='T18 Emprunts'!J7 -> Exercice clos le : | I6: ='T5 ESG'!$G$3 -> 31/12/2022
H7: Nature du contrat (1)
B8: Nature du | C8: Lieu de | D8: Noms et prénoms ou Raison sociale et | E8: Date de conclusion | F8: Montant annuel de | G8: Montant du loyer
B9: bien loué | C9: situation | D9: adresse du propriétaire | E9: de l'acte de | F9: location | G9: compris dans les | H9: Bail-ordinaire | I9: (Néme période)
E10: location | G10: charges de l'exercice
B11: 1 | C11: 2 | D11: 3 | E11: 4 | F11: 5 | G11: 6 | H11: 7 | I11: 8
B12: dfdfd | C12: ffsfsfs | D12: sfsfsffsfs | E12: 42594 | F12: 12000 | G12: 12000 | H12: Bail-ordinaire
B13: fdfdfdfd de location | C13: fsfsff | D13: ssfsfsfs
D14: CINN°PB4536
C18: TOTAL | F18: =SUM(F12:F17) -> 12000 | G18: =SUM(G12:G17) -> 12000
B19: (1) Marquer d'une croix la colonne adéquate
B20: Au cas où le nombre de propriétaires dépasserait quinze, veuillez ajouter des annexes d'une contexture identique à celle du présent état.
A23: Cadrage T6 détail CPC | G23: ='T6 TB11'!C23 -> 12000
A25: Ecart | G25: =G18-G23 -> 0

Sheet T20 Stocks
A1: Tableau n° 20
A2: ETAT DETAILLE DES STOCKS
F3: ='T18 Emprunts'!J7 -> Exercice clos le : | H3: ='T5 ESG'!$G$3 -> 31/12/2022
B4: STOCK FINAL | E4: STOCK INITIAL | H4: Variation de
A5: STOCKS | C5: Provision | F5: Provision | H5: Stock en
B6: Montant Brut | C6: pour | D6: Montant Net | E6: Montant Brut | F6: pour | G6: Montant Net | H6: valeur (+ ou - )
C7: dépréciation | F7: dépréciation | H7: 7 = 6 - 3
A8: I. Stocks Approvisionnement | D8: =B8-C8 -> 0 | G8: =E8-F8 -> 0 | H8: =+G8-D8 -> 0
A9: 1 - Biens et produits destinés à la revente en l'état : | D9: =+B9-C9 -> 0 | G9: =E9-F9 -> 0 | H9: =+G9-D9 -> 0
A10: * Biens immeubles ; | D10: =+B10-C10 -> 0 | G10: =E10-F10 -> 0 | H10: =+G10-D10 -> 0 | I10: 1
A11: * Biens meubles. | B11: =SUMIF('Balance N Retraitée'!$A:$A,"311*",'Balance N Retraitée'!$G:$G)-SUMIF('Balance N Retraitée'!$A:$A,"311*",'Balance N Retraitée'!$H:$H) -> 0 | C11: =SUMIF('Balance N Retraitée'!$A:$A,"3911*",'Balance N Retraitée'!$H:$H)-SUMIF('Balance N Retraitée'!$A:$A,"3911*",'Balance N Retraitée'!$G:$G) -> 0 | D11: =+B11-C11 -> 0 | E11: =SUMIF('Balance N-1 Retraitée'!$A:$A,"311*",'Balance N-1 Retraitée'!$G:$G)-SUMIF('Balance N-1 Retraitée'!$A:$A,"311*",'Balance N-1 Retraitée'!$H:$H) -> 0 | F11: =SUMIF('Balance N-1 Retraitée'!$A:$A,"3911*",'Balance N-1 Retraitée'!$H:$H)-SUMIF('Balance N-1 Retraitée'!$A:$A,"3911*",'Balance N-1 Retraitée'!$G:$G) -> 0 | G11: =E11-F11 -> 0 | H11: =+G11-D11 -> 0 | I11: 2
A12: 2 - Biens et Matières Premières destinés aux activités de production et de transformation : | B12: =SUMIF('Balance N Retraitée'!$A:$A,"3121*",'Balance N Retraitée'!$G:$G)-SUMIF('Balance N Retraitée'!$A:$A,"3121*",'Balance N Retraitée'!$H:$H) -> 0 | C12: =SUMIF('Balance N Retraitée'!$A:$A,"39121*",'Balance N Retraitée'!$H:$H)-SUMIF('Balance N Retraitée'!$A:$A,"39121*",'Balance N Retraitée'!$G:$G) -> 0 | D12: =+B12-C12 -> 0 | E12: =SUMIF('Balance N-1 Retraitée'!$A:$A,"3121*",'Balance N-1 Retraitée'!$G:$G)-SUMIF('Balance N-1 Retraitée'!$A:$A,"3121*",'Balance N-1 Retraitée'!$H:$H) -> 0 | F12: =SUMIF('Balance N-1 Retraitée'!$A:$A,"39121*",'Balance N-1 Retraitée'!$H:$H)-SUMIF('Balance N-1 Retraitée'!$A:$A,"39121*",'Balance N-1 Retraitée'!$G:$G) -> 0 | G12: =E12-F12 -> 0 | H12: =+G12-D12 -> 0 | I12: 3
D13: =+B13-C13 -> 0
A14: 3 - Matières Premières
A15: 4 - Matières consommables | B15: =SUMIF('Balance N Retraitée'!$A:$A,"31221*",'Balance N Retraitée'!$G:$G)-SUMIF('Balance N Retraitée'!$A:$A,"31221*",'Balance N Retraitée'!$H:$H) -> 0 | C15: =SUMIF('Balance N Retraitée'!$A:$A,"391221*",'Balance N Retraitée'!$H:$H)-SUMIF('Balance N Retraitée'!$A:$A,"391221*",'Balance N Retraitée'!$G:$G) -> 0 | D15: =+B15-C15 -> 0 | E15: =SUMIF('Balance N-1 Retraitée'!$A:$A,"31221*",'Balance N-1 Retraitée'!$G:$G)-SUMIF('Balance N-1 Retraitée'!$A:$A,"31221*",'Balance N-1 Retraitée'!$H:$H) -> 0 | F15: =SUMIF('Balance N-1 Retraitée'!$A:$A,"391221*",'Balance N-1 Retraitée'!$H:$H)-SUMIF('Balance N-1 Retraitée'!$A:$A,"391221*",'Balance N-1 Retraitée'!$G:$G) -> 0 | G15: =E15-F15 -> 0 | H15: =+G15-D15 -> 0 | I15: 4
A16: 5 - Pièces détachées | B16: =SUMIF('Balance N Retraitée'!$A:$A,"31225*",'Balance N Retraitée'!$G:$G)-SUMIF('Balance N Retraitée'!$A:$A,"31225*",'Balance N Retraitée'!$H:$H) -> 0 | C16: =SUMIF('Balance N Retraitée'!$A:$A,"391225*",'Balance N Retraitée'!$H:$H)-SUMIF('Balance N Retraitée'!$A:$A,"391225*",'Balance N Retraitée'!$G:$G) -> 0 | D16: =+B16-C16 -> 0 | E16: =SUMIF('Balance N-1 Retraitée'!$A:$A,"31225*",'Balance N-1 Retraitée'!$G:$G)-SUMIF('Balance N-1 Retraitée'!$A:$A,"31225*",'Balance N-1 Retraitée'!$H:$H) -> 0 | F16: =SUMIF('Balance N-1 Retraitée'!$A:$A,"391225*",'Balance N-1 Retraitée'!$H:$H)-SUMIF('Balance N-1 Retraitée'!$A:$A,"391225*",'Balance N-1 Retraitée'!$G:$G) -> 0 | G16: =E16-F16 -> 0 | H16: =+G16-D16 -> 0 | I16: 5
A17: 6 - Carburants, lubrifiants pour véhicules de transport | D17: =+B17-C17 -> 0 | G17: =E17-F17 -> 0 | H17: =+G17-D17 -> 0 | I17: 6
A18: - Emballages | D18: =+B18-C18 -> 0 | G18: =E18-F18 -> 0 | H18: =+G18-D18 -> 0
A19: 7 * récupérables | B19: =SUMIF('Balance N Retraitée'!$A:$A,"31232*",'Balance N Retraitée'!$G:$G)-SUMIF('Balance N Retraitée'!$A:$A,"31232*",'Balance N Retraitée'!$H:$H) -> 0 | C19: =SUMIF('Balance N Retraitée'!$A:$A,"391232*",'Balance N Retraitée'!$H:$H)-SUMIF('Balance N Retraitée'!$A:$A,"391232*",'Balance N Retraitée'!$G:$G) -> 0 | D19: =+B19-C19 -> 0 | E19: =SUMIF('Balance N-1 Retraitée'!$A:$A,"31232*",'Balance N-1 Retraitée'!$G:$G)-SUMIF('Balance N-1 Retraitée'!$A:$A,"31232*",'Balance N-1 Retraitée'!$H:$H) -> 0 | F19: =SUMIF('Balance N-1 Retraitée'!$A:$A,"391232*",'Balance N-1 Retraitée'!$H:$H)-SUMIF('Balance N-1 Retraitée'!$A:$A,"391232*",'Balance N-1 Retraitée'!$G:$G) -> 0 | G19: =E19-F19 -> 0 | H19: =+G19-D19 -> 0 | I19: 7
A20: 8 * vendus | D20: =+B20-C20 -> 0 | G20: =E20-F20 -> 0 | H20: =+G20-D20 -> 0 | I20: 8
A21: 9 * perdus | B21: =SUMIF('Balance N Retraitée'!$A:$A,"31231*",'Balance N Retraitée'!$G:$G)-SUMIF('Balance N Retraitée'!$A:$A,"31231*",'Balance N Retraitée'!$H:$H) -> 0 | C21: =SUMIF('Balance N Retraitée'!$A:$A,"3912391*",'Balance N Retraitée'!$H:$H)-SUMIF('Balance N Retraitée'!$A:$A,"3912391*",'Balance N Retraitée'!$G:$G) -> 0 | D21: =+B21-C21 -> 0 | E21: =SUMIF('Balance N-1 Retraitée'!$A:$A,"31231*",'Balance N-1 Retraitée'!$G:$G)-SUMIF('Balance N-1 Retraitée'!$A:$A,"31231*",'Balance N-1 Retraitée'!$H:$H) -> 0 | F21: =SUMIF('Balance N-1 Retraitée'!$A:$A,"3912391*",'Balance N-1 Retraitée'!$H:$H)-SUMIF('Balance N-1 Retraitée'!$A:$A,"3912391*",'Balance N-1 Retraitée'!$G:$G) -> 0 | G21: =E21-F21 -> 0 | H21: =+G21-D21 -> 0 | I21: 9
A22: 10- Total Stocks des approvisionnements | B22: =SUM(B8:B21) -> 0 | C22: =SUM(C8:C21) -> 0 | D22: =SUM(D8:D21) -> 0 | E22: =SUM(E8:E21) -> 0 | F22: =SUM(F8:F21) -> 0 | G22: =SUM(G8:G21) -> 0 | H22: =+G22-D22 -> 0 | I22: 10
A23: II. Stock en cours Production de biens et services
A24: 11- Produits en cours | B24: =SUMIF('Balance N Retraitée'!$A:$A,"3131*",'Balance N Retraitée'!$G:$G)-SUMIF('Balance N Retraitée'!$A:$A,"3131*",'Balance N Retraitée'!$H:$H) -> 0 | C24: =SUMIF('Balance N Retraitée'!$A:$A,"391391*",'Balance N Retraitée'!$H:$H)-SUMIF('Balance N Retraitée'!$A:$A,"391391*",'Balance N Retraitée'!$G:$G) -> 0 | D24: =B24-C24 -> 0 | E24: =SUMIF('Balance N-1 Retraitée'!$A:$A,"3131*",'Balance N-1 Retraitée'!$G:$G)-SUMIF('Balance N-1 Retraitée'!$A:$A,"3131*",'Balance N-1 Retraitée'!$H:$H) -> 0 | F24: =SUMIF('Balance N-1 Retraitée'!$A:$A,"391391*",'Balance N-1 Retraitée'!$H:$H)-SUMIF('Balance N-1 Retraitée'!$A:$A,"391391*",'Balance N-1 Retraitée'!$G:$G) -> 0 | G24: =E24-F24 -> 0 | H24: =+G24-D24 -> 0 | I24: 11
A25: 12- Etudes en cours | B25: =SUMIF('Balance N Retraitée'!$A:$A,"31342*",'Balance N Retraitée'!$G:$G)-SUMIF('Balance N Retraitée'!$A:$A,"31342*",'Balance N Retraitée'!$H:$H) -> 0 | C25: =SUMIF('Balance N Retraitée'!$A:$A,"391342*",'Balance N Retraitée'!$H:$H)-SUMIF('Balance N Retraitée'!$A:$A,"391342*",'Balance N Retraitée'!$G:$G) -> 0 | D25: =B25-C25 -> 0 | E25: =SUMIF('Balance N-1 Retraitée'!$A:$A,"31342*",'Balance N-1 Retraitée'!$G:$G)-SUMIF('Balance N-1 Retraitée'!$A:$A,"31342*",'Balance N-1 Retraitée'!$H:$H) -> 0 | F25: =SUMIF('Balance N-1 Retraitée'!$A:$A,"391342*",'Balance N-1 Retraitée'!$H:$H)-SUMIF('Balance N-1 Retraitée'!$A:$A,"391342*",'Balance N-1 Retraitée'!$G:$G) -> 0 | G25: =E25-F25 -> 0 | H25: =+G25-D25 -> 0 | I25: 12
A26: 13 - Travaux en cours | B26: =SUMIF('Balance N Retraitée'!$A:$A,"31341*",'Balance N Retraitée'!$G:$G)-SUMIF('Balance N Retraitée'!$A:$A,"31341*",'Balance N Retraitée'!$H:$H) -> 0 | C26: =SUMIF('Balance N Retraitée'!$A:$A,"391341*",'Balance N Retraitée'!$H:$H)-SUMIF('Balance N Retraitée'!$A:$A,"391341*",'Balance N Retraitée'!$G:$G) -> 0 | D26: =B26-C26 -> 0 | E26: =SUMIF('Balance N-1 Retraitée'!$A:$A,"31341*",'Balance N-1 Retraitée'!$G:$G)-SUMIF('Balance N-1 Retraitée'!$A:$A,"31341*",'Balance N-1 Retraitée'!$H:$H) -> 0 | F26: =SUMIF('Balance N-1 Retraitée'!$A:$A,"391341*",'Balance N-1 Retraitée'!$H:$H)-SUMIF('Balance N-1 Retraitée'!$A:$A,"391341*",'Balance N-1 Retraitée'!$G:$G) -> 0 | G26: =E26-F26 -> 0 | H26: =+G26-D26 -> 0 | I26: 13
A27: 14 - Services en cours | B27: =SUMIF('Balance N Retraitée'!$A:$A,"31343*",'Balance N Retraitée'!$G:$G)-SUMIF('Balance N Retraitée'!$A:$A,"31343*",'Balance N Retraitée'!$H:$H) -> 0 | C27: =SUMIF('Balance N Retraitée'!$A:$A,"391343*",'Balance N Retraitée'!$H:$H)-SUMIF('Balance N Retraitée'!$A:$A,"391343*",'Balance N Retraitée'!$G:$G) -> 0 | D27: =B27-C27 -> 0 | E27: =SUMIF('Balance N-1 Retraitée'!$A:$A,"31343*",'Balance N-1 Retraitée'!$G:$G)-SUMIF('Balance N-1 Retraitée'!$A:$A,"31343*",'Balance N-1 Retraitée'!$H:$H) -> 0 | F27: =SUMIF('Balance N-1 Retraitée'!$A:$A,"391343*",'Balance N-1 Retraitée'!$H:$H)-SUMIF('Balance N-1 Retraitée'!$A:$A,"391343*",'Balance N-1 Retraitée'!$G:$G) -> 0 | G27: =E27-F27 -> 0 | H27: =+G27-D27 -> 0 | I27: 14
A28: 15- Total Stocks des encours | B28: =SUM(B24:B27) -> 0 | C28: =SUM(C24:C27) -> 0 | D28: =SUM(D24:D27) -> 0 | E28: =SUM(E24:E27) -> 0 | F28: =SUM(F24:F27) -> 0 | G28: =SUM(G24:G27) -> 0 | H28: =+G28-D28 -> 0 | I28: 15
A29: III. Stock Produits finis | H29: =+G29-D29 -> 0
A30: 16 - Produits finis | B30: =SUMIF('Balance N Retraitée'!$A:$A,"315*",'Balance N Retraitée'!$G:$G)-SUMIF('Balance N Retraitée'!$A:$A,"315*",'Balance N Retraitée'!$H:$H) -> 0 | C30: =SUMIF('Balance N Retraitée'!$A:$A,"3915*",'Balance N Retraitée'!$H:$H)-SUMIF('Balance N Retraitée'!$A:$A,"3915*",'Balance N Retraitée'!$G:$G) -> 0 | D30: =B30-C30 -> 0 | E30: =SUMIF('Balance N-1 Retraitée'!$A:$A,"315*",'Balance N-1 Retraitée'!$G:$G)-SUMIF('Balance N-1 Retraitée'!$A:$A,"315*",'Balance N-1 Retraitée'!$H:$H) -> 0 | F30: =SUMIF('Balance N-1 Retraitée'!$A:$A,"3915*",'Balance N-1 Retraitée'!$H:$H)-SUMIF('Balance N-1 Retraitée'!$A:$A,"3915*",'Balance N-1 Retraitée'!$G:$G) -> 0 | G30: =E30-F30 -> 0 | H30: =+G30-D30 -> 0 | I30: 16
A31: 17 - Biens finis | D31: =B31-C31 -> 0 | G31: =E31-F31 -> 0 | H31: =+G31-D31 -> 0 | I31: 17
A32: 18- Total Stocks Produits et Biens Finis | B32: =SUM(B30:B31) -> 0 | C32: =SUM(C30:C31) -> 0 | D32: =SUM(D30:D31) -> 0 | E32: =SUM(E30:E31) -> 0 | F32: =SUM(F30:F31) -> 0 | G32: =SUM(G30:G31) -> 0 | H32: =+G32-D32 -> 0 | I32: 18
A33: IV. Stock Produits résiduels | H33: =+G33-D33 -> 0
A34: 19 - Déchets | B34: =SUMIF('Balance N Retraitée'!$A:$A,"31451*",'Balance N Retraitée'!$G:$G)-SUMIF('Balance N Retraitée'!$A:$A,"31451*",'Balance N Retraitée'!$H:$H) -> 0 | C34: =SUMIF('Balance N Retraitée'!$A:$A,"391451*",'Balance N Retraitée'!$H:$H)-SUMIF('Balance N Retraitée'!$A:$A,"391451*",'Balance N Retraitée'!$G:$G) -> 0 | D34: =B34-C34 -> 0 | E34: =SUMIF('Balance N-1 Retraitée'!$A:$A,"31451*",'Balance N-1 Retraitée'!$G:$G)-SUMIF('Balance N-1 Retraitée'!$A:$A,"31451*",'Balance N-1 Retraitée'!$H:$H) -> 0 | F34: =SUMIF('Balance N-1 Retraitée'!$A:$A,"391451*",'Balance N-1 Retraitée'!$H:$H)-SUMIF('Balance N-1 Retraitée'!$A:$A,"391451*",'Balance N-1 Retraitée'!$G:$G) -> 0 | G34: =E34-F34 -> 0 | H34: =+G34-D34 -> 0 | I34: 19
A35: 20 - Rebuts | B35: =SUMIF('Balance N Retraitée'!$A:$A,"31452*",'Balance N Retraitée'!$G:$G)-SUMIF('Balance N Retraitée'!$A:$A,"31452*",'Balance N Retraitée'!$H:$H) -> 0 | C35: =SUMIF('Balance N Retraitée'!$A:$A,"391452*",'Balance N Retraitée'!$H:$H)-SUMIF('Balance N Retraitée'!$A:$A,"391452*",'Balance N Retraitée'!$G:$G) -> 0 | D35: =B35-C35 -> 0 | E35: =SUMIF('Balance N-1 Retraitée'!$A:$A,"31452*",'Balance N-1 Retraitée'!$G:$G)-SUMIF('Balance N-1 Retraitée'!$A:$A,"31452*",'Balance N-1 Retraitée'!$H:$H) -> 0 | F35: =SUMIF('Balance N-1 Retraitée'!$A:$A,"391452*",'Balance N-1 Retraitée'!$H:$H)-SUMIF('Balance N-1 Retraitée'!$A:$A,"391452*",'Balance N-1 Retraitée'!$G:$G) -> 0 | G35: =E35-F35 -> 0 | H35: =+G35-D35 -> 0 | I35: 20
A36: 21 - Matières de récupération | B36: =SUMIF('Balance N Retraitée'!$A:$A,"31453*",'Balance N Retraitée'!$G:$G)-SUMIF('Balance N Retraitée'!$A:$A,"31453*",'Balance N Retraitée'!$H:$H) -> 0 | C36: =SUMIF('Balance N Retraitée'!$A:$A,"391453*",'Balance N Retraitée'!$H:$H)-SUMIF('Balance N Retraitée'!$A:$A,"391453*",'Balance N Retraitée'!$G:$G) -> 0 | D36: =B36-C36 -> 0 | E36: =SUMIF('Balance N-1 Retraitée'!$A:$A,"31453*",'Balance N-1 Retraitée'!$G:$G)-SUMIF('Balance N-1 Retraitée'!$A:$A,"31453*",'Balance N-1 Retraitée'!$H:$H) -> 0 | F36: =SUMIF('Balance N-1 Retraitée'!$A:$A,"391453*",'Balance N-1 Retraitée'!$H:$H)-SUMIF('Balance N-1 Retraitée'!$A:$A,"391453*",'Balance N-1 Retraitée'!$G:$G) -> 0 | G36: =E36-F36 -> 0 | H36: =+G36-D36 -> 0 | I36: 21
A37: 22 - Total Stocks Produits Résiduels | B37: =SUM(B34:B36) -> 0 | C37: =SUM(C34:C36) -> 0 | D37: =SUM(D34:D36) -> 0 | E37: =SUM(E34:E36) -> 0 | F37: =SUM(F34:F36) -> 0 | G37: =SUM(G34:G36) -> 0 | H37: =+G37-D37 -> 0 | I37: 22
A38: 23- TOTAL GENERAL | B38: =B22+B28+B32+B37 -> 0 | C38: =C22+C28+C392+C37 -> 0 | D38: =D22+D28+D32+D37 -> 0 | E38: =E22+E28+E32+E37 -> 0 | F38: =F22+F28+F392+F37 -> 0 | G38: =G22+G28+G32+G37 -> 0 | H38: =+G38-D38 -> 0 | I38: 23
A39: (ligne 10 + 15 + 18 + 22) | H39: =+G39-D39 -> 0
A42: Cadrage T1 Bilan | B42: ='T1 Bilan'!C35 -> 0 | C42: ='T1 Bilan'!D35 -> 0 | D42: ='T1 Bilan'!E35 -> 0 | G42: ='T1 Bilan'!G35 -> 0
A44: Ecart | B44: =B38-B42 -> 0 | C44: =C38-C42 -> 0 | D44: =D38-D42 -> 0 | G44: =G38-G42 -> 0

Sheet ETIC  A0 A1
B5: =' A2 '!C7 -> 31/12/2022
B6: A.0 . Présentation de la société
B8: 1.1 Présentation :
B28: A.1. Principales méthodes d'évaluation spécifiques à l'entreprise
B30: A.1.1 Immobilisations en non valeurs :
B39: A.1.2 Immobilisations incorporelles :
B48: A.1.3 Immobilisations corporelles :
B60: A.1.4 Immobilisations financières :
B66: A.1.5 Stocks :
B78: A.1.6 Créances clients :
B86: A.1.7 Les créances et dettes libellées en monnaie étrangère:
B93: A.1.8 Engagements de retraite

Sheet  A2 
A5: Etat A 2 : Etat des dérogations
B7: Exercice clos le | C7: ='T20 Stocks'!H3 -> 31/12/2022
A8: Indication des | B8: Justification des | C8: Influence des dérogations sur
A9: Dérogations | B9: Dérogations | C9: le patrimoine , la situation
C10: financière et les résultats
A11: I. Dérogations aux Principes comptables fondamentaux
A26: II.Dérogations aux Méthodes
A27: d'évaluation
A33: III. Dérogations aux Règles
A34: d'établissement et de Présentation
A35: des états de synthèse

Sheet A3
B4: Etat A 3 : Etat des changements de méthodes
C6: Exercice clos le | D6: =' A2 '!C7 -> 31/12/2022
B7: Nature des | C7: Justification des | D7: Influence sur le patrimoine , la
B8: Changements | C8: Changements | D8: situation financière et les résultats
B9: Changements affectant les
B10: Méthodes d'évaluation
B21: Changements affectant les
B22: Règles de présentation

Sheet B1-Tab non val
D3: ETAT B1
C4: DETAIL DES NON-VALEURS
C5: Exercice clos le | D5: ='T5 ESG'!$G$3 -> 31/12/2022
B6: COMPTE | C6: INTITULE | D6: MONTANT
B7: PRINCIPAL
B9: 2111 | C9: FRAIS DE CONSTRUCTION | D9: =SUMIF('Balance N Retraitée'!A:A,"2111*",'Balance N Retraitée'!G:G)-SUMIF('Balance N Retraitée'!A:A,"2111*",'Balance N Retraitée'!H:H) -> 5000
B10: 2112 | C10: FRAIS PREALABLES AU DEMARRAGE | D10: =SUMIF('Balance N Retraitée'!A:A,"2112*",'Balance N Retraitée'!G:G)-SUMIF('Balance N Retraitée'!A:A,"2112*",'Balance N Retraitée'!H:H) -> 0
B11: 2113 | C11: FRAIS D'AUGMENTATION DE CAPITAL | D11: =SUMIF('Balance N Retraitée'!A:A,"2113*",'Balance N Retraitée'!G:G)-SUMIF('Balance N Retraitée'!A:A,"2113*",'Balance N Retraitée'!H:H) -> 0
B12: 2114 | C12: FRAIS SUR OPERATIONS DE FUSIONS, SCISSIONS ET TRANSFORMATIONS | D12: =SUMIF('Balance N Retraitée'!A:A,"2114*",'Balance N Retraitée'!G:G)-SUMIF('Balance N Retraitée'!A:A,"2114*",'Balance N Retraitée'!H:H) -> 0
B13: 2116 | C13: FRAIS DE PROSPECTION | D13: =SUMIF('Balance N Retraitée'!A:A,"2116*",'Balance N Retraitée'!G:G)-SUMIF('Balance N Retraitée'!A:A,"2116*",'Balance N Retraitée'!H:H) -> 0
B14: 2117 | C14: FRAIS DE PUBLICITE | D14: =SUMIF('Balance N Retraitée'!A:A,"2117*",'Balance N Retraitée'!G:G)-SUMIF('Balance N Retraitée'!A:A,"2117*",'Balance N Retraitée'!H:H) -> 0
B15: 2118 | C15: AUTRES FRAIS PRELIMINAIRES | D15: =SUMIF('Balance N Retraitée'!A:A,"2118*",'Balance N Retraitée'!G:G)-SUMIF('Balance N Retraitée'!A:A,"2118*",'Balance N Retraitée'!H:H) -> 0
B16: 2121 | C16: FRAIS D'ACQUISITION DES IMMOBILISATIONS | D16: =SUMIF('Balance N Retraitée'!A:A,"2121*",'Balance N Retraitée'!G:G)-SUMIF('Balance N Retraitée'!A:A,"2121*",'Balance N Retraitée'!H:H) -> 0
B17: 2125 | C17: FRAIS D'EMISSION DES EMPRUNTS | D17: =SUMIF('Balance N Retraitée'!A:A,"2125*",'Balance N Retraitée'!G:G)-SUMIF('Balance N Retraitée'!A:A,"2125*",'Balance N Retraitée'!H:H) -> 0
B18: 2128 | C18: AUTRES CHARGES A REPARTIR | D18: =SUMIF('Balance N Retraitée'!A:A,"2128*",'Balance N Retraitée'!G:G)-SUMIF('Balance N Retraitée'!A:A,"2128*",'Balance N Retraitée'!H:H) -> 0
B19: 2130 | C19: PRIME DE REMBOURSEMENT DES OBLIGATIONS | D19: =SUMIF('Balance N Retraitée'!A:A,"2130*",'Balance N Retraitée'!G:G)-SUMIF('Balance N Retraitée'!A:A,"2130*",'Balance N Retraitée'!H:H) -> 0
C30: TOTAL | D30: =SUM(D8:D29) -> 5000

Sheet B6-CREANCES-01
A2: B 6 - TABLEAU DES CREANCES
G3: =+'T8 B2 BIS'!D4 -> Exercice clos le : | I3: ='T5 ESG'!$G$3 -> 31/12/2022
A4: CREANCES | B4: TOTAL | C4: ANALYSE PAR ECHEANCE | F4: AUTRES ANALYSES
C5: Plus d'un an | D5: Moins d'un an | E5: Echus et non recouvrés | F5: Montant en devise | G5: Montants l'Etat et organismes publics | H5: Montants sur les entreprises liées | I5: Montants représentés par des effets
A6: DE L'ACTIF IMMOBILISE | B6: =SUM(B8:B9) -> 0 | C6: =SUM(C8:C9) -> 0 | D6: =SUM(D8:D9) -> 0 | E6: =SUM(E8:E9) -> 0 | F6: =SUM(F8:F9) -> 0 | G6: =SUM(G8:G9) -> 0 | H6: =SUM(H8:H9) -> 0 | I6: =SUM(I8:I9) -> 0
A8: Prêt immobilisés | B8: =SUMIF('Balance N Retraitée'!A:A,"241*",'Balance N Retraitée'!G:G)-SUMIF('Balance N Retraitée'!A:A,"241*",'Balance N Retraitée'!H:H) -> 0 | C8: =B8-D8-E8 -> 0
A9: Autres créances financières | B9: =SUMIF('Balance N Retraitée'!A:A,"248*",'Balance N Retraitée'!G:G)-SUMIF('Balance N Retraitée'!A:A,"248*",'Balance N Retraitée'!H:H) -> 0 | C9: =B9-D9-E9 -> 0
A11: DE L'ACTIF CIRCULANT | B11: =SUM(B14:B19) -> 308800.72 | C11: =SUM(C14:C19) -> 0 | D11: =SUM(D14:D19) -> 308800.72 | E11: =SUM(E14:E19) -> 0 | F11: =SUM(F14:F19) -> 0 | G11: =SUM(G14:G19) -> 20800.72 | H11: =SUM(H14:H19) -> 0 | I11: =SUM(I14:I19) -> 0
A13: Fournisseurs débiteurs, avances et acomptes | B13: =SUMIF('Balance N Retraitée'!A:A,"341*",'Balance N Retraitée'!G:G)-SUMIF('Balance N Retraitée'!A:A,"341*",'Balance N Retraitée'!H:H) -> 0 | D13: =B13-C13-E13 -> 0
A14: Clients et comptes rattachés | B14: =SUMIF('Balance N Retraitée'!A:A,"342*",'Balance N Retraitée'!G:G)-SUMIF('Balance N Retraitée'!A:A,"342*",'Balance N Retraitée'!H:H) -> 288000 | D14: =B14-C14-E14 -> 288000 | I14: =SUMIF('Balance N Retraitée'!A:A,"3425*",'Balance N Retraitée'!G:G)-SUMIF('Balance N Retraitée'!A:A,"3425*",'Balance N Retraitée'!H:H) -> 0
A15: Personnel | B15: =SUMIF('Balance N Retraitée'!A:A,"343*",'Balance N Retraitée'!G:G)-SUMIF('Balance N Retraitée'!A:A,"343*",'Balance N Retraitée'!H:H) -> 0 | D15: =B15-C15-E15 -> 0
A16: Etat | B16: =SUMIF('Balance N Retraitée'!A:A,"345*",'Balance N Retraitée'!G:G)-SUMIF('Balance N Retraitée'!A:A,"345*",'Balance N Retraitée'!H:H) -> 20800.72 | D16: =B16-C16-E16 -> 20800.72 | G16: =+D16 -> 20800.72
A17: Comptes d'associés | B17: =SUMIF('Balance N Retraitée'!A:A,"346*",'Balance N Retraitée'!G:G)-SUMIF('Balance N Retraitée'!A:A,"346*",'Balance N Retraitée'!H:H) -> 0 | D17: =B17-C17-E17 -> 0
A18: Autres débiteurs | B18: =SUMIF('Balance N Retraitée'!A:A,"348*",'Balance N Retraitée'!G:G)-SUMIF('Balance N Retraitée'!A:A,"348*",'Balance N Retraitée'!H:H) -> 0 | D18: =B18-C18-E18 -> 0
A19: Comptes de régularisations - Actif | B19: =SUMIF('Balance N Retraitée'!A:A,"349*",'Balance N Retraitée'!G:G)-SUMIF('Balance N Retraitée'!A:A,"349*",'Balance N Retraitée'!H:H) -> 0 | D19: =B19-C19-E19 -> 0

Sheet B7-dettes
A1: ONDUMAR
A4: B 7 - TABLEAU DES DETTES
G5: =+'T8 B2 BIS'!D4 -> Exercice clos le : | I5: ='T5 ESG'!$G$3 -> 31/12/2022
A6: DETTES | B6: TOTAL | C6: ANALYSE PAR ECHEANCE | F6: AUTRES ANALYSES
C7: Plus d'un an | D7: Moins d'un an | E7: Echus et non recouvrés | F7: Montant en devise | G7: Montants l'Etat et organismes publics | H7: Montants sur les entreprises liées | I7: Montants représentés par des effets
A8: DETTES DE FINANCEMENT | B8: =SUM(B9:B10) -> 1005415.6 | C8: =SUM(C9:C10) -> 0 | D8: =SUM(D9:D10) -> 1005415.6 | E8: =SUM(E9:E10) -> 0 | F8: =SUM(F9:F10) -> 0 | G8: =SUM(G9:G10) -> 0 | H8: =SUM(H9:H10) -> 0 | I8: =SUM(I9:I10) -> 0
A9: Emprunts obligataires | B9: =SUMIF('Balance N Retraitée'!A:A,"141*",'Balance N Retraitée'!H:H)-SUMIF('Balance N Retraitée'!A:A,"141*",'Balance N Retraitée'!G:G) -> 0 | D9: =+B9-C9-E9 -> 0
A10: Autres dettes de financement | B10: =SUMIF('Balance N Retraitée'!A:A,"148*",'Balance N Retraitée'!H:H)-SUMIF('Balance N Retraitée'!A:A,"148*",'Balance N Retraitée'!G:G) -> 1005415.6 | D10: =+B10-C10-E10 -> 1005415.6 | F10: 0
A12: DU PASSIF CIRCULANT | B12: =SUM(B13:B20) -> 621333.33 | C12: =SUM(C13:C20) -> 0 | D12: =SUM(D13:D20) -> 621333.33 | E12: =SUM(E13:E20) -> 0 | F12: =SUM(F13:F21) -> 0 | G12: =SUM(G13:G21) -> 53797.84 | H12: =SUM(H13:H21) -> 0 | I12: =SUM(I13:I21) -> 0
A13: Fournisseurs et comptes rattachés | B13: =SUMIF('Balance N Retraitée'!A:A,"441*",'Balance N Retraitée'!H:H)-SUMIF('Balance N Retraitée'!A:A,"441*",'Balance N Retraitée'!G:G) -> 7573.2 | D13: =+B13-C13-E13 -> 7573.2 | F13: 0 | I13: =SUMIF('Balance N Retraitée'!A:A,"4415*",'Balance N Retraitée'!H:H)-SUMIF('Balance N Retraitée'!A:A,"4415*",'Balance N Retraitée'!G:G) -> 0
A14: Clients créditeurs , avances et acomptes | B14: =SUMIF('Balance N Retraitée'!A:A,"442*",'Balance N Retraitée'!H:H)-SUMIF('Balance N Retraitée'!A:A,"442*",'Balance N Retraitée'!G:G) -> 0 | D14: =+B14-C14-E14 -> 0 | F14: 0
A15: Personnel | B15: =SUMIF('Balance N Retraitée'!A:A,"443*",'Balance N Retraitée'!H:H)-SUMIF('Balance N Retraitée'!A:A,"443*",'Balance N Retraitée'!G:G) -> 0 | D15: =+B15-C15-E15 -> 0 | F15: 0
A16: Organismes sociaux | B16: =SUMIF('Balance N Retraitée'!A:A,"444*",'Balance N Retraitée'!H:H)-SUMIF('Balance N Retraitée'!A:A,"444*",'Balance N Retraitée'!G:G) -> 796.02 | D16: =+B16-C16-E16 -> 796.02 | F16: 0 | G16: =+D16 -> 796.02
A17: Etat | B17: =SUMIF('Balance N Retraitée'!A:A,"445*",'Balance N Retraitée'!H:H)-SUMIF('Balance N Retraitée'!A:A,"445*",'Balance N Retraitée'!G:G) -> 53001.82 | D17: =+B17-C17-E17 -> 53001.82 | F17: 0 | G17: =+D17 -> 53001.82
A18: Comptes d'associés | B18: =SUMIF('Balance N Retraitée'!A:A,"446*",'Balance N Retraitée'!H:H)-SUMIF('Balance N Retraitée'!A:A,"446*",'Balance N Retraitée'!G:G) -> 559962.29 | D18: =+B18-C18-E18 -> 559962.29 | F18: 0
